Workbook

Sheet Vlookup
K17: Źródło: | L17: https://www.kaggle.com/yasserh/song-popularity-dataset?select=song_data.csv
A18: Funkcje VLOOKUP i MATCH | K18: Dane do zadań z karty | AA18: Zadanie 1
A19: Funkcja VLOOKUP (WYSZUKAJ.PIONOWO) to kręgosłup Excela. Wraz z MATCH (PODAJ.POZYCJĘ) tworzą potęzną parę. | K19: song_name | L19: song_popularity | M19: song_duration_ms | N19: acousticness | O19: danceability | P19: energy | Q19: instrumentalness | R19: key | S19: liveness | T19: loudness | U19: audio_mode | V19: speechiness | W19: tempo | X19: time_signature | Y19: audio_valence | AA19: Użyj funkcji VLOOKUP, aby wyszukać wartości z kolumw nagłówkach
K20: Boulevard of Broken Dreams | L20: 73 | M20: 262333 | N20: 0.00552 | O20: 0.496 | P20: 0.682 | Q20: 2.94e-05 | R20: 8 | S20: 0.0589 | T20: -4.095 | U20: 1 | V20: 0.0294 | W20: 167.06 | X20: 4 | Y20: 0.474
K21: In The End | L21: 66 | M21: 216933 | N21: 0.0103 | O21: 0.542 | P21: 0.853 | Q21: 0 | R21: 3 | S21: 0.108 | T21: -6.407 | U21: 0 | V21: 0.0498 | W21: 105.256 | X21: 4 | Y21: 0.37
A22: VLOOKUP: | K22: Seven Nation Army | L22: 76 | M22: 231733 | N22: 0.00817 | O22: 0.737 | P22: 0.463 | Q22: 0.447 | R22: 0 | S22: 0.255 | T22: -7.828 | U22: 1 | V22: 0.0792 | W22: 123.881 | X22: 4 | Y22: 0.324 | AA22: Nr kolumny:
K23: By The Way | L23: 74 | M23: 216933 | N23: 0.0264 | O23: 0.451 | P23: 0.97 | Q23: 0.00355 | R23: 0 | S23: 0.102 | T23: -4.938 | U23: 1 | V23: 0.107 | W23: 122.444 | X23: 4 | Y23: 0.198 | AA23: Piosenka | AB23: song_popularity | AC23: danceability | AD23: tempo
B24: =VLOOKUP(WARTOŚĆ, ZAKRES,Nr. Kolumny, TYP.DOPASOWANIA) | K24: How You Remind Me | L24: 56 | M24: 223826 | N24: 0.000954 | O24: 0.447 | P24: 0.766 | Q24: 0 | R24: 10 | S24: 0.113 | T24: -5.065 | U24: 1 | V24: 0.0313 | W24: 172.011 | X24: 4 | Y24: 0.574 | AA24: Chop Suey!
K25: Bring Me To Life | L25: 80 | M25: 235893 | N25: 0.00895 | O25: 0.316 | P25: 0.945 | Q25: 1.85e-06 | R25: 4 | S25: 0.396 | T25: -3.169 | U25: 0 | V25: 0.124 | W25: 189.931 | X25: 4 | Y25: 0.32 | AA25: What's My Age Again?
A26: Gdzie: | K26: Last Resort | L26: 81 | M26: 199893 | N26: 0.000504 | O26: 0.581 | P26: 0.887 | Q26: 0.00111 | R26: 4 | S26: 0.268 | T26: -3.659 | U26: 0 | V26: 0.0624 | W26: 90.578 | X26: 4 | Y26: 0.724 | AA26: Numb
K27: Are You Gonna Be My Girl | L27: 76 | M27: 213800 | N27: 0.00148 | O27: 0.613 | P27: 0.953 | Q27: 0.000582 | R27: 2 | S27: 0.152 | T27: -3.435 | U27: 1 | V27: 0.0855 | W27: 105.046 | X27: 4 | Y27: 0.537
B28: WARTOŚĆ | C28: - | D28: Poszukiwana przez nas wartość w 1 kolumnie tablicy | K28: Mr. Brightside | L28: 80 | M28: 222586 | N28: 0.00108 | O28: 0.33 | P28: 0.936 | Q28: 0 | R28: 1 | S28: 0.0926 | T28: -3.66 | U28: 1 | V28: 0.0917 | W28: 148.112 | X28: 4 | Y28: 0.234
K29: Sex on Fire | L29: 81 | M29: 203346 | N29: 0.00172 | O29: 0.542 | P29: 0.905 | Q29: 0.0104 | R29: 9 | S29: 0.136 | T29: -5.653 | U29: 1 | V29: 0.054 | W29: 153.398 | X29: 4 | Y29: 0.374 | AA29: Zadanie 2
B30: ZAKRES | C30: - | D30: Wybrana przez nas tablica | K30: The Middle | L30: 78 | M30: 168253 | N30: 0.0424 | O30: 0.629 | P30: 0.897 | Q30: 0 | R30: 2 | S30: 0.263 | T30: -3.401 | U30: 1 | V30: 0.0483 | W30: 161.944 | X30: 4 | Y30: 0.93 | AA30: Użyf unkcji MATCH (PODAJ.POZYCJE), aby znaleźć w której kolumnie są następujące dane:
K31: Numb | L31: 63 | M31: 185586 | N31: 0.0046 | O31: 0.496 | P31: 0.863 | Q31: 0 | R31: 9 | S31: 0.639 | T31: -4.153 | U31: 1 | V31: 0.0381 | W31: 110.018 | X31: 4 | Y31: 0.243
B32: Nr. Kolumny | C32: - | D32: Kolumna w naszej wybranej tablicy, którą mamy zwrócić | K32: Smooth Criminal | L32: 75 | M32: 209266 | N32: 0.00434 | O32: 0.647 | P32: 0.964 | Q32: 0.0036 | R32: 9 | S32: 0.15 | T32: -4.225 | U32: 0 | V32: 0.06 | W32: 126.942 | X32: 4 | Y32: 0.875
K33: Can't Stop | L33: 81 | M33: 269000 | N33: 0.0179 | O33: 0.618 | P33: 0.938 | Q33: 0 | R33: 9 | S33: 0.167 | T33: -3.442 | U33: 1 | V33: 0.0456 | W33: 91.455 | X33: 4 | Y33: 0.875 | AA33: Zmienna | AB33: audio_mode | AC33: energy | AD33: instrumentalness
B34: TYP.DOPASOWANIA | C34: - | D34: FAŁSZ dopasowuje dokładnie wybrany tekst PRAWDA - najbliższy pasujący (może dać dziwny wynik przy liczbach) | K34: Chop Suey! | L34: 69 | M34: 210240 | N34: 0.000353 | O34: 0.42 | P34: 0.929 | Q34: 0.000747 | R34: 7 | S34: 0.122 | T34: -3.899 | U34: 0 | V34: 0.121 | W34: 127.204 | X34: 4 | Y34: 0.3 | AA34: Nr Kolumny
K35: Take Me Out | L35: 77 | M35: 237026 | N35: 0.000423 | O35: 0.278 | P35: 0.676 | Q35: 0.000899 | R35: 9 | S35: 0.136 | T35: -8.821 | U35: 1 | V35: 0.0371 | W35: 104.545 | X35: 4 | Y35: 0.494
A36: MATCH: | K36: I Miss You | L36: 71 | M36: 227240 | N36: 0.00136 | O36: 0.659 | P36: 0.778 | Q36: 6.79e-06 | R36: 11 | S36: 0.0841 | T36: -6.423 | U36: 1 | V36: 0.0379 | W36: 110.022 | X36: 4 | Y36: 0.623
K37: Best of You | L37: 62 | M37: 256600 | N37: 0.00701 | O37: 0.37 | P37: 0.944 | Q37: 2.9e-06 | R37: 1 | S37: 0.135 | T37: -4.979 | U37: 0 | V37: 0.0767 | W37: 130.315 | X37: 4 | Y37: 0.345
B38: =MATCH(WARTOŚĆ, ZAKRES, TYP.DOPASOWANIA) | K38: I Write Sins Not Tragedies | L38: 77 | M38: 187613 | N38: 0.0938 | O38: 0.567 | P38: 0.795 | Q38: 0 | R38: 9 | S38: 0.114 | T38: -4.985 | U38: 0 | V38: 0.134 | W38: 170.06 | X38: 4 | Y38: 0.635 | AA38: Zadanie 3
K39: Kryptonite | L39: 79 | M39: 233933 | N39: 0.00664 | O39: 0.545 | P39: 0.865 | Q39: 1.12e-05 | R39: 11 | S39: 0.168 | T39: -5.708 | U39: 0 | V39: 0.0286 | W39: 99.01 | X39: 4 | Y39: 0.543 | AA39: Połączmy umiejętności z zadań 1 i 2, aby rozwiązać tabelę bez wpisywania numerów kolumn
B40: WARTOŚĆ | C40: - | D40: Poszukiwana przez nas wartość w 1 kolumnie tablic | K40: The Kill (Bury Me) | L40: 69 | M40: 231533 | N40: 0.0014 | O40: 0.309 | P40: 0.912 | Q40: 0.000271 | R40: 4 | S40: 0.582 | T40: -3.881 | U40: 0 | V40: 0.0646 | W40: 183.035 | X40: 3 | Y40: 0.302
K41: Use Somebody | L41: 79 | M41: 230760 | N41: 0.00552 | O41: 0.276 | P41: 0.715 | Q41: 0.000417 | R41: 0 | S41: 0.201 | T41: -5.356 | U41: 1 | V41: 0.0432 | W41: 137.028 | X41: 4 | Y41: 0.173
B42: ZAKRES | C42: - | D42: Wybrana przez nas tablica | K42: No One Knows | L42: 13 | M42: 255066 | N42: 0.0137 | O42: 0.518 | P42: 0.538 | Q42: 0.000398 | R42: 0 | S42: 0.141 | T42: -5.818 | U42: 1 | V42: 0.0486 | W42: 170.953 | X42: 4 | Y42: 0.687
K43: Jerk It Out | L43: 62 | M43: 195666 | N43: 0.0171 | O43: 0.58 | P43: 0.981 | Q43: 1.07e-05 | R43: 8 | S43: 0.386 | T43: -2.603 | U43: 0 | V43: 0.06 | W43: 134.007 | X43: 4 | Y43: 0.861 | AA43: Piosenka | AB43: song_popularity | AC43: danceability | AD43: tempo
B44: TYP.DOPASOWANIA | C44: - | D44: 1 - największa wartość poniżej szukanej wartości (wymaga posortowania) 0 - dokładne wybieranie szukanej wartości -1 - najmniejsza wartość powyżej szukanej wartości (wymaga posortowania) | K44: Uprising | L44: 77 | M44: 304840 | N44: 0.000202 | O44: 0.602 | P44: 0.905 | Q44: 0.064 | R44: 2 | S44: 0.117 | T44: -4.046 | U44: 1 | V44: 0.0775 | W44: 128.019 | X44: 4 | Y44: 0.411 | AA44: Chop Suey!
K45: Hey There Delilah | L45: 79 | M45: 232533 | N45: 0.872 | O45: 0.657 | P45: 0.291 | Q45: 0 | R45: 2 | S45: 0.114 | T45: -10.572 | U45: 1 | V45: 0.0293 | W45: 103.973 | X45: 4 | Y45: 0.298 | AA45: What's My Age Again?
K46: Blurry | L46: 28 | M46: 303920 | N46: 0.0102 | O46: 0.44 | P46: 0.932 | Q46: 0 | R46: 3 | S46: 0.142 | T46: -4.488 | U46: 0 | V46: 0.0584 | W46: 157.438 | X46: 4 | Y46: 0.495 | AA46: Numb
K47: American Idiot | L47: 78 | M47: 176346 | N47: 2.64e-05 | O47: 0.38 | P47: 0.988 | Q47: 7.86e-05 | R47: 1 | S47: 0.368 | T47: -2.042 | U47: 1 | V47: 0.0639 | W47: 186.113 | X47: 4 | Y47: 0.769
A48: Wykonamy 3 zadania, które pokażą nam jej funkcjonalność | K48: Welcome to the Black Parade | L48: 77 | M48: 311106 | N48: 0.000289 | O48: 0.217 | P48: 0.905 | Q48: 0.00011 | R48: 2 | S48: 0.222 | T48: -4.103 | U48: 1 | V48: 0.0752 | W48: 96.95 | X48: 4 | Y48: 0.236
K49: Gives You Hell | L49: 71 | M49: 213106 | N49: 0.0156 | O49: 0.714 | P49: 0.725 | Q49: 0 | R49: 4 | S49: 0.0726 | T49: -6.411 | U49: 1 | V49: 0.0402 | W49: 99.988 | X49: 4 | Y49: 0.59
K50: All My Life | L50: 11 | M50: 262733 | N50: 0.000194 | O50: 0.582 | P50: 0.597 | Q50: 0.000273 | R50: 5 | S50: 0.517 | T50: -5.671 | U50: 1 | V50: 0.0512 | W50: 167.738 | X50: 4 | Y50: 0.674
K51: Like a Stone | L51: 77 | M51: 293960 | N51: 0.00797 | O51: 0.614 | P51: 0.568 | Q51: 0 | R51: 7 | S51: 0.0997 | T51: -5.477 | U51: 0 | V51: 0.0276 | W51: 107.849 | X51: 4 | Y51: 0.516
K52: It's Been Awhile | L52: 65 | M52: 264706 | N52: 0.00189 | O52: 0.509 | P52: 0.774 | Q52: 0.000549 | R52: 6 | S52: 0.143 | T52: -4.054 | U52: 1 | V52: 0.0338 | W52: 116.529 | X52: 4 | Y52: 0.0824
K53: I Hate Everything About You | L53: 75 | M53: 231480 | N53: 0.00461 | O53: 0.498 | P53: 0.83 | Q53: 0 | R53: 6 | S53: 0.139 | T53: -5.157 | U53: 0 | V53: 0.0421 | W53: 89.342 | X53: 4 | Y53: 0.453
K54: Rollin' (Air Raid Vehicle) | L54: 74 | M54: 213760 | N54: 0.00506 | O54: 0.599 | P54: 0.932 | Q54: 0 | R54: 9 | S54: 0.269 | T54: -3.328 | U54: 1 | V54: 0.18 | W54: 96.234 | X54: 4 | Y54: 0.692
K55: Fat Lip | L55: 74 | M55: 178266 | N55: 0.000618 | O55: 0.574 | P55: 0.911 | Q55: 0 | R55: 9 | S55: 0.0769 | T55: -5.176 | U55: 1 | V55: 0.0715 | W55: 98.075 | X55: 4 | Y55: 0.573
K56: The Pretender | L56: 11 | M56: 269373 | N56: 0.000917 | O56: 0.433 | P56: 0.959 | Q56: 0 | R56: 9 | S56: 0.028 | T56: -4.04 | U56: 1 | V56: 0.0431 | W56: 172.984 | X56: 4 | Y56: 0.365
K57: Savior | L57: 73 | M57: 242280 | N57: 0.00164 | O57: 0.549 | P57: 0.93 | Q57: 6.67e-05 | R57: 5 | S57: 0.39 | T57: -3.468 | U57: 0 | V57: 0.0487 | W57: 112.447 | X57: 4 | Y57: 0.526
K58: Bodies | L58: 74 | M58: 201960 | N58: 0.00347 | O58: 0.656 | P58: 0.932 | Q58: 0.00147 | R58: 4 | S58: 0.144 | T58: -3.405 | U58: 0 | V58: 0.0708 | W58: 130.936 | X58: 4 | Y58: 0.544
K59: Sugar, We're Goin Down | L59: 79 | M59: 229093 | N59: 0.00898 | O59: 0.499 | P59: 0.824 | Q59: 0 | R59: 7 | S59: 0.163 | T59: -4.741 | U59: 1 | V59: 0.0794 | W59: 161.977 | X59: 4 | Y59: 0.699
K60: Last Nite | L60: 70 | M60: 193373 | N60: 0.0223 | O60: 0.624 | P60: 0.899 | Q60: 0.000155 | R60: 0 | S60: 0.0975 | T60: -5.71 | U60: 1 | V60: 0.0295 | W60: 104.055 | X60: 4 | Y60: 0.797
... K650: The One That You Love | L650: 62 | M650: 259000 | N650: 0.728 | O650: 0.396 | P650: 0.479 | Q650: 9.51e-06 | R650: 5 | S650: 0.102 | T650: -8.072 | U650: 1 | V650: 0.0268 | W650: 109.973 | X650: 4 | Y650: 0.184
K651: TRUE | L651: 74 | M651: 328293 | N651: 0.506 | O651: 0.744 | P651: 0.545 | Q651: 0.0977 | R651: 0 | S651: 0.0649 | T651: -9.361 | U651: 1 | V651: 0.0297 | W651: 97.409 | X651: 4 | Y651: 0.346
K652: The Flame | L652: 64 | M652: 338800 | N652: 0.513 | O652: 0.629 | P652: 0.581 | Q652: 2.06e-06 | R652: 4 | S652: 0.0755 | T652: -11.856 | U652: 1 | V652: 0.027 | W652: 97.074 | X652: 4 | Y652: 0.359
K653: Nothing's Gonna Stop Us Now | L653: 75 | M653: 270333 | N653: 0.0298 | O653: 0.643 | P653: 0.801 | Q653: 0 | R653: 6 | S653: 0.0719 | T653: -4.921 | U653: 1 | V653: 0.0228 | W653: 95.988 | X653: 4 | Y653: 0.534
K654: Say You, Say Me | L654: 32 | M654: 241066 | N654: 0.355 | O654: 0.636 | P654: 0.405 | Q654: 0 | R654: 8 | S654: 0.081 | T654: -11.113 | U654: 1 | V654: 0.0287 | W654: 128.068 | X654: 4 | Y654: 0.257
K655: Straight From The Heart | L655: 55 | M655: 211933 | N655: 0.0814 | O655: 0.578 | P655: 0.213 | Q655: 0 | R655: 0 | S655: 0.116 | T655: -18.504 | U655: 1 | V655: 0.0277 | W655: 84.778 | X655: 4 | Y655: 0.317
K656: Take On Me | L656: 85 | M656: 225280 | N656: 0.018 | O656: 0.573 | P656: 0.902 | Q656: 0.00125 | R656: 6 | S656: 0.0928 | T656: -7.638 | U656: 0 | V656: 0.054 | W656: 84.412 | X656: 4 | Y656: 0.876
K657: Waiting For A Girl Like You | L657: 69 | M657: 292066 | N657: 0.31 | O657: 0.33 | P657: 0.469 | Q657: 2.3e-06 | R657: 10 | S657: 0.0402 | T657: -9.286 | U657: 0 | V657: 0.0335 | W657: 201.327 | X657: 4 | Y657: 0.433
K658: Careless Whisper | L658: 13 | M658: 300093 | N658: 0.144 | O658: 0.575 | P658: 0.634 | Q658: 1.68e-06 | R658: 2 | S658: 0.314 | T658: -8.822 | U658: 0 | V658: 0.0348 | W658: 153.217 | X658: 4 | Y658: 0.79
K659: Woman in Love | L659: 67 | M659: 231840 | N659: 0.248 | O659: 0.469 | P659: 0.278 | Q659: 0.000126 | R659: 3 | S659: 0.133 | T659: -16.311 | U659: 0 | V659: 0.028 | W659: 169.735 | X659: 4 | Y659: 0.331
K660: Do You Remember? - 2016 Remastered | L660: 60 | M660: 275986 | N660: 0.114 | O660: 0.677 | P660: 0.509 | Q660: 0.0134 | R660: 5 | S660: 0.0659 | T660: -7.472 | U660: 1 | V660: 0.0252 | W660: 93.042 | X660: 4 | Y660: 0.525
K661: Listen To Your Heart | L661: 73 | M661: 328093 | N661: 0.108 | O661: 0.539 | P661: 0.583 | Q661: 0 | R661: 1 | S661: 0.111 | T661: -4.935 | U661: 0 | V661: 0.0275 | W661: 86.063 | X661: 4 | Y661: 0.337
K662: Heaven | L662: 14 | M662: 243666 | N662: 0.0596 | O662: 0.34 | P662: 0.412 | Q662: 0 | R662: 9 | S662: 0.117 | T662: -13.727 | U662: 0 | V662: 0.0268 | W662: 69.857 | X662: 4 | Y662: 0.402
K663: Glory Of Love | L663: 72 | M663: 258120 | N663: 0.0778 | O663: 0.518 | P663: 0.585 | Q663: 2.43e-06 | R663: 5 | S663: 0.31 | T663: -8.485 | U663: 1 | V663: 0.0279 | W663: 144.998 | X663: 4 | Y663: 0.312
... K959: Loser | L959: 70 | M959: 235000 | N959: 0.0341 | O959: 0.66 | P959: 0.627 | Q959: 9.64e-05 | R959: 6 | S959: 0.385 | T959: -10.397 | U959: 0 | V959: 0.124 | W959: 85.44 | X959: 4 | Y959: 0.789
K960: 1979 | L960: 19 | M960: 265893 | N960: 0.0218 | O960: 0.768 | P960: 0.744 | Q960: 0.712 | R960: 8 | S960: 0.063 | T960: -11.267 | U960: 1 | V960: 0.0338 | W960: 127.036 | X960: 4 | Y960: 0.963
K961: Losing My Religion | L961: 28 | M961: 267733 | N961: 0.0767 | O961: 0.672 | P961: 0.841 | Q961: 0 | R961: 9 | S961: 0.135 | T961: -5.992 | U961: 0 | V961: 0.0285 | W961: 125.437 | X961: 4 | Y961: 0.82
K962: Push | L962: 72 | M962: 238666 | N962: 0.0067 | O962: 0.42 | P962: 0.672 | Q962: 0 | R962: 6 | S962: 0.108 | T962: -7.902 | U962: 1 | V962: 0.027 | W962: 168.019 | X962: 4 | Y962: 0.476
K963: When I Come Around | L963: 74 | M963: 178000 | N963: 0.0175 | O963: 0.531 | P963: 0.909 | Q963: 0 | R963: 11 | S963: 0.231 | T963: -4.236 | U963: 1 | V963: 0.034 | W963: 97.546 | X963: 4 | Y963: 0.814
K964: What It's Like | L964: 17 | M964: 303133 | N964: 0.0904 | O964: 0.678 | P964: 0.556 | Q964: 0.0334 | R964: 0 | S964: 0.0866 | T964: -7.423 | U964: 1 | V964: 0.0281 | W964: 85.158 | X964: 4 | Y964: 0.405
K965: Plush - Acoustic | L965: 63 | M965: 230293 | N965: 0.712 | O965: 0.644 | P965: 0.363 | Q965: 0 | R965: 5 | S965: 0.659 | T965: -11.019 | U965: 0 | V965: 0.0397 | W965: 133.396 | X965: 4 | Y965: 0.303
K966: Everlong - Acoustic Version | L966: 70 | M966: 250906 | N966: 0.909 | O966: 0.643 | P966: 0.344 | Q966: 0.0112 | R966: 2 | S966: 0.106 | T966: -11.342 | U966: 1 | V966: 0.0349 | W966: 144.171 | X966: 4 | Y966: 0.547
K967: Name | L967: 66 | M967: 270000 | N967: 0.0691 | O967: 0.464 | P967: 0.701 | Q967: 0.00182 | R967: 9 | S967: 0.0766 | T967: -5.943 | U967: 1 | V967: 0.0341 | W967: 73.97 | X967: 4 | Y967: 0.407
K968: A Long December | L968: 59 | M968: 295066 | N968: 0.469 | O968: 0.398 | P968: 0.591 | Q968: 0.000588 | R968: 5 | S968: 0.337 | T968: -6.925 | U968: 1 | V968: 0.0298 | W968: 142.336 | X968: 4 | Y968: 0.425
K969: Kiss From A Rose - Acoustic Version | L969: 56 | M969: 324066 | N969: 0.743 | O969: 0.659 | P969: 0.407 | Q969: 0 | R969: 4 | S969: 0.0784 | T969: -9.718 | U969: 0 | V969: 0.0353 | W969: 119.321 | X969: 3 | Y969: 0.269
K970: More Than Words | L970: 69 | M970: 334106 | N970: 0.468 | O970: 0.615 | P970: 0.129 | Q970: 0 | R970: 6 | S970: 0.114 | T970: -14.892 | U970: 1 | V970: 0.0286 | W970: 91.769 | X970: 4 | Y970: 0.249
K971: Head Over Feet - Live/Unplugged Version | L971: 54 | M971: 262560 | N971: 0.0688 | O971: 0.421 | P971: 0.734 | Q971: 0 | R971: 0 | S971: 0.974 | T971: -8.692 | U971: 1 | V971: 0.0511 | W971: 168.772 | X971: 4 | Y971: 0.34
K972: All The Small Things | L972: 80 | M972: 168000 | N972: 0.0122 | O972: 0.439 | P972: 0.891 | Q972: 0 | R972: 0 | S972: 0.547 | T972: -4.764 | U972: 1 | V972: 0.057 | W972: 148.599 | X972: 4 | Y972: 0.695
... K1187: Four Leaf Clover - Edit | L1187: 62 | M1187: 191726 | N1187: 0.00461 | O1187: 0.46 | P1187: 0.965 | Q1187: 7.02e-05 | R1187: 7 | S1187: 0.276 | T1187: -3.011 | U1187: 1 | V1187: 0.0555 | W1187: 147.278 | X1187: 4 | Y1187: 0.81
K1188: 22 | L1188: 32 | M1188: 232120 | N1188: 0.00274 | O1188: 0.662 | P1188: 0.736 | Q1188: 0.000844 | R1188: 7 | S1188: 0.0464 | T1188: -6.511 | U1188: 1 | V1188: 0.0374 | W1188: 104.003 | X1188: 4 | Y1188: 0.674
K1189: Back Again | L1189: 66 | M1189: 176960 | N1189: 0.00205 | O1189: 0.634 | P1189: 0.865 | Q1189: 1.25e-06 | R1189: 9 | S1189: 0.307 | T1189: -4.363 | U1189: 0 | V1189: 0.0367 | W1189: 112.021 | X1189: 4 | Y1189: 0.879
K1190: All This Love | L1190: 74 | M1190: 193597 | N1190: 0.168 | O1190: 0.621 | P1190: 0.524 | Q1190: 0 | R1190: 5 | S1190: 0.0925 | T1190: -7.056 | U1190: 1 | V1190: 0.0248 | W1190: 97.456 | X1190: 3 | Y1190: 0.434
K1191: L.I.F.E.G.O.E.S.O.N. | L1191: 19 | M1191: 226946 | N1191: 0.205 | O1191: 0.608 | P1191: 0.745 | Q1191: 0 | R1191: 4 | S1191: 0.342 | T1191: -5.82 | U1191: 1 | V1191: 0.0354 | W1191: 82.003 | X1191: 4 | Y1191: 0.595
K1192: Thursday | L1192: 73 | M1192: 216239 | N1192: 0.452 | O1192: 0.603 | P1192: 0.554 | Q1192: 0 | R1192: 2 | S1192: 0.0545 | T1192: -4.381 | U1192: 1 | V1192: 0.0646 | W1192: 111.989 | X1192: 4 | Y1192: 0.354
K1193: The Way It Is | L1193: 70 | M1193: 297853 | N1193: 0.607 | O1193: 0.582 | P1193: 0.689 | Q1193: 0.0571 | R1193: 7 | S1193: 0.145 | T1193: -12.203 | U1193: 1 | V1193: 0.0277 | W1193: 111.166 | X1193: 4 | Y1193: 0.531
K1194: Little Bit Of Lovin' | L1194: 58 | M1194: 393960 | N1194: 0.593 | O1194: 0.509 | P1194: 0.582 | Q1194: 0.000811 | R1194: 10 | S1194: 0.0996 | T1194: -7.172 | U1194: 1 | V1194: 0.0333 | W1194: 92.044 | X1194: 4 | Y1194: 0.552
K1195: I Want You Back | L1195: 41 | M1195: 176333 | N1195: 0.29 | O1195: 0.639 | P1195: 0.548 | Q1195: 9.68e-05 | R1195: 8 | S1195: 0.366 | T1195: -13.534 | U1195: 1 | V1195: 0.0394 | W1195: 98.359 | X1195: 4 | Y1195: 0.887
K1196: Hand In My Pocket - 2015 Remastered | L1196: 67 | M1196: 222013 | N1196: 0.135 | O1196: 0.657 | P1196: 0.655 | Q1196: 0.00303 | R1196: 0 | S1196: 0.102 | T1196: -8.3 | U1196: 1 | V1196: 0.0248 | W1196: 92.259 | X1196: 4 | Y1196: 0.668
K1197: Glow | L1197: 41 | M1197: 230694 | N1197: 0.0612 | O1197: 0.576 | P1197: 0.795 | Q1197: 0 | R1197: 0 | S1197: 0.14 | T1197: -4.87 | U1197: 1 | V1197: 0.0346 | W1197: 123.071 | X1197: 4 | Y1197: 0.427
K1198: Three Little Birds | L1198: 39 | M1198: 180266 | N1198: 0.0111 | O1198: 0.814 | P1198: 0.482 | Q1198: 1.57e-06 | R1198: 9 | S1198: 0.0476 | T1198: -10.493 | U1198: 1 | V1198: 0.0588 | W1198: 148.404 | X1198: 4 | Y1198: 0.615
K1199: Light On | L1199: 69 | M1199: 233880 | N1199: 0.201 | O1199: 0.657 | P1199: 0.569 | Q1199: 1.38e-05 | R1199: 2 | S1199: 0.126 | T1199: -6.287 | U1199: 1 | V1199: 0.0542 | W1199: 102.054 | X1199: 4 | Y1199: 0.399
K1200: Cut Loose | L1200: 51 | M1200: 162003 | N1200: 0.00226 | O1200: 0.716 | P1200: 0.661 | Q1200: 0.000136 | R1200: 7 | S1200: 0.109 | T1200: -7.032 | U1200: 1 | V1200: 0.0486 | W1200: 102.009 | X1200: 4 | Y1200: 0.663
... K1632: Prey | L1632: 66 | M1632: 255230 | N1632: 3.28e-05 | O1632: 0.27 | P1632: 0.964 | Q1632: 0.0247 | R1632: 6 | S1632: 0.525 | T1632: -4.545 | U1632: 1 | V1632: 0.0866 | W1632: 99.731 | X1632: 3 | Y1632: 0.325
K1633: 1234 | L1633: 15 | M1633: 202907 | N1633: 5.32e-05 | O1633: 0.558 | P1633: 0.953 | Q1633: 0.000375 | R1633: 7 | S1633: 0.062 | T1633: -4.705 | U1633: 1 | V1633: 0.0288 | W1633: 95 | X1633: 4 | Y1633: 0.75
K1634: Chaos And Earthquakes | L1634: 66 | M1634: 225133 | N1634: 0.000417 | O1634: 0.524 | P1634: 0.843 | Q1634: 0.125 | R1634: 10 | S1634: 0.375 | T1634: -5.578 | U1634: 0 | V1634: 0.0536 | W1634: 85.993 | X1634: 4 | Y1634: 0.212
K1635: Dumptruck | L1635: 61 | M1635: 217720 | N1635: 4.49e-05 | O1635: 0.491 | P1635: 0.87 | Q1635: 0.000145 | R1635: 2 | S1635: 0.0607 | T1635: -4.327 | U1635: 1 | V1635: 0.0443 | W1635: 103.072 | X1635: 4 | Y1635: 0.21
K1636: Sleep Walking Elite | L1636: 59 | M1636: 219760 | N1636: 0.00567 | O1636: 0.427 | P1636: 0.959 | Q1636: 0.000279 | R1636: 8 | S1636: 0.151 | T1636: -4.67 | U1636: 1 | V1636: 0.0711 | W1636: 84.979 | X1636: 3 | Y1636: 0.398
K1637: Who Do You Trust? | L1637: 68 | M1637: 196480 | N1637: 0.047 | O1637: 0.56 | P1637: 0.885 | Q1637: 3.47e-06 | R1637: 2 | S1637: 0.361 | T1637: -5.631 | U1637: 1 | V1637: 0.0363 | W1637: 102.003 | X1637: 4 | Y1637: 0.312
K1638: Hereafter | L1638: 65 | M1638: 255586 | N1638: 4.58e-05 | O1638: 0.513 | P1638: 0.973 | Q1638: 0.00326 | R1638: 6 | S1638: 0.224 | T1638: -4.115 | U1638: 0 | V1638: 0.0849 | W1638: 121.018 | X1638: 4 | Y1638: 0.159
K1639: The Devil's Bleeding Crown | L1639: 14 | M1639: 238653 | N1639: 1.85e-05 | O1639: 0.55 | P1639: 0.917 | Q1639: 0.214 | R1639: 7 | S1639: 0.0333 | T1639: -4.575 | U1639: 1 | V1639: 0.0378 | W1639: 109.552 | X1639: 3 | Y1639: 0.245
K1640: All or Nothing | L1640: 55 | M1640: 198144 | N1640: 0.00103 | O1640: 0.466 | P1640: 0.954 | Q1640: 2.94e-06 | R1640: 7 | S1640: 0.111 | T1640: -5.077 | U1640: 1 | V1640: 0.333 | W1640: 198.049 | X1640: 4 | Y1640: 0.325
K1641: Animal | L1641: 53 | M1641: 212933 | N1641: 1.6e-05 | O1641: 0.414 | P1641: 0.987 | Q1641: 1.65e-06 | R1641: 10 | S1641: 0.361 | T1641: -1.691 | U1641: 0 | V1641: 0.0922 | W1641: 157.924 | X1641: 4 | Y1641: 0.255
K1642: Are You Ready | L1642: 72 | M1642: 261705 | N1642: 0.000108 | O1642: 0.528 | P1642: 0.976 | Q1642: 0 | R1642: 2 | S1642: 0.24 | T1642: -2.188 | U1642: 1 | V1642: 0.0803 | W1642: 100.082 | X1642: 4 | Y1642: 0.511
K1643: Monster | L1643: 58 | M1643: 207200 | N1643: 0.000112 | O1643: 0.377 | P1643: 0.971 | Q1643: 0.00146 | R1643: 6 | S1643: 0.371 | T1643: -3.316 | U1643: 1 | V1643: 0.134 | W1643: 140.025 | X1643: 4 | Y1643: 0.326
K1644: Do You Really Want It | L1644: 60 | M1644: 233333 | N1644: 8.6e-05 | O1644: 0.223 | P1644: 0.891 | Q1644: 0.000422 | R1644: 7 | S1644: 0.107 | T1644: -4.918 | U1644: 1 | V1644: 0.133 | W1644: 170.6 | X1644: 4 | Y1644: 0.558
K1645: Calm Before the Storm | L1645: 48 | M1645: 235013 | N1645: 1.34e-05 | O1645: 0.377 | P1645: 0.975 | Q1645: 0.00344 | R1645: 2 | S1645: 0.268 | T1645: -4.31 | U1645: 0 | V1645: 0.171 | W1645: 163.168 | X1645: 4 | Y1645: 0.311
...

Sheet Vlookup2
B4: Zadanie - Uzupełnij tabelę wydaktów militarnych na podstawie
B6: https://www.sipri.org/databases
B15: Wydatki % PKB | F15: Wydatki % budżetu
D16: 2020 | H16: 2020
B17: Russia | C17: Rosja | F17: Russia | G17: Rosja
B18: USA | C18: USA | F18: USA | G18: USA
B19: Germany | C19: Niemcy | F19: Germany | G19: Niemcy
B20: Poland | C20: Polska | F20: Poland | G20: Polska
B21: Ukraine | C21: Ukraina | F21: Ukraine | G21: Ukraina
B22: France | C22: Francja | F22: France | G22: Francja
B23: Italy | C23: Włochy | F23: Italy | G23: Włochy
B24: China | C24: Chiny | F24: China | G24: Chiny
B25: Sweden | C25: Szwecja | F25: Sweden | G25: Szwecja
B26: Finland | C26: Finlandia | F26: Finland | G26: Finlandia

Sheet Indeks
I17: Źródło: | K17: https://stat.gov.pl/wskazniki-makroekonomiczne/ | AM17: Źródło: | AN17: https://www.kaggle.com/jmcslk/ballon-d-or-data-analysis/data
A18: Funkcja Indeks | I18: Dane do zadań - zwróćcie uwagę jaka formuła je wyciągnęła z tabeli | U18: Zadanie 1 - Dynamiczne wykresy | AC18: Zadanie 2 - Vlookup na lewo | AK18: Dane - zadanie 2
A19: Indeks to chyba najbardziej niedoceniana funkcja Excela. | I19: Nr wiersza z tabeli | M19: 19 | N19: 24 | O19: 25 | P19: 26 | Q19: 27 | R19: 28 | U19: Funkcji INDEKS może pomóc za jednym ruchem dużo zmieniać na wykresie. | AC19: Ograniczeniem funkcji Vlookup (WYSZUKAJ.PIONOWO) jest wybór danych z pierwszej kolumny z lewej strony. Funkcja INDEKS nie uznaje takich ograniczeń. Połączymy ja z Match (PODAJ.POZYCJĘ), aby znaleźć informacje po lewej stronie. Pytanie: W którym roku CR7 i Leo Messi byli po raz pierwszy nominowanie do złotej piłki. Na którym miejscu skończyli rywalizacje? | AL19: year | AM19: rank | AN19: player | AO19: team | AP19: points | AQ19: percentages
I20: Nr kolumny z tabeli | J20: LP | K20: Okres | M20: Przeciętne wynagrodzenie - przemysł | N20: Przeciętne wynagrodzenie - budownictwo | O20: Przeciętne wynagrodzenie - handel | P20: Przeciętne wynagrodzenie - transport | Q20: Przeciętne wynagrodzenie - informacja i komunikacja | R20: Przeciętne wynagrodzenie - finanse | AK20: 0 | AL20: 1956 | AM20: 1st | AN20: Stanley Matthews | AO20: Blackpool | AP20: 47 | AQ20: 37.9
A21: Zwraca wybrany element tablicy. Działa następująco: | I21: =COLUMN(Dane_Index!BL5) -> 64 | J21: 1 | K21: 2015 | L21: I | M21: =IF(ISNUMBER(INDEX(Dane_Index!$1:$1048576,M$19,$I21)),INDEX(Dane_Index!$1:$1048576,M$19,$I21),NA()) -> 4111.89 | N21: =IF(ISNUMBER(INDEX(Dane_Index!$1:$1048576,N$19,$I21)),INDEX(Dane_Index!$1:$1048576,N$19,$I21),NA()) -> 3899.01 | O21: =IF(ISNUMBER(INDEX(Dane_Index!$1:$1048576,O$19,$I21)),INDEX(Dane_Index!$1:$1048576,O$19,$I21),NA()) -> 3723.97 | P21: =IF(ISNUMBER(INDEX(Dane_Index!$1:$1048576,P$19,$I21)),INDEX(Dane_Index!$1:$1048576,P$19,$I21),NA()) -> 3656.08 | Q21: =IF(ISNUMBER(INDEX(Dane_Index!$1:$1048576,Q$19,$I21)),INDEX(Dane_Index!$1:$1048576,Q$19,$I21),NA()) -> 7299.99 | R21: =IF(ISNUMBER(INDEX(Dane_Index!$1:$1048576,R$19,$I21)),INDEX(Dane_Index!$1:$1048576,R$19,$I21),NA()) -> 7240.12 | AK21: 1 | AL21: 1956 | AM21: 2nd | AN21: Alfredo Di StÃ©fano | AO21: Real Madrid | AP21: 44 | AQ21: 35.48
I22: =I21+1 -> 65 | J22: 2 | L22: II | M22: =IF(ISNUMBER(INDEX(Dane_Index!$1:$1048576,M$19,$I22)),INDEX(Dane_Index!$1:$1048576,M$19,$I22),NA()) -> 4120.43 | N22: =IF(ISNUMBER(INDEX(Dane_Index!$1:$1048576,N$19,$I22)),INDEX(Dane_Index!$1:$1048576,N$19,$I22),NA()) -> 4042.29 | O22: =IF(ISNUMBER(INDEX(Dane_Index!$1:$1048576,O$19,$I22)),INDEX(Dane_Index!$1:$1048576,O$19,$I22),NA()) -> 3703.1 | P22: =IF(ISNUMBER(INDEX(Dane_Index!$1:$1048576,P$19,$I22)),INDEX(Dane_Index!$1:$1048576,P$19,$I22),NA()) -> 3757.29 | Q22: =IF(ISNUMBER(INDEX(Dane_Index!$1:$1048576,Q$19,$I22)),INDEX(Dane_Index!$1:$1048576,Q$19,$I22),NA()) -> 7280.78 | R22: =IF(ISNUMBER(INDEX(Dane_Index!$1:$1048576,R$19,$I22)),INDEX(Dane_Index!$1:$1048576,R$19,$I22),NA()) -> 6906 | X22: 1 | Y22: 3 | AK22: 2 | AL22: 1956 | AM22: 3rd | AN22: Raymond Kopa | AO22: Real Madrid | AP22: 33 | AQ22: 26.61
B23: =INDEX(ZAKRES,Nr. Wiersza, Nr. Kolumny) | I23: =I22+1 -> 66 | J23: 3 | L23: III | M23: =IF(ISNUMBER(INDEX(Dane_Index!$1:$1048576,M$19,$I23)),INDEX(Dane_Index!$1:$1048576,M$19,$I23),NA()) -> 4124.24 | N23: =IF(ISNUMBER(INDEX(Dane_Index!$1:$1048576,N$19,$I23)),INDEX(Dane_Index!$1:$1048576,N$19,$I23),NA()) -> 4111.21 | O23: =IF(ISNUMBER(INDEX(Dane_Index!$1:$1048576,O$19,$I23)),INDEX(Dane_Index!$1:$1048576,O$19,$I23),NA()) -> 3677.22 | P23: =IF(ISNUMBER(INDEX(Dane_Index!$1:$1048576,P$19,$I23)),INDEX(Dane_Index!$1:$1048576,P$19,$I23),NA()) -> 3831.3 | Q23: =IF(ISNUMBER(INDEX(Dane_Index!$1:$1048576,Q$19,$I23)),INDEX(Dane_Index!$1:$1048576,Q$19,$I23),NA()) -> 7142.81 | R23: =IF(ISNUMBER(INDEX(Dane_Index!$1:$1048576,R$19,$I23)),INDEX(Dane_Index!$1:$1048576,R$19,$I23),NA()) -> 6583.08 | V23: Okres | X23: =PROPER(SUBSTITUTE(INDEX($M$20:$R$20,X$22),"Przeciętne wynagrodzenie - ","")) -> Przemysł | Y23: =PROPER(SUBSTITUTE(INDEX($M$20:$R$20,Y$22),"Przeciętne wynagrodzenie - ","")) -> Handel | Z23: ="Relacja " &X23&"/"&Y23 -> Relacja Przemysł/Handel | AA23: ="Relacja " &X23&"/"&Y23 &" - średnia 3m" -> Relacja Przemysł/Handel - średnia 3m | AK23: 3 | AL23: 1957 | AM23: 1st | AN23: Alfredo Di StÃ©fano | AO23: Real Madrid | AP23: 72 | AQ23: 58.54
I24: =I23+1 -> 67 | J24: 4 | L24: IV | M24: =IF(ISNUMBER(INDEX(Dane_Index!$1:$1048576,M$19,$I24)),INDEX(Dane_Index!$1:$1048576,M$19,$I24),NA()) -> 4406.61 | N24: =IF(ISNUMBER(INDEX(Dane_Index!$1:$1048576,N$19,$I24)),INDEX(Dane_Index!$1:$1048576,N$19,$I24),NA()) -> 4249.78 | O24: =IF(ISNUMBER(INDEX(Dane_Index!$1:$1048576,O$19,$I24)),INDEX(Dane_Index!$1:$1048576,O$19,$I24),NA()) -> 3702.12 | P24: =IF(ISNUMBER(INDEX(Dane_Index!$1:$1048576,P$19,$I24)),INDEX(Dane_Index!$1:$1048576,P$19,$I24),NA()) -> 4089.43 | Q24: =IF(ISNUMBER(INDEX(Dane_Index!$1:$1048576,Q$19,$I24)),INDEX(Dane_Index!$1:$1048576,Q$19,$I24),NA()) -> 7171.27 | R24: =IF(ISNUMBER(INDEX(Dane_Index!$1:$1048576,R$19,$I24)),INDEX(Dane_Index!$1:$1048576,R$19,$I24),NA()) -> 6820.58 | U24: 1 | V24: 2015 | W24: I | Z24: =IF(ISNUMBER(X24),X24/Y24,NA()) -> #N/A | AA24: =NA() -> #N/A | AK24: 4 | AL24: 1957 | AM24: 2nd | AN24: Billy Wright | AO24: Wolverhampton Wanderers | AP24: 19 | AQ24: 15.45
A25: Gdzie: | I25: =I24+1 -> 68 | J25: 5 | K25: =K21+1 -> 2016 | L25: I | M25: =IF(ISNUMBER(INDEX(Dane_Index!$1:$1048576,M$19,$I25)),INDEX(Dane_Index!$1:$1048576,M$19,$I25),NA()) -> 4233.42 | N25: =IF(ISNUMBER(INDEX(Dane_Index!$1:$1048576,N$19,$I25)),INDEX(Dane_Index!$1:$1048576,N$19,$I25),NA()) -> 4042.8 | O25: =IF(ISNUMBER(INDEX(Dane_Index!$1:$1048576,O$19,$I25)),INDEX(Dane_Index!$1:$1048576,O$19,$I25),NA()) -> 3887.89 | P25: =IF(ISNUMBER(INDEX(Dane_Index!$1:$1048576,P$19,$I25)),INDEX(Dane_Index!$1:$1048576,P$19,$I25),NA()) -> 3767.09 | Q25: =IF(ISNUMBER(INDEX(Dane_Index!$1:$1048576,Q$19,$I25)),INDEX(Dane_Index!$1:$1048576,Q$19,$I25),NA()) -> 7599.24 | R25: =IF(ISNUMBER(INDEX(Dane_Index!$1:$1048576,R$19,$I25)),INDEX(Dane_Index!$1:$1048576,R$19,$I25),NA()) -> 7329.59 | U25: 2 | W25: II | Z25: =IF(ISNUMBER(X25),X25/Y25,NA()) -> #N/A | AA25: =NA() -> #N/A | AD25: Rok | AE25: Miejsce | AF25: Klub | AK25: 5 | AL25: 1957 | AM25: 3rd | AN25: Duncan Edwards | AO25: Manchester United | AP25: 16 | AQ25: 13.01
B26: ZAKRES | C26: - | D26: Wybrana przez nas tablica | I26: =I25+1 -> 69 | J26: 6 | L26: II | M26: =IF(ISNUMBER(INDEX(Dane_Index!$1:$1048576,M$19,$I26)),INDEX(Dane_Index!$1:$1048576,M$19,$I26),NA()) -> 4252.65 | N26: =IF(ISNUMBER(INDEX(Dane_Index!$1:$1048576,N$19,$I26)),INDEX(Dane_Index!$1:$1048576,N$19,$I26),NA()) -> 4296.46 | O26: =IF(ISNUMBER(INDEX(Dane_Index!$1:$1048576,O$19,$I26)),INDEX(Dane_Index!$1:$1048576,O$19,$I26),NA()) -> 3934.17 | P26: =IF(ISNUMBER(INDEX(Dane_Index!$1:$1048576,P$19,$I26)),INDEX(Dane_Index!$1:$1048576,P$19,$I26),NA()) -> 3884.53 | Q26: =IF(ISNUMBER(INDEX(Dane_Index!$1:$1048576,Q$19,$I26)),INDEX(Dane_Index!$1:$1048576,Q$19,$I26),NA()) -> 7593.05 | R26: =IF(ISNUMBER(INDEX(Dane_Index!$1:$1048576,R$19,$I26)),INDEX(Dane_Index!$1:$1048576,R$19,$I26),NA()) -> 7017.37 | U26: 3 | W26: III | Z26: =IF(ISNUMBER(X26),X26/Y26,NA()) -> #N/A | AA26: =AVERAGE(Z24:Z26) -> #N/A | AC26: Cristiano Ronaldo | AK26: 6 | AL26: 1957 | AM26: 3rd | AN26: Raymond Kopa | AO26: Real Madrid | AP26: 16 | AQ26: 13.01
I27: =I26+1 -> 70 | J27: 7 | L27: III | M27: =IF(ISNUMBER(INDEX(Dane_Index!$1:$1048576,M$19,$I27)),INDEX(Dane_Index!$1:$1048576,M$19,$I27),NA()) -> 4315.08 | N27: =IF(ISNUMBER(INDEX(Dane_Index!$1:$1048576,N$19,$I27)),INDEX(Dane_Index!$1:$1048576,N$19,$I27),NA()) -> 4257.77 | O27: =IF(ISNUMBER(INDEX(Dane_Index!$1:$1048576,O$19,$I27)),INDEX(Dane_Index!$1:$1048576,O$19,$I27),NA()) -> 3902 | P27: =IF(ISNUMBER(INDEX(Dane_Index!$1:$1048576,P$19,$I27)),INDEX(Dane_Index!$1:$1048576,P$19,$I27),NA()) -> 3966.77 | Q27: =IF(ISNUMBER(INDEX(Dane_Index!$1:$1048576,Q$19,$I27)),INDEX(Dane_Index!$1:$1048576,Q$19,$I27),NA()) -> 7316.85 | R27: =IF(ISNUMBER(INDEX(Dane_Index!$1:$1048576,R$19,$I27)),INDEX(Dane_Index!$1:$1048576,R$19,$I27),NA()) -> 6936.01 | U27: 4 | W27: IV | Z27: =IF(ISNUMBER(X27),X27/Y27,NA()) -> #N/A | AA27: =AVERAGE(Z25:Z27) -> #N/A | AC27: Lionel Messi | AK27: 7 | AL27: 1958 | AM27: 1st | AN27: Raymond Kopa | AO27: Real Madrid | AP27: 71 | AQ27: 52.99
B28: Nr. Wiersza | C28: - | D28: Wiersz w naszej wybranej tablicy | I28: =I27+1 -> 71 | J28: 8 | L28: IV | M28: =IF(ISNUMBER(INDEX(Dane_Index!$1:$1048576,M$19,$I28)),INDEX(Dane_Index!$1:$1048576,M$19,$I28),NA()) -> 4498.18 | N28: =IF(ISNUMBER(INDEX(Dane_Index!$1:$1048576,N$19,$I28)),INDEX(Dane_Index!$1:$1048576,N$19,$I28),NA()) -> 4408.35 | O28: =IF(ISNUMBER(INDEX(Dane_Index!$1:$1048576,O$19,$I28)),INDEX(Dane_Index!$1:$1048576,O$19,$I28),NA()) -> 3871.17 | P28: =IF(ISNUMBER(INDEX(Dane_Index!$1:$1048576,P$19,$I28)),INDEX(Dane_Index!$1:$1048576,P$19,$I28),NA()) -> 4225.82 | Q28: =IF(ISNUMBER(INDEX(Dane_Index!$1:$1048576,Q$19,$I28)),INDEX(Dane_Index!$1:$1048576,Q$19,$I28),NA()) -> 7762.5 | R28: =IF(ISNUMBER(INDEX(Dane_Index!$1:$1048576,R$19,$I28)),INDEX(Dane_Index!$1:$1048576,R$19,$I28),NA()) -> 6965.46 | U28: 5 | V28: =V24+1 -> 2016 | W28: I | Z28: =IF(ISNUMBER(X28),X28/Y28,NA()) -> #N/A | AA28: =AVERAGE(Z26:Z28) -> #N/A | AK28: 8 | AL28: 1958 | AM28: 2nd | AN28: Helmut Rahn | AO28: Rot-Weiss Essen | AP28: 40 | AQ28: 29.85
I29: =I28+1 -> 72 | J29: 9 | K29: =K25+1 -> 2017 | L29: I | M29: =IF(ISNUMBER(INDEX(Dane_Index!$1:$1048576,M$19,$I29)),INDEX(Dane_Index!$1:$1048576,M$19,$I29),NA()) -> 4408.47 | N29: =IF(ISNUMBER(INDEX(Dane_Index!$1:$1048576,N$19,$I29)),INDEX(Dane_Index!$1:$1048576,N$19,$I29),NA()) -> 4267.02 | O29: =IF(ISNUMBER(INDEX(Dane_Index!$1:$1048576,O$19,$I29)),INDEX(Dane_Index!$1:$1048576,O$19,$I29),NA()) -> 4148.02 | P29: =IF(ISNUMBER(INDEX(Dane_Index!$1:$1048576,P$19,$I29)),INDEX(Dane_Index!$1:$1048576,P$19,$I29),NA()) -> 3906.89 | Q29: =IF(ISNUMBER(INDEX(Dane_Index!$1:$1048576,Q$19,$I29)),INDEX(Dane_Index!$1:$1048576,Q$19,$I29),NA()) -> 7879.1 | R29: =IF(ISNUMBER(INDEX(Dane_Index!$1:$1048576,R$19,$I29)),INDEX(Dane_Index!$1:$1048576,R$19,$I29),NA()) -> 7680.19 | U29: 6 | W29: II | Z29: =IF(ISNUMBER(X29),X29/Y29,NA()) -> #N/A | AA29: =AVERAGE(Z27:Z29) -> #N/A | AK29: 9 | AL29: 1958 | AM29: 3rd | AN29: Just Fontaine | AO29: Stade de Reims | AP29: 23 | AQ29: 17.16
B30: Nr. Kolumny | C30: - | D30: Kolumna w naszej wybranej tablicy | I30: =I29+1 -> 73 | J30: 10 | L30: II | M30: =IF(ISNUMBER(INDEX(Dane_Index!$1:$1048576,M$19,$I30)),INDEX(Dane_Index!$1:$1048576,M$19,$I30),NA()) -> 4504.89 | N30: =IF(ISNUMBER(INDEX(Dane_Index!$1:$1048576,N$19,$I30)),INDEX(Dane_Index!$1:$1048576,N$19,$I30),NA()) -> 4466.95 | O30: =IF(ISNUMBER(INDEX(Dane_Index!$1:$1048576,O$19,$I30)),INDEX(Dane_Index!$1:$1048576,O$19,$I30),NA()) -> 4201.81 | P30: =IF(ISNUMBER(INDEX(Dane_Index!$1:$1048576,P$19,$I30)),INDEX(Dane_Index!$1:$1048576,P$19,$I30),NA()) -> 4054.33 | Q30: =IF(ISNUMBER(INDEX(Dane_Index!$1:$1048576,Q$19,$I30)),INDEX(Dane_Index!$1:$1048576,Q$19,$I30),NA()) -> 7864.12 | R30: =IF(ISNUMBER(INDEX(Dane_Index!$1:$1048576,R$19,$I30)),INDEX(Dane_Index!$1:$1048576,R$19,$I30),NA()) -> 7617.38 | U30: 7 | W30: III | Z30: =IF(ISNUMBER(X30),X30/Y30,NA()) -> #N/A | AA30: =AVERAGE(Z28:Z30) -> #N/A | AK30: 10 | AL30: 1959 | AM30: 1st | AN30: Alfredo Di StÃ©fano | AO30: Real Madrid | AP30: 80 | AQ30: 54.79
I31: =I30+1 -> 74 | J31: 11 | L31: III | M31: =IF(ISNUMBER(INDEX(Dane_Index!$1:$1048576,M$19,$I31)),INDEX(Dane_Index!$1:$1048576,M$19,$I31),NA()) -> 4540.04 | N31: =IF(ISNUMBER(INDEX(Dane_Index!$1:$1048576,N$19,$I31)),INDEX(Dane_Index!$1:$1048576,N$19,$I31),NA()) -> 4572.97 | O31: =IF(ISNUMBER(INDEX(Dane_Index!$1:$1048576,O$19,$I31)),INDEX(Dane_Index!$1:$1048576,O$19,$I31),NA()) -> 4181.35 | P31: =IF(ISNUMBER(INDEX(Dane_Index!$1:$1048576,P$19,$I31)),INDEX(Dane_Index!$1:$1048576,P$19,$I31),NA()) -> 4168.34 | Q31: =IF(ISNUMBER(INDEX(Dane_Index!$1:$1048576,Q$19,$I31)),INDEX(Dane_Index!$1:$1048576,Q$19,$I31),NA()) -> 7825.5 | R31: =IF(ISNUMBER(INDEX(Dane_Index!$1:$1048576,R$19,$I31)),INDEX(Dane_Index!$1:$1048576,R$19,$I31),NA()) -> 7158.32 | U31: 8 | W31: IV | Z31: =IF(ISNUMBER(X31),X31/Y31,NA()) -> #N/A | AA31: =AVERAGE(Z29:Z31) -> #N/A | AK31: 11 | AL31: 1959 | AM31: 2nd | AN31: Raymond Kopa | AO31: Real Madrid | AP31: 42 | AQ31: 28.77
I32: =I31+1 -> 75 | J32: 12 | L32: IV | M32: =IF(ISNUMBER(INDEX(Dane_Index!$1:$1048576,M$19,$I32)),INDEX(Dane_Index!$1:$1048576,M$19,$I32),NA()) -> 4805.63 | N32: =IF(ISNUMBER(INDEX(Dane_Index!$1:$1048576,N$19,$I32)),INDEX(Dane_Index!$1:$1048576,N$19,$I32),NA()) -> 4816.68 | O32: =IF(ISNUMBER(INDEX(Dane_Index!$1:$1048576,O$19,$I32)),INDEX(Dane_Index!$1:$1048576,O$19,$I32),NA()) -> 4291.26 | P32: =IF(ISNUMBER(INDEX(Dane_Index!$1:$1048576,P$19,$I32)),INDEX(Dane_Index!$1:$1048576,P$19,$I32),NA()) -> 4523.08 | Q32: =IF(ISNUMBER(INDEX(Dane_Index!$1:$1048576,Q$19,$I32)),INDEX(Dane_Index!$1:$1048576,Q$19,$I32),NA()) -> 7948.16 | R32: =IF(ISNUMBER(INDEX(Dane_Index!$1:$1048576,R$19,$I32)),INDEX(Dane_Index!$1:$1048576,R$19,$I32),NA()) -> 7354.18 | U32: 9 | V32: =V28+1 -> 2017 | W32: I | Z32: =IF(ISNUMBER(X32),X32/Y32,NA()) -> #N/A | AA32: =AVERAGE(Z30:Z32) -> #N/A | AK32: 12 | AL32: 1959 | AM32: 3rd | AN32: John Charles | AO32: Juventus | AP32: 24 | AQ32: 16.44
A33: Wykonamy 3 zadania, które pokażą nam jej funkcjonalność | I33: =I32+1 -> 76 | J33: 13 | K33: =K29+1 -> 2018 | L33: I | M33: =IF(ISNUMBER(INDEX(Dane_Index!$1:$1048576,M$19,$I33)),INDEX(Dane_Index!$1:$1048576,M$19,$I33),NA()) -> 4705.67 | N33: =IF(ISNUMBER(INDEX(Dane_Index!$1:$1048576,N$19,$I33)),INDEX(Dane_Index!$1:$1048576,N$19,$I33),NA()) -> 4592.89 | O33: =IF(ISNUMBER(INDEX(Dane_Index!$1:$1048576,O$19,$I33)),INDEX(Dane_Index!$1:$1048576,O$19,$I33),NA()) -> 4443.41 | P33: =IF(ISNUMBER(INDEX(Dane_Index!$1:$1048576,P$19,$I33)),INDEX(Dane_Index!$1:$1048576,P$19,$I33),NA()) -> 4167.51 | Q33: =IF(ISNUMBER(INDEX(Dane_Index!$1:$1048576,Q$19,$I33)),INDEX(Dane_Index!$1:$1048576,Q$19,$I33),NA()) -> 8500.58 | R33: =IF(ISNUMBER(INDEX(Dane_Index!$1:$1048576,R$19,$I33)),INDEX(Dane_Index!$1:$1048576,R$19,$I33),NA()) -> 8190.82 | U33: 10 | W33: II | Z33: =IF(ISNUMBER(X33),X33/Y33,NA()) -> #N/A | AA33: =AVERAGE(Z31:Z33) -> #N/A | AK33: 13 | AL33: 1960 | AM33: 1st | AN33: Luis SuÃ¡rez | AO33: Barcelona | AP33: 54 | AQ33: 43.55
I34: =I33+1 -> 77 | J34: 14 | L34: II | M34: =IF(ISNUMBER(INDEX(Dane_Index!$1:$1048576,M$19,$I34)),INDEX(Dane_Index!$1:$1048576,M$19,$I34),NA()) -> 4857.38 | N34: =IF(ISNUMBER(INDEX(Dane_Index!$1:$1048576,N$19,$I34)),INDEX(Dane_Index!$1:$1048576,N$19,$I34),NA()) -> 4869.6 | O34: =IF(ISNUMBER(INDEX(Dane_Index!$1:$1048576,O$19,$I34)),INDEX(Dane_Index!$1:$1048576,O$19,$I34),NA()) -> 4516.23 | P34: =IF(ISNUMBER(INDEX(Dane_Index!$1:$1048576,P$19,$I34)),INDEX(Dane_Index!$1:$1048576,P$19,$I34),NA()) -> 4285.75 | Q34: =IF(ISNUMBER(INDEX(Dane_Index!$1:$1048576,Q$19,$I34)),INDEX(Dane_Index!$1:$1048576,Q$19,$I34),NA()) -> 8458.7 | R34: =IF(ISNUMBER(INDEX(Dane_Index!$1:$1048576,R$19,$I34)),INDEX(Dane_Index!$1:$1048576,R$19,$I34),NA()) -> 8006.79 | U34: 11 | W34: III | Z34: =IF(ISNUMBER(X34),X34/Y34,NA()) -> #N/A | AA34: =AVERAGE(Z32:Z34) -> #N/A | AK34: 14 | AL34: 1960 | AM34: 2nd | AN34: Ferenc PuskÃ¡s | AO34: Real Madrid | AP34: 37 | AQ34: 29.84
I35: =I34+1 -> 78 | J35: 15 | L35: III | M35: =IF(ISNUMBER(INDEX(Dane_Index!$1:$1048576,M$19,$I35)),INDEX(Dane_Index!$1:$1048576,M$19,$I35),NA()) -> 4854.78 | N35: =IF(ISNUMBER(INDEX(Dane_Index!$1:$1048576,N$19,$I35)),INDEX(Dane_Index!$1:$1048576,N$19,$I35),NA()) -> 5010.96 | O35: =IF(ISNUMBER(INDEX(Dane_Index!$1:$1048576,O$19,$I35)),INDEX(Dane_Index!$1:$1048576,O$19,$I35),NA()) -> 4485.01 | P35: =IF(ISNUMBER(INDEX(Dane_Index!$1:$1048576,P$19,$I35)),INDEX(Dane_Index!$1:$1048576,P$19,$I35),NA()) -> 4382.28 | Q35: =IF(ISNUMBER(INDEX(Dane_Index!$1:$1048576,Q$19,$I35)),INDEX(Dane_Index!$1:$1048576,Q$19,$I35),NA()) -> 8276.44 | R35: =IF(ISNUMBER(INDEX(Dane_Index!$1:$1048576,R$19,$I35)),INDEX(Dane_Index!$1:$1048576,R$19,$I35),NA()) -> 7562.98 | U35: 12 | W35: IV | Z35: =IF(ISNUMBER(X35),X35/Y35,NA()) -> #N/A | AA35: =AVERAGE(Z33:Z35) -> #N/A | AK35: 15 | AL35: 1960 | AM35: 3rd | AN35: Uwe Seeler | AO35: Hamburg | AP35: 33 | AQ35: 26.61
I36: =I35+1 -> 79 | J36: 16 | L36: IV | M36: =IF(ISNUMBER(INDEX(Dane_Index!$1:$1048576,M$19,$I36)),INDEX(Dane_Index!$1:$1048576,M$19,$I36),NA()) -> 5180.9 | N36: =IF(ISNUMBER(INDEX(Dane_Index!$1:$1048576,N$19,$I36)),INDEX(Dane_Index!$1:$1048576,N$19,$I36),NA()) -> 5119.68 | O36: =IF(ISNUMBER(INDEX(Dane_Index!$1:$1048576,O$19,$I36)),INDEX(Dane_Index!$1:$1048576,O$19,$I36),NA()) -> 4603.43 | P36: =IF(ISNUMBER(INDEX(Dane_Index!$1:$1048576,P$19,$I36)),INDEX(Dane_Index!$1:$1048576,P$19,$I36),NA()) -> 4723.04 | Q36: =IF(ISNUMBER(INDEX(Dane_Index!$1:$1048576,Q$19,$I36)),INDEX(Dane_Index!$1:$1048576,Q$19,$I36),NA()) -> 8477.04 | R36: =IF(ISNUMBER(INDEX(Dane_Index!$1:$1048576,R$19,$I36)),INDEX(Dane_Index!$1:$1048576,R$19,$I36),NA()) -> 7767.1 | U36: 13 | V36: =V32+1 -> 2018 | W36: I | Z36: =IF(ISNUMBER(X36),X36/Y36,NA()) -> #N/A | AA36: =AVERAGE(Z34:Z36) -> #N/A | AK36: 16 | AL36: 1961 | AM36: 1st | AN36: Omar SÃ­vori | AO36: Juventus | AP36: 46 | AQ36: 42.59
I37: =I36+1 -> 80 | J37: 17 | K37: =K33+1 -> 2019 | L37: I | M37: =IF(ISNUMBER(INDEX(Dane_Index!$1:$1048576,M$19,$I37)),INDEX(Dane_Index!$1:$1048576,M$19,$I37),NA()) -> 5035.98 | N37: =IF(ISNUMBER(INDEX(Dane_Index!$1:$1048576,N$19,$I37)),INDEX(Dane_Index!$1:$1048576,N$19,$I37),NA()) -> 4873.42 | O37: =IF(ISNUMBER(INDEX(Dane_Index!$1:$1048576,O$19,$I37)),INDEX(Dane_Index!$1:$1048576,O$19,$I37),NA()) -> 4751.4 | P37: =IF(ISNUMBER(INDEX(Dane_Index!$1:$1048576,P$19,$I37)),INDEX(Dane_Index!$1:$1048576,P$19,$I37),NA()) -> 4400.32 | Q37: =IF(ISNUMBER(INDEX(Dane_Index!$1:$1048576,Q$19,$I37)),INDEX(Dane_Index!$1:$1048576,Q$19,$I37),NA()) -> 8896.65 | R37: =IF(ISNUMBER(INDEX(Dane_Index!$1:$1048576,R$19,$I37)),INDEX(Dane_Index!$1:$1048576,R$19,$I37),NA()) -> 8539.55 | U37: 14 | W37: II | Z37: =IF(ISNUMBER(X37),X37/Y37,NA()) -> #N/A | AA37: =AVERAGE(Z35:Z37) -> #N/A | AK37: 17 | AL37: 1961 | AM37: 2nd | AN37: Luis SuÃ¡rez | AO37: Internazionale | AP37: 40 | AQ37: 37.04
I38: =I37+1 -> 81 | J38: 18 | L38: II | M38: =IF(ISNUMBER(INDEX(Dane_Index!$1:$1048576,M$19,$I38)),INDEX(Dane_Index!$1:$1048576,M$19,$I38),NA()) -> 5164.94 | N38: =IF(ISNUMBER(INDEX(Dane_Index!$1:$1048576,N$19,$I38)),INDEX(Dane_Index!$1:$1048576,N$19,$I38),NA()) -> 5283.01 | O38: =IF(ISNUMBER(INDEX(Dane_Index!$1:$1048576,O$19,$I38)),INDEX(Dane_Index!$1:$1048576,O$19,$I38),NA()) -> 4844.88 | P38: =IF(ISNUMBER(INDEX(Dane_Index!$1:$1048576,P$19,$I38)),INDEX(Dane_Index!$1:$1048576,P$19,$I38),NA()) -> 4533.99 | Q38: =IF(ISNUMBER(INDEX(Dane_Index!$1:$1048576,Q$19,$I38)),INDEX(Dane_Index!$1:$1048576,Q$19,$I38),NA()) -> 8964.9 | R38: =IF(ISNUMBER(INDEX(Dane_Index!$1:$1048576,R$19,$I38)),INDEX(Dane_Index!$1:$1048576,R$19,$I38),NA()) -> 8150.59 | U38: 15 | W38: III | Z38: =IF(ISNUMBER(X38),X38/Y38,NA()) -> #N/A | AA38: =AVERAGE(Z36:Z38) -> #N/A | AK38: 18 | AL38: 1961 | AM38: 3rd | AN38: Johnny Haynes | AO38: Fulham | AP38: 22 | AQ38: 20.37
I39: =I38+1 -> 82 | J39: 19 | L39: III | M39: =IF(ISNUMBER(INDEX(Dane_Index!$1:$1048576,M$19,$I39)),INDEX(Dane_Index!$1:$1048576,M$19,$I39),NA()) -> 5207.63 | N39: =IF(ISNUMBER(INDEX(Dane_Index!$1:$1048576,N$19,$I39)),INDEX(Dane_Index!$1:$1048576,N$19,$I39),NA()) -> 5234.73 | O39: =IF(ISNUMBER(INDEX(Dane_Index!$1:$1048576,O$19,$I39)),INDEX(Dane_Index!$1:$1048576,O$19,$I39),NA()) -> 4797.29 | P39: =IF(ISNUMBER(INDEX(Dane_Index!$1:$1048576,P$19,$I39)),INDEX(Dane_Index!$1:$1048576,P$19,$I39),NA()) -> 4637.46 | Q39: =IF(ISNUMBER(INDEX(Dane_Index!$1:$1048576,Q$19,$I39)),INDEX(Dane_Index!$1:$1048576,Q$19,$I39),NA()) -> 8492.08 | R39: =IF(ISNUMBER(INDEX(Dane_Index!$1:$1048576,R$19,$I39)),INDEX(Dane_Index!$1:$1048576,R$19,$I39),NA()) -> 8095.63 | U39: 16 | W39: IV | Z39: =IF(ISNUMBER(X39),X39/Y39,NA()) -> #N/A | AA39: =AVERAGE(Z37:Z39) -> #N/A | AK39: 19 | AL39: 1962 | AM39: 1st | AN39: Josef Masopust | AO39: Dukla Prague | AP39: 65 | AQ39: 43.05
I40: =I39+1 -> 83 | J40: 20 | L40: IV | M40: =IF(ISNUMBER(INDEX(Dane_Index!$1:$1048576,M$19,$I40)),INDEX(Dane_Index!$1:$1048576,M$19,$I40),NA()) -> 5448.29 | N40: =IF(ISNUMBER(INDEX(Dane_Index!$1:$1048576,N$19,$I40)),INDEX(Dane_Index!$1:$1048576,N$19,$I40),NA()) -> 5462.46 | O40: =IF(ISNUMBER(INDEX(Dane_Index!$1:$1048576,O$19,$I40)),INDEX(Dane_Index!$1:$1048576,O$19,$I40),NA()) -> 4908.84 | P40: =IF(ISNUMBER(INDEX(Dane_Index!$1:$1048576,P$19,$I40)),INDEX(Dane_Index!$1:$1048576,P$19,$I40),NA()) -> 4984.21 | Q40: =IF(ISNUMBER(INDEX(Dane_Index!$1:$1048576,Q$19,$I40)),INDEX(Dane_Index!$1:$1048576,Q$19,$I40),NA()) -> 8811.58 | R40: =IF(ISNUMBER(INDEX(Dane_Index!$1:$1048576,R$19,$I40)),INDEX(Dane_Index!$1:$1048576,R$19,$I40),NA()) -> 8159.23 | U40: 17 | V40: =V36+1 -> 2019 | W40: I | Z40: =IF(ISNUMBER(X40),X40/Y40,NA()) -> #N/A | AA40: =AVERAGE(Z38:Z40) -> #N/A | AK40: 20 | AL40: 1962 | AM40: 2nd | AN40: EusÃ©bio | AO40: Benfica | AP40: 53 | AQ40: 35.1
I41: =I40+1 -> 84 | J41: 21 | K41: =K37+1 -> 2020 | L41: I | M41: =IF(ISNUMBER(INDEX(Dane_Index!$1:$1048576,M$19,$I41)),INDEX(Dane_Index!$1:$1048576,M$19,$I41),NA()) -> 5368.95 | N41: =IF(ISNUMBER(INDEX(Dane_Index!$1:$1048576,N$19,$I41)),INDEX(Dane_Index!$1:$1048576,N$19,$I41),NA()) -> 5180.03 | O41: =IF(ISNUMBER(INDEX(Dane_Index!$1:$1048576,O$19,$I41)),INDEX(Dane_Index!$1:$1048576,O$19,$I41),NA()) -> 5118.87 | P41: =IF(ISNUMBER(INDEX(Dane_Index!$1:$1048576,P$19,$I41)),INDEX(Dane_Index!$1:$1048576,P$19,$I41),NA()) -> 4668 | Q41: =IF(ISNUMBER(INDEX(Dane_Index!$1:$1048576,Q$19,$I41)),INDEX(Dane_Index!$1:$1048576,Q$19,$I41),NA()) -> 9457.34 | R41: =IF(ISNUMBER(INDEX(Dane_Index!$1:$1048576,R$19,$I41)),INDEX(Dane_Index!$1:$1048576,R$19,$I41),NA()) -> 9461.46 | U41: 18 | W41: II | Z41: =IF(ISNUMBER(X41),X41/Y41,NA()) -> #N/A | AA41: =AVERAGE(Z39:Z41) -> #N/A | AK41: 21 | AL41: 1962 | AM41: 3rd | AN41: Karl-Heinz Schnellinger | AO41: KÃ¶ln | AP41: 33 | AQ41: 21.85
I42: =I41+1 -> 85 | J42: 22 | L42: II | M42: =IF(ISNUMBER(INDEX(Dane_Index!$1:$1048576,M$19,$I42)),INDEX(Dane_Index!$1:$1048576,M$19,$I42),NA()) -> 5212.61 | N42: =IF(ISNUMBER(INDEX(Dane_Index!$1:$1048576,N$19,$I42)),INDEX(Dane_Index!$1:$1048576,N$19,$I42),NA()) -> 5325.21 | O42: =IF(ISNUMBER(INDEX(Dane_Index!$1:$1048576,O$19,$I42)),INDEX(Dane_Index!$1:$1048576,O$19,$I42),NA()) -> 5017.82 | P42: =IF(ISNUMBER(INDEX(Dane_Index!$1:$1048576,P$19,$I42)),INDEX(Dane_Index!$1:$1048576,P$19,$I42),NA()) -> 4560.35 | Q42: =IF(ISNUMBER(INDEX(Dane_Index!$1:$1048576,Q$19,$I42)),INDEX(Dane_Index!$1:$1048576,Q$19,$I42),NA()) -> 9073.65 | R42: =IF(ISNUMBER(INDEX(Dane_Index!$1:$1048576,R$19,$I42)),INDEX(Dane_Index!$1:$1048576,R$19,$I42),NA()) -> 8757.83 | U42: 19 | W42: III | Z42: =IF(ISNUMBER(X42),X42/Y42,NA()) -> #N/A | AA42: =AVERAGE(Z40:Z42) -> #N/A | AK42: 22 | AL42: 1963 | AM42: 1st | AN42: Lev Yashin | AO42: Dynamo Moscow | AP42: 73 | AQ42: 45.91
I43: =I42+1 -> 86 | J43: 23 | L43: III | M43: =IF(ISNUMBER(INDEX(Dane_Index!$1:$1048576,M$19,$I43)),INDEX(Dane_Index!$1:$1048576,M$19,$I43),NA()) -> 5397.57 | N43: =IF(ISNUMBER(INDEX(Dane_Index!$1:$1048576,N$19,$I43)),INDEX(Dane_Index!$1:$1048576,N$19,$I43),NA()) -> 5490.26 | O43: =IF(ISNUMBER(INDEX(Dane_Index!$1:$1048576,O$19,$I43)),INDEX(Dane_Index!$1:$1048576,O$19,$I43),NA()) -> 4976.77 | P43: =IF(ISNUMBER(INDEX(Dane_Index!$1:$1048576,P$19,$I43)),INDEX(Dane_Index!$1:$1048576,P$19,$I43),NA()) -> 4742.85 | Q43: =IF(ISNUMBER(INDEX(Dane_Index!$1:$1048576,Q$19,$I43)),INDEX(Dane_Index!$1:$1048576,Q$19,$I43),NA()) -> 9191.28 | R43: =IF(ISNUMBER(INDEX(Dane_Index!$1:$1048576,R$19,$I43)),INDEX(Dane_Index!$1:$1048576,R$19,$I43),NA()) -> 8060.39 | U43: 20 | W43: IV | Z43: =IF(ISNUMBER(X43),X43/Y43,NA()) -> #N/A | AA43: =AVERAGE(Z41:Z43) -> #N/A | AK43: 23 | AL43: 1963 | AM43: 2nd | AN43: Gianni Rivera | AO43: Milan | AP43: 53 | AQ43: 33.33
I44: =I43+1 -> 87 | J44: 24 | L44: IV | M44: =IF(ISNUMBER(INDEX(Dane_Index!$1:$1048576,M$19,$I44)),INDEX(Dane_Index!$1:$1048576,M$19,$I44),NA()) -> 5818.05 | N44: =IF(ISNUMBER(INDEX(Dane_Index!$1:$1048576,N$19,$I44)),INDEX(Dane_Index!$1:$1048576,N$19,$I44),NA()) -> 5610.77 | O44: =IF(ISNUMBER(INDEX(Dane_Index!$1:$1048576,O$19,$I44)),INDEX(Dane_Index!$1:$1048576,O$19,$I44),NA()) -> 5121.16 | P44: =IF(ISNUMBER(INDEX(Dane_Index!$1:$1048576,P$19,$I44)),INDEX(Dane_Index!$1:$1048576,P$19,$I44),NA()) -> 5044.2 | Q44: =IF(ISNUMBER(INDEX(Dane_Index!$1:$1048576,Q$19,$I44)),INDEX(Dane_Index!$1:$1048576,Q$19,$I44),NA()) -> 9279.29 | R44: =IF(ISNUMBER(INDEX(Dane_Index!$1:$1048576,R$19,$I44)),INDEX(Dane_Index!$1:$1048576,R$19,$I44),NA()) -> 8308.22 | U44: 21 | V44: =V40+1 -> 2020 | W44: I | Z44: =IF(ISNUMBER(X44),X44/Y44,NA()) -> #N/A | AA44: =AVERAGE(Z42:Z44) -> #N/A | AK44: 24 | AL44: 1963 | AM44: 3rd | AN44: Jimmy Greaves | AO44: Tottenham Hotspur | AP44: 33 | AQ44: 20.75
I45: =I44+1 -> 88 | J45: 25 | K45: =K41+1 -> 2021 | L45: I | M45: =IF(ISNUMBER(INDEX(Dane_Index!$1:$1048576,M$19,$I45)),INDEX(Dane_Index!$1:$1048576,M$19,$I45),NA()) -> 5696.99 | N45: =IF(ISNUMBER(INDEX(Dane_Index!$1:$1048576,N$19,$I45)),INDEX(Dane_Index!$1:$1048576,N$19,$I45),NA()) -> 5374.33 | O45: =IF(ISNUMBER(INDEX(Dane_Index!$1:$1048576,O$19,$I45)),INDEX(Dane_Index!$1:$1048576,O$19,$I45),NA()) -> 5409.71 | P45: =IF(ISNUMBER(INDEX(Dane_Index!$1:$1048576,P$19,$I45)),INDEX(Dane_Index!$1:$1048576,P$19,$I45),NA()) -> 4811.71 | Q45: =IF(ISNUMBER(INDEX(Dane_Index!$1:$1048576,Q$19,$I45)),INDEX(Dane_Index!$1:$1048576,Q$19,$I45),NA()) -> 10007.26 | R45: =IF(ISNUMBER(INDEX(Dane_Index!$1:$1048576,R$19,$I45)),INDEX(Dane_Index!$1:$1048576,R$19,$I45),NA()) -> 9555.71 | U45: 22 | W45: II | Z45: =IF(ISNUMBER(X45),X45/Y45,NA()) -> #N/A | AA45: =AVERAGE(Z43:Z45) -> #N/A | AK45: 25 | AL45: 1964 | AM45: 1st | AN45: Denis Law | AO45: Manchester United | AP45: 61 | AQ45: 42.96
I46: =I45+1 -> 89 | J46: 26 | L46: II | M46: =IF(ISNUMBER(INDEX(Dane_Index!$1:$1048576,M$19,$I46)),INDEX(Dane_Index!$1:$1048576,M$19,$I46),NA()) -> 5806.87 | N46: =IF(ISNUMBER(INDEX(Dane_Index!$1:$1048576,N$19,$I46)),INDEX(Dane_Index!$1:$1048576,N$19,$I46),NA()) -> 5770.24 | O46: =IF(ISNUMBER(INDEX(Dane_Index!$1:$1048576,O$19,$I46)),INDEX(Dane_Index!$1:$1048576,O$19,$I46),NA()) -> 5436.56 | P46: =IF(ISNUMBER(INDEX(Dane_Index!$1:$1048576,P$19,$I46)),INDEX(Dane_Index!$1:$1048576,P$19,$I46),NA()) -> 4930.98 | Q46: =IF(ISNUMBER(INDEX(Dane_Index!$1:$1048576,Q$19,$I46)),INDEX(Dane_Index!$1:$1048576,Q$19,$I46),NA()) -> 9968.64 | R46: =IF(ISNUMBER(INDEX(Dane_Index!$1:$1048576,R$19,$I46)),INDEX(Dane_Index!$1:$1048576,R$19,$I46),NA()) -> 8986.86 | U46: 23 | W46: III | Z46: =IF(ISNUMBER(X46),X46/Y46,NA()) -> #N/A | AA46: =AVERAGE(Z44:Z46) -> #N/A | AK46: 26 | AL46: 1964 | AM46: 2nd | AN46: Luis SuÃ¡rez | AO46: Internazionale | AP46: 43 | AQ46: 30.28
I47: =I46+1 -> 90 | J47: 27 | L47: III | M47: =IF(ISNUMBER(INDEX(Dane_Index!$1:$1048576,M$19,$I47)),INDEX(Dane_Index!$1:$1048576,M$19,$I47),NA()) -> 5881.63 | N47: =IF(ISNUMBER(INDEX(Dane_Index!$1:$1048576,N$19,$I47)),INDEX(Dane_Index!$1:$1048576,N$19,$I47),NA()) -> 5983.87 | O47: =IF(ISNUMBER(INDEX(Dane_Index!$1:$1048576,O$19,$I47)),INDEX(Dane_Index!$1:$1048576,O$19,$I47),NA()) -> 5513.59 | P47: =IF(ISNUMBER(INDEX(Dane_Index!$1:$1048576,P$19,$I47)),INDEX(Dane_Index!$1:$1048576,P$19,$I47),NA()) -> 5131.22 | Q47: =IF(ISNUMBER(INDEX(Dane_Index!$1:$1048576,Q$19,$I47)),INDEX(Dane_Index!$1:$1048576,Q$19,$I47),NA()) -> 9951.79 | R47: =IF(ISNUMBER(INDEX(Dane_Index!$1:$1048576,R$19,$I47)),INDEX(Dane_Index!$1:$1048576,R$19,$I47),NA()) -> 8959.93 | U47: 24 | W47: IV | Z47: =IF(ISNUMBER(X47),X47/Y47,NA()) -> #N/A | AA47: =AVERAGE(Z45:Z47) -> #N/A | AK47: 27 | AL47: 1964 | AM47: 3rd | AN47: Amancio | AO47: Real Madrid | AP47: 38 | AQ47: 26.76
I48: =I47+1 -> 91 | J48: 28 | L48: IV | M48: =IF(ISNUMBER(INDEX(Dane_Index!$1:$1048576,M$19,$I48)),INDEX(Dane_Index!$1:$1048576,M$19,$I48),NA()) -> #N/A | N48: =IF(ISNUMBER(INDEX(Dane_Index!$1:$1048576,N$19,$I48)),INDEX(Dane_Index!$1:$1048576,N$19,$I48),NA()) -> #N/A | O48: =IF(ISNUMBER(INDEX(Dane_Index!$1:$1048576,O$19,$I48)),INDEX(Dane_Index!$1:$1048576,O$19,$I48),NA()) -> #N/A | P48: =IF(ISNUMBER(INDEX(Dane_Index!$1:$1048576,P$19,$I48)),INDEX(Dane_Index!$1:$1048576,P$19,$I48),NA()) -> #N/A | Q48: =IF(ISNUMBER(INDEX(Dane_Index!$1:$1048576,Q$19,$I48)),INDEX(Dane_Index!$1:$1048576,Q$19,$I48),NA()) -> #N/A | R48: =IF(ISNUMBER(INDEX(Dane_Index!$1:$1048576,R$19,$I48)),INDEX(Dane_Index!$1:$1048576,R$19,$I48),NA()) -> #N/A | U48: 25 | V48: =V44+1 -> 2021 | W48: I | Z48: =IF(ISNUMBER(X48),X48/Y48,NA()) -> #N/A | AA48: =AVERAGE(Z46:Z48) -> #N/A | AK48: 28 | AL48: 1965 | AM48: 1st | AN48: EusÃ©bio | AO48: Benfica | AP48: 67 | AQ48: 39.18
U49: 26 | W49: II | Z49: =IF(ISNUMBER(X49),X49/Y49,NA()) -> #N/A | AA49: =AVERAGE(Z47:Z49) -> #N/A | AK49: 29 | AL49: 1965 | AM49: 2nd | AN49: Giacinto Facchetti | AO49: Internazionale | AP49: 59 | AQ49: 34.5
U50: 27 | W50: III | Z50: =IF(ISNUMBER(X50),X50/Y50,NA()) -> #N/A | AA50: =AVERAGE(Z48:Z50) -> #N/A | AK50: 30 | AL50: 1965 | AM50: 3rd | AN50: Luis SuÃ¡rez | AO50: Internazionale | AP50: 45 | AQ50: 26.32
U51: 28 | W51: IV | Z51: =IF(ISNUMBER(X51),X51/Y51,NA()) -> #N/A | AA51: =AVERAGE(Z49:Z51) -> #N/A | AK51: 31 | AL51: 1966 | AM51: 1st | AN51: Bobby Charlton | AO51: Manchester United | AP51: 81 | AQ51: 36.82
AK52: 32 | AL52: 1966 | AM52: 2nd | AN52: EusÃ©bio | AO52: Benfica | AP52: 80 | AQ52: 36.36
AK53: 33 | AL53: 1966 | AM53: 3rd | AN53: Franz Beckenbauer | AO53: Bayern Munich | AP53: 59 | AQ53: 26.82
AK54: 34 | AL54: 1967 | AM54: 1st | AN54: FlÃ³riÃ¡n Albert | AO54: FerencvÃ¡ros | AP54: 68 | AQ54: 46.26
AK55: 35 | AL55: 1967 | AM55: 2nd | AN55: Bobby Charlton | AO55: Manchester United | AP55: 40 | AQ55: 27.21
AK56: 36 | AL56: 1967 | AM56: 3rd | AN56: Jimmy Johnstone | AO56: Celtic | AP56: 39 | AQ56: 26.53
AK57: 37 | AL57: 1968 | AM57: 1st | AN57: George Best | AO57: Manchester United | AP57: 61 | AQ57: 38.12
AK58: 38 | AL58: 1968 | AM58: 2nd | AN58: Bobby Charlton | AO58: Manchester United | AP58: 53 | AQ58: 33.12
AK59: 39 | AL59: 1968 | AM59: 3rd | AN59: Dragan DÅ¾ajiÄ‡ | AO59: Red Star Belgrade | AP59: 46 | AQ59: 28.75
AK60: 40 | AL60: 1969 | AM60: 1st | AN60: Gianni Rivera | AO60: Milan | AP60: 83 | AQ60: 41.5
AK61: 41 | AL61: 1969 | AM61: 2nd | AN61: Luigi Riva | AO61: Cagliari | AP61: 79 | AQ61: 39.5
AK62: 42 | AL62: 1969 | AM62: 3rd | AN62: Gerd MÃ¼ller | AO62: Bayern Munich | AP62: 38 | AQ62: 19
AK63: 43 | AL63: 1970 | AM63: 1st | AN63: Gerd MÃ¼ller | AO63: Bayern Munich | AP63: 77 | AQ63: 36.32
... AK183: 163 | AL183: 2009 | AM183: 3rd | AN183: Xavi | AO183: Barcelona | AP183: 170 | AQ183: 19.41
AK184: 164 | AL184: 2010 | AM184: 1st | AN184: Lionel Messi | AO184: Barcelona | AQ184: 22.65
AK185: 165 | AL185: 2010 | AM185: 2nd | AN185: AndrÃ©s Iniesta | AO185: Barcelona | AQ185: 17.36
AK186: 166 | AL186: 2010 | AM186: 3rd | AN186: Xavi | AO186: Barcelona | AQ186: 16.48
AK187: 167 | AL187: 2011 | AM187: 1st | AN187: Lionel Messi | AO187: Barcelona | AQ187: 47.88
AK188: 168 | AL188: 2011 | AM188: 2nd | AN188: Cristiano Ronaldo | AO188: Real Madrid | AQ188: 21.6
AK189: 169 | AL189: 2011 | AM189: 3rd | AN189: Xavi | AO189: Barcelona | AQ189: 9.23
AK190: 170 | AL190: 2012 | AM190: 1st | AN190: Lionel Messi | AO190: Barcelona | AQ190: 41.6
AK191: 171 | AL191: 2012 | AM191: 2nd | AN191: Cristiano Ronaldo | AO191: Real Madrid | AQ191: 23.68
AK192: 172 | AL192: 2012 | AM192: 3rd | AN192: AndrÃ©s Iniesta | AO192: Barcelona | AQ192: 10.91
AK193: 173 | AL193: 2013 | AM193: 1st | AN193: Cristiano Ronaldo | AO193: Real Madrid | AQ193: 27.99
AK194: 174 | AL194: 2013 | AM194: 2nd | AN194: Lionel Messi | AO194: Barcelona | AQ194: 24.72
AK195: 175 | AL195: 2013 | AM195: 3rd | AN195: Franck RibÃ©ry | AO195: Bayern Munich | AQ195: 23.36
... AK201: 181 | AL201: 2015 | AM201: 3rd | AN201: Neymar | AO201: Barcelona | AQ201: 7.86
AK202: 182 | AL202: 2016 | AM202: 1st | AN202: Cristiano Ronaldo | AO202: Real Madrid | AP202: 745 | AQ202: 59.17
AK203: 183 | AL203: 2016 | AM203: 2nd | AN203: Lionel Messi | AO203: Barcelona | AP203: 316 | AQ203: 25.1
AK204: 184 | AL204: 2016 | AM204: 3rd | AN204: Antoine Griezmann | AO204: AtlÃ©tico Madrid | AP204: 198 | AQ204: 15.73
AK205: 185 | AL205: 2017 | AM205: 1st | AN205: Cristiano Ronaldo | AO205: Real Madrid | AP205: 946 | AQ205: 47.85
AK206: 186 | AL206: 2017 | AM206: 2nd | AN206: Lionel Messi | AO206: Barcelona | AP206: 670 | AQ206: 33.89
AK207: 187 | AL207: 2017 | AM207: 3rd | AN207: Neymar | AO207: Paris Saint-Germain | AP207: 361 | AQ207: 18.26
AK208: 188 | AL208: 2018 | AM208: 1st | AN208: Luka ModriÄ‡ | AO208: Real Madrid | AP208: 753 | AQ208: 45.83
AK209: 189 | AL209: 2018 | AM209: 2nd | AN209: Cristiano Ronaldo | AO209: Juventus | AP209: 476 | AQ209: 28.97
AK210: 190 | AL210: 2018 | AM210: 3rd | AN210: Antoine Griezmann | AO210: AtlÃ©tico Madrid | AP210: 414 | AQ210: 25.2

Sheet Offset
A18: Funkcja Przesunięcie | I18: Zadanie 1 - Biuletyn Statystyczny | Q18: Zadanie 2 - Biuletyn Statystyczny
A19: OFFSET to ciekawa funkcja w przypadku arkuszy GUS | I19: W sztandarowej publikacji GUS Biuletynie Statystycznym, ktoś wpadł na świetny pomysł, aby podawać dane co 2 kolumnę. Zbierzmy je do kupy wykorzystująć OFFSET (Przesunięcie) | Q19: Przekształćmy częstotliwość danych z miesięczną na roczną - użyjmy sumy
I21: Wartości pomocnicze | K21: 0 | L21: 1 | M21: 3 | N21: 26 | O21: 27
A22: Buduje odniesienie do komórki i zakresu znajdującego się w określonej pozycji | I22: LP | J22: Data | K22: =OFFSET(Dane_Offset!$B$5,0,2*K21) -> Ogółem Grand total | L22: =OFFSET(Dane_Offset!$B$5,0,2*L21) -> Górnictwo i wydobywanie Mining and quarrying | M22: =OFFSET(Dane_Offset!$B$5,0,2*M21) -> Przetwórstwo przemysłowe Manufacturing | N22: =OFFSET(Dane_Offset!$B$5,0,2*N21) -> Wytwarzanie i zaopatrywanie w energię elektryczną, gaz, parę wodną i gorącą wodę∆ Electricity, gas, steam and air conditioning supply | O22: =OFFSET(Dane_Offset!$B$5,0,2*O21) -> Dostawa wody; gospodarowanie ściekami i odpadami; rekultywacja∆ Water supply; sewerage, waste management and remediation activities | R22: =K22 -> Ogółem Grand total | S22: =L22 -> Górnictwo i wydobywanie Mining and quarrying | T22: =M22 -> Przetwórstwo przemysłowe Manufacturing | U22: =N22 -> Wytwarzanie i zaopatrywanie w energię elektryczną, gaz, parę wodną i gorącą wodę∆ Electricity, gas, steam and air conditioning supply | V22: =O22 -> Dostawa wody; gospodarowanie ściekami i odpadami; rekultywacja∆ Water supply; sewerage, waste management and remediation activities
B23: =OFFSET(ZAKRES,Nr. Wiersza, Nr. Kolumny) | I23: 1 | J23: 40179 | Q23: 2010
I24: =I23+1 -> 2 | J24: =EOMONTH(J23,0)+1 -> 40210 | Q24: =Q23+1 -> 2011
A25: Gdzie: | I25: =I24+1 -> 3 | J25: =EOMONTH(J24,0)+1 -> 40238 | Q25: =Q24+1 -> 2012
B26: ZAKRES | C26: - | D26: Wybrana przez nas komórka lub zakres | I26: =I25+1 -> 4 | J26: =EOMONTH(J25,0)+1 -> 40269 | Q26: =Q25+1 -> 2013
I27: =I26+1 -> 5 | J27: =EOMONTH(J26,0)+1 -> 40299 | Q27: =Q26+1 -> 2014
B28: Nr. Wiersza | C28: - | D28: O ile komórek w dół przesunąć zakres | I28: =I27+1 -> 6 | J28: =EOMONTH(J27,0)+1 -> 40330 | Q28: =Q27+1 -> 2015
I29: =I28+1 -> 7 | J29: =EOMONTH(J28,0)+1 -> 40360 | Q29: =Q28+1 -> 2016
B30: Nr. Kolumny | C30: - | D30: O ile komórek w prawo przesunąć zakres | I30: =I29+1 -> 8 | J30: =EOMONTH(J29,0)+1 -> 40391 | Q30: =Q29+1 -> 2017
I31: =I30+1 -> 9 | J31: =EOMONTH(J30,0)+1 -> 40422 | Q31: =Q30+1 -> 2018
I32: =I31+1 -> 10 | J32: =EOMONTH(J31,0)+1 -> 40452 | Q32: =Q31+1 -> 2019
A33: Wykonamy 2 zadania, które pokażą nam jej funkcjonalność | I33: =I32+1 -> 11 | J33: =EOMONTH(J32,0)+1 -> 40483 | Q33: =Q32+1 -> 2020
I34: =I33+1 -> 12 | J34: =EOMONTH(J33,0)+1 -> 40513 | Q34: =Q33+1 -> 2021
I35: =I34+1 -> 13 | J35: =EOMONTH(J34,0)+1 -> 40544
I36: =I35+1 -> 14 | J36: =EOMONTH(J35,0)+1 -> 40575
I37: =I36+1 -> 15 | J37: =EOMONTH(J36,0)+1 -> 40603
I38: =I37+1 -> 16 | J38: =EOMONTH(J37,0)+1 -> 40634
I39: =I38+1 -> 17 | J39: =EOMONTH(J38,0)+1 -> 40664
I40: =I39+1 -> 18 | J40: =EOMONTH(J39,0)+1 -> 40695
I41: =I40+1 -> 19 | J41: =EOMONTH(J40,0)+1 -> 40725
I42: =I41+1 -> 20 | J42: =EOMONTH(J41,0)+1 -> 40756
I43: =I42+1 -> 21 | J43: =EOMONTH(J42,0)+1 -> 40787
I44: =I43+1 -> 22 | J44: =EOMONTH(J43,0)+1 -> 40817
I45: =I44+1 -> 23 | J45: =EOMONTH(J44,0)+1 -> 40848
I46: =I45+1 -> 24 | J46: =EOMONTH(J45,0)+1 -> 40878
... I166: =I165+1 -> 144 | J166: =EOMONTH(J165,0)+1 -> 44531

Sheet Dane_Index
B1: CZĘŚĆ II Kwartalne wskaźniki makroekonomiczne
B2: Aktualizacja: | C2: 44588 | F2: Powrót do spisu | BY2: Powrót do spisu
B3: WARUNKI ŻYCIA LUDNOŚCI
B4: Wyszczególnienie A – analogiczny okres roku poprzedniego=100 A1 – od początku roku do końca okresu (analogiczny okres roku poprzedniego=100) B – okres poprzedni=100 | D4: 2000 | H4: 2001 | L4: 2002 | P4: 2003 | T4: 2004 | X4: 2005 | AB4: 2006 | AF4: 2007 | AJ4: 2008 | AN4: 2009 | AR4: 2010 | AV4: 2011 | AZ4: 2012 | BD4: 2013 | BH4: 2014 | BL4: 2015 | BP4: 2016 | BT4: 2017 | BX4: 2018 | CB4: 2019 | CF4: 2020 | CJ4: 2021
D5: 1 kw. | E5: 2 kw. | F5: 3 kw. | G5: 4 kw. | H5: 1 kw. | I5: 2 kw. | J5: 3 kw. | K5: 4 kw. | L5: 1 kw. | M5: 2 kw. | N5: 3 kw. | O5: 4 kw. | P5: 1 kw. | Q5: 2 kw. | R5: 3 kw. | S5: 4 kw. | T5: 1 kw. | U5: 2 kw. | V5: 3 kw. | W5: 4 kw. | X5: 1 kw. | Y5: 2 kw. | Z5: 3 kw. | AA5: 4 kw. | AB5: 1 kw. | AC5: 2 kw. | AD5: 3 kw. | AE5: 4 kw. | AF5: 1 kw. | AG5: 2 kw. | AH5: 3 kw. | AI5: 4 kw. | AJ5: 1 kw. | AK5: 2 kw. | AL5: 3 kw. | AM5: 4 kw. | AN5: 1 kw. | AO5: 2 kw. | AP5: 3 kw. | AQ5: 4 kw. | AR5: 1 kw. | AS5: 2 kw. | AT5: 3 kw. | AU5: 4 kw. | AV5: 1 kw. | AW5: 2 kw. | AX5: 3 kw. | AY5: 4 kw. | AZ5: 1 kw. | BA5: 2 kw. | BB5: 3 kw. | BC5: 4 kw. | BD5: 1 kw. | BE5: 2 kw. | BF5: 3 kw. | BG5: 4 kw. | BH5: 1 kw. | BI5: 2 kw. | BJ5: 3 kw. | BK5: 4 kw. | BL5: 1 kw. | BM5: 2 kw. | BN5: 3 kw. | BO5: 4 kw. | BP5: 1 kw. | BQ5: 2 kw. | BR5: 3 kw. | BS5: 4 kw. | BT5: 1 kw. | BU5: 2 kw. | BV5: 3 kw. | BW5: 4 kw. | BX5: 1 kw. | BY5: 2 kw. | BZ5: 3 kw. | CA5: 4 kw. | CB5: 1 kw. | CC5: 2 kw. | CD5: 3 kw. | CE5: 4 kw. | CF5: 1 kw. | CG5: 2 kw. | CH5: 3 kw. | CI5: 4 kw. | CJ5: 1 kw. | CK5: 2 kw. | CL5: 3 kw. | CM5: 4 kw.
B6: WARUNKI ŻYCIA LUDNOŚCI | D6: 1868.65 | E6: 1869.78 | F6: 1905.76 | G6: 2051.74 | H6: 2043.55 | I6: 2006.92 | J6: 2047.29 | K6: 2152.99 | L6: 2155.54 | M6: 2061.95 | N6: 2095.81 | O6: 2225.41 | P6: 2228.68 | Q6: 2141.01 | R6: 2160.02 | S6: 2276.84 | T6: 2332.17 | U6: 2230.53 | V6: 2269.93 | W6: 2405.46 | X6: 2415.45 | Y6: 2318.53 | Z6: 2347.24 | AA6: 2528.62 | AB6: 2530.18 | AC6: 2427.27 | AD6: 2464.66 | AE6: 2662.51 | AF6: 2709.14 | AG6: 2644.34 | AH6: 2703.41 | AI6: 2899.83 | AJ6: 2983.98 | AK6: 2951.36 | AL6: 2968.55 | AM6: 3096.55 | AN6: 3185.61 | AO6: 3081.48 | AP6: 3113.86 | AQ6: 3243.6 | AR6: 3316.38 | AS6: 3197.85 | AT6: 3203.08 | AU6: 3438.21 | AV6: 3466.33 | AW6: 3366.11 | AX6: 3416 | AY6: 3586.75 | AZ6: 3646.09 | BA6: 3496.82 | BB6: 3510.22 | BC6: 3690.3 | BD6: 3740.05 | BE6: 3612.51 | BF6: 3651.72 | BG6: 3823.32 | BH6: 3895.31 | BI6: 3739.97 | BJ6: 3781.14 | BK6: 3942.67 | BL6: 4054.89 | BM6: 3854.88 | BN6: 3895.33 | BO6: 4066.95 | BP6: 4181.49 | BQ6: 4019.08 | BR6: 4055.04 | BS6: 4218.92 | BT6: 4353.55 | BU6: 4220.69 | BV6: 4255.59 | BW6: 4516.69 | BX6: 4622.84 | BY6: 4521.08 | BZ6: 4580.2 | CA6: 4863.74 | CB6: 4950.94 | CC6: 4839.24 | CD6: 4931.59 | CE6: 5198.58 | CF6: 5331.47 | CG6: 5024.48 | CH6: 5168.93 | CI6: 5457.98 | CJ6: 5681.56 | CK6: 5504.52 | CL6: 5657.3
B7: Przeciętne miesięczne wynagrodzenie nominalne bruttoa w gospodarce narodowej | C7: w zł
C8: A | D8: 115.5 | E8: 112.6 | F8: 111.2 | G8: 110.6 | H8: 109.4 | I8: 107.3 | J8: 107.4 | K8: 104.9 | L8: 105.5 | M8: 102.7 | N8: 102.4 | O8: 103.4 | P8: 103.4 | Q8: 103.8 | R8: 103.1 | S8: 102.3 | T8: 104.6 | U8: 104.2 | V8: 105.1 | W8: 105.6 | X8: 103.6 | Y8: 103.9 | Z8: 103.4 | AA8: 105.1 | AB8: 104.7 | AC8: 104.7 | AD8: 105 | AE8: 105.3 | AF8: 107.1 | AG8: 108.9 | AH8: 109.7 | AI8: 108.9 | AJ8: 110.1 | AK8: 111.6 | AL8: 109.8 | AM8: 106.8 | AN8: 106.8 | AO8: 104.4 | AP8: 104.9 | AQ8: 104.7 | AR8: 104.1 | AS8: 103.8 | AT8: 102.9 | AU8: 106 | AV8: 104.5 | AW8: 105.3 | AX8: 106.6 | AY8: 104.3 | AZ8: 105.2 | BA8: 103.9 | BB8: 102.8 | BC8: 102.9 | BD8: 102.6 | BE8: 103.3 | BF8: 104 | BG8: 103.6 | BH8: 104.2 | BI8: 103.5 | BJ8: 103.5 | BK8: 103.1 | BL8: 104.1 | BM8: 103.1 | BN8: 103 | BO8: 103.2 | BP8: 103.1 | BQ8: 104.3 | BR8: 104.1 | BS8: 103.7 | BT8: 104.1 | BU8: 105 | BV8: 104.9 | BW8: 107.1 | BX8: 106.2 | BY8: 107.1 | BZ8: 107.6 | CA8: 107.7 | CB8: 107.1 | CC8: 107 | CD8: 107.7 | CE8: 106.9 | CF8: 107.7 | CG8: 103.8 | CH8: 104.8 | CI8: 105 | CJ8: 106.6 | CK8: 109.6 | CL8: 109.4
C9: A1 | D9: 115.5 | E9: 114 | F9: 113.1 | G9: 112.9 | H9: 109.4 | I9: 108.4 | J9: 108 | K9: 108.9 | L9: 105.5 | M9: 104.1 | N9: 103.5 | O9: 104.3 | P9: 103.4 | Q9: 103.6 | R9: 103.4 | S9: 104.9 | T9: 104.6 | U9: 104.4 | V9: 104.6 | W9: 104.8 | X9: 103.6 | Y9: 103.8 | Z9: 103.6 | AA9: 104.7 | AB9: 104.7 | AC9: 104.7 | AD9: 104.8 | AE9: 104.9 | AF9: 107.1 | AG9: 108 | AH9: 108.6 | AI9: 108.7 | AJ9: 110.1 | AK9: 110.9 | AL9: 110.4 | AM9: 110.2 | AN9: 106.8 | AO9: 105.6 | AP9: 105.5 | AQ9: 105.5 | AR9: 104.1 | AS9: 103.9 | AT9: 103.5 | AU9: 104 | AV9: 104.5 | AW9: 104.9 | AX9: 105.5 | AY9: 105.4 | AZ9: 105.2 | BA9: 104.6 | BB9: 104 | BC9: 103.5 | BD9: 102.6 | BE9: 102.9 | BF9: 103.3 | BG9: 103.4 | BH9: 104.2 | BI9: 103.9 | BJ9: 103.7 | BK9: 103.4 | BL9: 104.1 | BM9: 103.6 | BN9: 103.4 | BO9: 103.2 | BP9: 103.1 | BQ9: 103.6 | BR9: 103.7 | BS9: 103.6 | BT9: 104.1 | BU9: 104.6 | BV9: 104.9 | BW9: 105.4 | BX9: 106.2 | BY9: 106.7 | BZ9: 106.9 | CA9: 107 | CB9: 107.1 | CC9: 107.1 | CD9: 107.3 | CE9: 107.2 | CF9: 107.7 | CG9: 105.8 | CH9: 105.5 | CI9: 105 | CJ9: 106.6 | CK9: 108 | CL9: 108.5
C10: B | D10: 100.7 | E10: 100.1 | F10: 101.9 | G10: 107.7 | H10: 99.6 | I10: 98.2 | J10: 102 | K10: 105.2 | L10: 100.1 | M10: 95.7 | N10: 101.6 | O10: 106.2 | P10: 100.1 | Q10: 96.1 | R10: 100.9 | S10: 105.4 | T10: 102.4 | U10: 95.6 | V10: 101.8 | W10: 106 | X10: 100.4 | Y10: 96 | Z10: 101.2 | AA10: 107.7 | AB10: 100.1 | AC10: 95.9 | AD10: 101.5 | AE10: 108 | AF10: 101.8 | AG10: 97.6 | AH10: 102.2 | AI10: 107.3 | AJ10: 102.9 | AK10: 98.9 | AL10: 100.6 | AM10: 104.3 | AN10: 102.9 | AO10: 96.7 | AP10: 101.1 | AQ10: 104.2 | AR10: 102.2 | AS10: 96.4 | AT10: 100.2 | AU10: 107.3 | AV10: 100.8 | AW10: 97.1 | AX10: 101.5 | AY10: 105 | AZ10: 101.7 | BA10: 95.9 | BB10: 100.4 | BC10: 105.1 | BD10: 101.3 | BE10: 96.6 | BF10: 101.1 | BG10: 104.7 | BH10: 101.9 | BI10: 96 | BJ10: 101.1 | BK10: 104.3 | BL10: 102.8 | BM10: 95.1 | BN10: 101 | BO10: 104.4 | BP10: 102.8 | BQ10: 96.1 | BR10: 100.9 | BS10: 104 | BT10: 103.2 | BU10: 96.9 | BV10: 100.8 | BW10: 106.1 | BX10: 102.4 | BY10: 97.8 | BZ10: 101.3 | CA10: 106.2 | CB10: 101.8 | CC10: 97.7 | CD10: 101.9 | CE10: 105.4 | CF10: 102.6 | CG10: 94.2 | CH10: 102.9 | CI10: 105.6 | CJ10: 104.1 | CK10: 96.9 | CL10: 102.8
B11: Przeciętne miesięczne wynagrodzenie nominalne brutto w sferze budżetowej | C11: w zł | D11: 2046.43 | E11: 1751.15 | F11: 1813.5 | G11: 2116.43 | H11: 2330.18 | I11: 1932.41 | J11: 1984.64 | K11: 2098.57 | L11: 2492.58 | M11: 1958.86 | N11: 1985.47 | O11: 2149.53 | P11: 2601.11 | Q11: 2098.18 | R11: 2117.08 | S11: 2244.94 | T11: 2736.12 | U11: 2226.77 | V11: 2233.77 | W11: 2342.2 | X11: 2876.89 | Y11: 2304.04 | Z11: 2327.4 | AA11: 2497.59 | AB11: 2986.24 | AC11: 2410.73 | AD11: 2448.6 | AE11: 2640.55 | AF11: 3104.5 | AG11: 2582.76 | AH11: 2582.6 | AI11: 2827 | AJ11: 3334.46 | AK11: 2937.79 | AL11: 2915.76 | AM11: 3219.37 | AN11: 3712.9 | AO11: 3115.23 | AP11: 3110.88 | AQ11: 3304.14 | AR11: 4052 | AS11: 3183.02 | AT11: 3218.1 | AU11: 3566 | AV11: 4260.48 | AW11: 3362.34 | AX11: 3458.77 | AY11: 3715.78 | AZ11: 4485.53 | BA11: 3483.91 | BB11: 3594.17 | BC11: 3841.63 | BD11: 4655.48 | BE11: 3642.41 | BF11: 3744.02 | BG11: 3946.81 | BH11: 4799.57 | BI11: 3750.73 | BJ11: 3807.57 | BK11: 4078.77 | BL11: 4920.47 | BM11: 3840.74 | BN11: 3899.84 | BO11: 4169.68 | BP11: 5004.17 | BQ11: 3982.83 | BR11: 4049.11 | BS11: 4365.79 | BT11: 5162.43 | BU11: 4110.81 | BV11: 4123.05 | BW11: 4613.17 | BX11: 5384.73 | BY11: 4327.32 | BZ11: 4442.46 | CA11: 4850.78 | CB11: 5748.64 | CC11: 4532.04 | CD11: 4858.42 | CE11: 5306.15 | CF11: 6269.83 | CG11: 5007.64 | CH11: 5325.65 | CI11: 5698.13 | CJ11: 6765.85 | CK11: 5292.39 | CL11: 5567.21
C12: A | D12: . | E12: . | F12: . | G12: . | H12: . | I12: . | J12: . | K12: . | L12: . | M12: . | N12: . | O12: . | P12: . | Q12: . | R12: . | S12: . | T12: . | U12: . | V12: . | W12: . | X12: . | Y12: . | Z12: . | AA12: . | AB12: . | AC12: . | AD12: . | AE12: . | AF12: 104 | AG12: 107.1 | AH12: 105.5 | AI12: 107.1 | AJ12: 107.4 | AK12: 113.7 | AL12: 112.9 | AM12: 113.9 | AN12: 111.3 | AO12: 106 | AP12: 106.7 | AQ12: 106.8 | AR12: 109.1 | AS12: 102.1 | AT12: 103.4 | AU12: 107.9 | AV12: 105.1 | AW12: 105.6 | AX12: 107.5 | AY12: 104.2 | AZ12: 105.3 | BA12: 103.6 | BB12: 103.9 | BC12: 103.4 | BD12: 103.8 | BE12: 104.5 | BF12: 104.2 | BG12: 102.7 | BH12: 103.1 | BI12: 103 | BJ12: 101.7 | BK12: 103.3 | BL12: 102.5 | BM12: 102.4 | BN12: 102.4 | BO12: 102.2 | BP12: 101.7 | BQ12: 103.7 | BR12: 103.8 | BS12: 104.7 | BT12: 103.2 | BU12: 103.2 | BV12: 101.8 | BW12: 105.7 | BX12: 104.3 | BY12: 105.3 | BZ12: 107.7 | CA12: 105.2 | CB12: 106.8 | CC12: 104.7 | CD12: 109.4 | CE12: 109.4 | CF12: 109.1 | CG12: 110.5 | CH12: 109.6 | CI12: 107.4 | CJ12: 107.9 | CK12: 105.7 | CL12: 104.5
C13: A1 | D13: . | E13: . | F13: . | G13: . | H13: . | I13: . | J13: . | K13: . | L13: . | M13: . | N13: . | O13: . | P13: . | Q13: . | R13: . | S13: . | T13: . | U13: . | V13: . | W13: . | X13: . | Y13: . | Z13: . | AA13: . | AB13: . | AC13: . | AD13: . | AE13: . | AF13: 104 | AG13: 105.3 | AH13: 105.4 | AI13: 105.8 | AJ13: 107.4 | AK13: 110.4 | AL13: 111.1 | AM13: 111.8 | AN13: 111.3 | AO13: 108.8 | AP13: 108.1 | AQ13: 102.6 | AR13: 109.1 | AS13: 105.9 | AT13: 105.1 | AU13: 105.9 | AV13: 105.1 | AW13: 105.4 | AX13: 106.1 | AY13: 105.6 | AZ13: 105.3 | BA13: 104.5 | BB13: 104.3 | BC13: 104.1 | BD13: 103.8 | BE13: 104.2 | BF13: 104.2 | BG13: 103.8 | BH13: 103.1 | BI13: 103 | BJ13: 102.6 | BK13: 102.8 | BL13: 102.5 | BM13: 102.5 | BN13: 102.5 | BO13: 102.4 | BP13: 101.7 | BQ13: 102.6 | BR13: 103 | BS13: 103.4 | BT13: 103.2 | BU13: 103.2 | BV13: 102.7 | BW13: 103.5 | BX13: 104.3 | BY13: 104.7 | BZ13: 105.7 | CA13: 105.6 | CB13: 106.8 | CC13: 105.9 | CD13: 107 | CE13: 107.6 | CF13: 109.1 | CG13: 109.8 | CH13: 109.7 | CI13: 109.1 | CJ13: 107.9 | CK13: 106.9 | CL13: 106.1
C14: B | D14: . | E14: . | F14: . | G14: . | H14: . | I14: . | J14: . | K14: . | L14: . | M14: . | N14: . | O14: . | P14: . | Q14: . | R14: . | S14: . | T14: . | U14: . | V14: . | W14: . | X14: . | Y14: . | Z14: . | AA14: . | AB14: . | AC14: . | AD14: . | AE14: . | AF14: 117.6 | AG14: 83.2 | AH14: 100 | AI14: 109.5 | AJ14: 118 | AK14: 88.1 | AL14: 99.3 | AM14: 110.4 | AN14: 115.3 | AO14: 83.9 | AP14: 99.9 | AQ14: 106.2 | AR14: 122.6 | AS14: 78.5 | AT14: 101.1 | AU14: 110.8 | AV14: 119.5 | AW14: 78.9 | AX14: 102.9 | AY14: 107.4 | AZ14: 120.7 | BA14: 77.7 | BB14: 103.2 | BC14: 106.9 | BD14: 121.2 | BE14: 78.2 | BF14: 102.8 | BG14: 105.4 | BH14: 121.6 | BI14: 78.1 | BJ14: 101.5 | BK14: 107.1 | BL14: 120.6 | BM14: 78.1 | BN14: 101.5 | BO14: 106.9 | BP14: 120 | BQ14: 79.6 | BR14: 101.7 | BS14: 107.8 | BT14: 118.2 | BU14: 79.6 | BV14: 100.3 | BW14: 111.9 | BX14: 116.7 | BY14: 80.4 | BZ14: 102.7 | CA14: 109.2 | CB14: 118.5 | CC14: 78.8 | CD14: 107.2 | CE14: 109.2 | CF14: 118.2 | CG14: 79.9 | CH14: 106.4 | CI14: 107 | CJ14: 118.7 | CK14: 78.2 | CL14: 105.2
B15: Przeciętne miesięczne wynagrodzenie nominalne brutto w sektorze przedsiębiorstwb | C15: w zł | D15: . | E15: . | F15: . | G15: . | H15: . | I15: . | J15: . | K15: . | L15: . | M15: . | N15: . | O15: . | P15: . | Q15: . | R15: . | S15: . | T15: . | U15: . | V15: . | W15: . | X15: . | Y15: . | Z15: . | AA15: . | AB15: . | AC15: . | AD15: . | AE15: . | AF15: 2737.56 | AG15: 2813.21 | AH15: 2893.07 | AI15: 3106.3 | AJ15: 3057.84 | AK15: 3159.3 | AL15: 3194.23 | AM15: 3329.81 | AN15: 3249.29 | AO15: 3276.94 | AP15: 3317.45 | AQ15: 3456.61 | AR15: 3340.89 | AS15: 3402.05 | AT15: 3385.23 | AU15: 3605.74 | AV15: 3478.91 | AW15: 3573.27 | AX15: 3593.42 | AY15: 3771.08 | AZ15: 3664.16 | BA15: 3681.85 | BB15: 3689.81 | BC15: 3877.5 | BD15: 3740.79 | BE15: 3788.26 | BF15: 3813.25 | BG15: 4005.97 | BH15: 3896.97 | BI15: 3943.91 | BJ15: 3939.22 | BK15: 4139.42 | BL15: 4053.71 | BM15: 4066.34 | BN15: 4081.9 | BO15: 4280.8 | BP15: 4201.91 | BQ15: 4246.21 | BR15: 4254.2 | BS15: 4404.17 | BT15: 4390.54 | BU15: 4477.18 | BV15: 4510.86 | BW15: 4739.91 | BX15: 4700.11 | BY15: 4812.84 | BZ15: 4822.83 | CA15: 5071.41 | CB15: 5015.03 | CC15: 5142.59 | CD15: 5150.15 | CE15: 5368.01 | CF15: 5367.68 | CG15: 5248.83 | CH15: 5371.81 | CI15: 5656.51 | CJ15: 5675.54 | CK15: 5775.25 | CL15: 5885.75 | CM15: 6221.04
C16: A | D16: . | E16: . | F16: . | G16: . | H16: . | I16: . | J16: . | K16: . | L16: . | M16: . | N16: . | O16: . | P16: . | Q16: . | R16: . | S16: . | T16: . | U16: . | V16: . | W16: . | X16: . | Y16: . | Z16: . | AA16: . | AB16: . | AC16: . | AD16: . | AE16: . | AF16: 107.8 | AG16: 109 | AH16: 110.1 | AI16: 110.1 | AJ16: 111.7 | AK16: 112.3 | AL16: 110.4 | AM16: 107.2 | AN16: 106.3 | AO16: 103.7 | AP16: 103.9 | AQ16: 103.8 | AR16: 102.8 | AS16: 103.8 | AT16: 102 | AU16: 104.3 | AV16: 104.1 | AW16: 105 | AX16: 106.1 | AY16: 104.6 | AZ16: 105.3 | BA16: 103 | BB16: 102.7 | BC16: 102.8 | BD16: 102.1 | BE16: 102.9 | BF16: 103.3 | BG16: 103.3 | BH16: 104.2 | BI16: 104.1 | BJ16: 103.3 | BK16: 103.3 | BL16: 104 | BM16: 103.1 | BN16: 103.6 | BO16: 103.4 | BP16: 103.7 | BQ16: 104.4 | BR16: 104.2 | BS16: 102.9 | BT16: 104.5 | BU16: 105.4 | BV16: 106 | BW16: 107.6 | BX16: 107.1 | BY16: 107.5 | BZ16: 106.9 | CA16: 107 | CB16: 106.7 | CC16: 106.9 | CD16: 106.8 | CE16: 105.8 | CF16: 107 | CG16: 102.1 | CH16: 104.3 | CI16: 105.4 | CJ16: 105.7 | CK16: 110 | CL16: 109.6 | CM16: 110
C17: A1 | D17: . | E17: . | F17: . | G17: . | H17: . | I17: . | J17: . | K17: . | L17: . | M17: . | N17: . | O17: . | P17: . | Q17: . | R17: . | S17: . | T17: . | U17: . | V17: . | W17: . | X17: . | Y17: . | Z17: . | AA17: . | AB17: . | AC17: . | AD17: . | AE17: . | AF17: 107.8 | AG17: 108.4 | AH17: 109 | AI17: 109.3 | AJ17: 111.7 | AK17: 112 | AL17: 111.4 | AM17: 110.3 | AN17: 106.3 | AO17: 105 | AP17: 104.6 | AQ17: 104.4 | AR17: 102.8 | AS17: 103.3 | AT17: 102.9 | AU17: 103.3 | AV17: 104.1 | AW17: 104.6 | AX17: 105.1 | AY17: 105 | AZ17: 105.3 | BA17: 104.2 | BB17: 103.7 | BC17: 103.4 | BD17: 102.1 | BE17: 102.5 | BF17: 102.8 | BG17: 102.9 | BH17: 104.2 | BI17: 104.1 | BJ17: 103.9 | BK17: 103.7 | BL17: 104 | BM17: 103.6 | BN17: 103.6 | BO17: 103.5 | BP17: 103.7 | BQ17: 104 | BR17: 104.1 | BS17: 103.8 | BT17: 104.5 | BU17: 105 | BV17: 105.3 | BW17: 105.9 | BX17: 107.1 | BY17: 107.3 | BZ17: 107.2 | CA17: 107.1 | CB17: 106.7 | CC17: 106.8 | CD17: 106.8 | CE17: 106.5 | CF17: 107 | CG17: 104.5 | CH17: 104.5 | CI17: 104.7 | CJ17: 105.7 | CK17: 107.8 | CL17: 108.4 | CM17: 108.8
C18: B | D18: . | E18: . | F18: . | G18: . | H18: . | I18: . | J18: . | K18: . | L18: . | M18: . | N18: . | O18: . | P18: . | Q18: . | R18: . | S18: . | T18: . | U18: . | V18: . | W18: . | X18: . | Y18: . | Z18: . | AA18: . | AB18: . | AC18: . | AD18: . | AE18: . | AF18: 97 | AG18: 102.8 | AH18: 102.8 | AI18: 107.4 | AJ18: 98.4 | AK18: 103.3 | AL18: 101.1 | AM18: 104.2 | AN18: 97.6 | AO18: 100.9 | AP18: 101.2 | AQ18: 104.2 | AR18: 96.7 | AS18: 101.8 | AT18: 99.5 | AU18: 106.5 | AV18: 96.5 | AW18: 102.7 | AX18: 100.6 | AY18: 104.9 | AZ18: 97.2 | BA18: 100.5 | BB18: 100.2 | BC18: 105.1 | BD18: 96.5 | BE18: 101.3 | BF18: 100.7 | BG18: 105.1 | BH18: 97.3 | BI18: 101.2 | BJ18: 99.9 | BK18: 105.1 | BL18: 97.9 | BM18: 100.3 | BN18: 100.4 | BO18: 104.9 | BP18: 98.2 | BQ18: 101.1 | BR18: 100.2 | BS18: 103.5 | BT18: 99.7 | BU18: 102 | BV18: 100.8 | BW18: 105.1 | BX18: 99.2 | BY18: 102.4 | BZ18: 100.2 | CA18: 105.2 | CB18: 98.9 | CC18: 102.5 | CD18: 100.1 | CE18: 104.2 | CF18: 100 | CG18: 97.8 | CH18: 102.3 | CI18: 105.3 | CJ18: 100.3 | CK18: 101.8 | CL18: 101.9 | CM18: 105.7
B19: Przeciętne miesięczne wynagrodzenie nominalne brutto w przemyśleb | C19: w zł | D19: . | E19: . | F19: . | G19: . | H19: . | I19: . | J19: . | K19: . | L19: . | M19: . | N19: . | O19: . | P19: . | Q19: . | R19: . | S19: . | T19: . | U19: . | V19: . | W19: . | X19: . | Y19: . | Z19: . | AA19: . | AB19: . | AC19: . | AD19: . | AE19: . | AF19: 2758.76 | AG19: 2808.46 | AH19: 2889.45 | AI19: 3094.32 | AJ19: 3041.16 | AK19: 3118.55 | AL19: 3161.81 | AM19: 3298 | AN19: 3217.65 | AO19: 3251.63 | AP19: 3290.22 | AQ19: 3482.25 | AR19: 3369.65 | AS19: 3399.35 | AT19: 3457.86 | AU19: 3699.49 | AV19: 3512.11 | AW19: 3639.5 | AX19: 3672.63 | AY19: 3870.18 | AZ19: 3741.88 | BA19: 3772.5 | BB19: 3769.29 | BC19: 4043.1 | BD19: 3825.65 | BE19: 3875.97 | BF19: 3924.55 | BG19: 4192.38 | BH19: 3982.39 | BI19: 4029.35 | BJ19: 4024.99 | BK19: 4292.2 | BL19: 4111.89 | BM19: 4120.43 | BN19: 4124.24 | BO19: 4406.61 | BP19: 4233.42 | BQ19: 4252.65 | BR19: 4315.08 | BS19: 4498.18 | BT19: 4408.47 | BU19: 4504.89 | BV19: 4540.04 | BW19: 4805.63 | BX19: 4705.67 | BY19: 4857.38 | BZ19: 4854.78 | CA19: 5180.9 | CB19: 5035.98 | CC19: 5164.94 | CD19: 5207.63 | CE19: 5448.29 | CF19: 5368.95 | CG19: 5212.61 | CH19: 5397.57 | CI19: 5818.05 | CJ19: 5696.99 | CK19: 5806.87 | CL19: 5881.63
B20: w górnictwie i wydobywaniu | C20: w zł | D20: . | E20: . | F20: . | G20: . | H20: . | I20: . | J20: . | K20: . | L20: . | M20: . | N20: . | O20: . | P20: . | Q20: . | R20: . | S20: . | T20: . | U20: . | V20: . | W20: . | X20: . | Y20: . | Z20: . | AA20: . | AB20: . | AC20: . | AD20: . | AE20: . | AF20: 4532.34 | AG20: 4307.43 | AH20: 4547.95 | AI20: 6381.9 | AJ20: 5061.83 | AK20: 5060.14 | AL20: 4993.06 | AM20: 6749.51 | AN20: 5413.49 | AO20: 5300.98 | AP20: 5187.13 | AQ20: 6972.59 | AR20: 5337.87 | AS20: 5382.49 | AT20: 5327.06 | AU20: 7524.41 | AV20: 5542.68 | AW20: 6163.66 | AX20: 6072.7 | AY20: 7819.66 | AZ20: 5832.17 | BA20: 6415.76 | BB20: 5920.08 | BC20: 8426.77 | BD20: 6060.28 | BE20: 6289.95 | BF20: 6060.89 | BG20: 8615.37 | BH20: 6333.21 | BI20: 6381.69 | BJ20: 6043.74 | BK20: 8771.38 | BL20: 6305.35 | BM20: 6457.98 | BN20: 6135.23 | BO20: 8900.46 | BP20: 6095.89 | BQ20: 6056.33 | BR20: 6798.11 | BS20: 8114.19 | BT20: 6361.6 | BU20: 6598.09 | BV20: 6643.43 | BW20: 9141.98 | BX20: 6442.24 | BY20: 7962.12 | BZ20: 7026.95 | CA20: 10338.03 | CB20: 7511.76 | CC20: 7904.94 | CD20: 7946.79 | CE20: 10482.01 | CF20: 7819.35 | CG20: 8103.16 | CH20: 7601.13 | CI20: 10963.43 | CJ20: 8070.12 | CK20: 8687.24 | CL20: 8450.81
B21: w przetwórstwie przemysłowym | C21: w zł | D21: . | E21: . | F21: . | G21: . | H21: . | I21: . | J21: . | K21: . | L21: . | M21: . | N21: . | O21: . | P21: . | Q21: . | R21: . | S21: . | T21: . | U21: . | V21: . | W21: . | X21: . | Y21: . | Z21: . | AA21: . | AB21: . | AC21: . | AD21: . | AE21: . | AF21: 2516.41 | AG21: 2607.54 | AH21: 2678.25 | AI21: 2741.08 | AJ21: 2783.97 | AK21: 2894.31 | AL21: 2924.7 | AM21: 2904.27 | AN21: 2920.78 | AO21: 2968.47 | AP21: 3016.06 | AQ21: 3051.59 | AR21: 3059.96 | AS21: 3124 | AT21: 3173.8 | AU21: 3229.36 | AV21: 3206.55 | AW21: 3321.82 | AX21: 3352.42 | AY21: 3394.7 | AZ21: 3421.81 | BA21: 3456.98 | BB21: 3463.43 | BC21: 3522.08 | BD21: 3491.43 | BE21: 3559.5 | BF21: 3625.28 | BG21: 3689.73 | BH21: 3663.13 | BI21: 3743.13 | BJ21: 3746.88 | BK21: 3833.55 | BL21: 3818.61 | BM21: 3863.25 | BN21: 3876.86 | BO21: 3971.21 | BP21: 3975 | BQ21: 4042.56 | BR21: 4061.49 | BS21: 4139.24 | BT21: 4181.25 | BU21: 4289.47 | BV21: 4331.12 | BW21: 4441.81 | BX21: 4483.92 | BY21: 4608.97 | BZ21: 4649.04 | CA21: 4790.19 | CB21: 4793.77 | CC21: 4941.42 | CD21: 4962.38 | CE21: 5062.38 | CF21: 5119.22 | CG21: 4965.15 | CH21: 5181.74 | CI21: 5423.43 | CJ21: 5453.83 | CK21: 5595.87 | CL21: 5653.43
B22: w wytwarzaniu i zaopatrywaniu w energię elektryczną, gaz, parę wodną i gorącą wodę∆ | C22: w zł | D22: . | E22: . | F22: . | G22: . | H22: . | I22: . | J22: . | K22: . | L22: . | M22: . | N22: . | O22: . | P22: . | Q22: . | R22: . | S22: . | T22: . | U22: . | V22: . | W22: . | X22: . | Y22: . | Z22: . | AA22: . | AB22: . | AC22: . | AD22: . | AE22: . | AF22: 4171.15 | AG22: 4018.97 | AH22: 4104.74 | AI22: 4424.77 | AJ22: 4534.82 | AK22: 4229.43 | AL22: 4538.22 | AM22: 4933.57 | AN22: 4795.61 | AO22: 4777.12 | AP22: 4802.56 | AQ22: 5168.82 | AR22: 5225.68 | AS22: 4875.77 | AT22: 5220.97 | AU22: 5864.35 | AV22: 5487.46 | AW22: 5338.56 | AX22: 5559.59 | AY22: 6130.62 | AZ22: 5937.3 | BA22: 5334.31 | BB22: 5790.49 | BC22: 6534.72 | BD22: 6195.72 | BE22: 5828.06 | BF22: 6020.95 | BG22: 6736.34 | BH22: 6358.44 | BI22: 6019.6 | BJ22: 6391.82 | BK22: 6747.38 | BL22: 6689.94 | BM22: 6042.42 | BN22: 6302.71 | BO22: 7204.53 | BP22: 7063.92 | BQ22: 6376.78 | BR22: 6572.55 | BS22: 7396.38 | BT22: 6996.8 | BU22: 6809.17 | BV22: 6766.58 | BW22: 7616.42 | BX22: 7706.82 | BY22: 7073.98 | BZ22: 7151.14 | CA22: 7905.97 | CB22: 7802.75 | CC22: 7356 | CD22: 7789.4 | CE22: 8345.57 | CF22: 8382.84 | CG22: 7593.55 | CH22: 7879.29 | CI22: 9051.28 | CJ22: 8772.72 | CK22: 7965.09 | CL22: 8614.93
B23: w dostawie wody; gospodarowaniu ściekami i odpadami; rekultywacji∆ | C23: w zł | D23: . | E23: . | F23: . | G23: . | H23: . | I23: . | J23: . | K23: . | L23: . | M23: . | N23: . | O23: . | P23: . | Q23: . | R23: . | S23: . | T23: . | U23: . | V23: . | W23: . | X23: . | Y23: . | Z23: . | AA23: . | AB23: . | AC23: . | AD23: . | AE23: . | AF23: 2620.64 | AG23: 2620.35 | AH23: 2668.8 | AI23: 2931.04 | AJ23: 2843.44 | AK23: 2917.38 | AL23: 2978.69 | AM23: 3176.5 | AN23: 3080.97 | AO23: 3069.43 | AP23: 3144.56 | AQ23: 3368.53 | AR23: 3275.76 | AS23: 3235.19 | AT23: 3303.62 | AU23: 3530.38 | AV23: 3379.78 | AW23: 3412.54 | AX23: 3465.05 | AY23: 3648.46 | AZ23: 3529.4 | BA23: 3513.13 | BB23: 3535.6 | BC23: 3798.57 | BD23: 3603.23 | BE23: 3609.44 | BF23: 3652.21 | BG23: 3848.19 | BH23: 3697.97 | BI23: 3723.87 | BJ23: 3773.99 | BK23: 4021.32 | BL23: 3842.46 | BM23: 3841.28 | BN23: 3896.36 | BO23: 4159.87 | BP23: 3969.41 | BQ23: 3993.19 | BR23: 4029.34 | BS23: 4310.75 | BT23: 4078.86 | BU23: 4153.81 | BV23: 4172.07 | BW23: 4485.39 | BX23: 4289.94 | BY23: 4319.28 | BZ23: 4422.45 | CA23: 4748.87 | CB23: 4539 | CC23: 4607.63 | CD23: 4696.81 | CE23: 4987.33 | CF23: 4859.51 | CG23: 4788.4 | CH23: 4959.84 | CI23: 5257.28 | CJ23: 5157.79 | CK23: 5126.35 | CL23: 5325.1
B24: Przeciętne miesięczne wynagrodzenie nominalne brutto w budownictwieb | C24: w zł | D24: . | E24: . | F24: . | G24: . | H24: . | I24: . | J24: . | K24: . | L24: . | M24: . | N24: . | O24: . | P24: . | Q24: . | R24: . | S24: . | T24: . | U24: . | V24: . | W24: . | X24: . | Y24: . | Z24: . | AA24: . | AB24: . | AC24: . | AD24: . | AE24: . | AF24: 2649.97 | AG24: 2875.72 | AH24: 3106.4 | AI24: 3256.29 | AJ24: 3095.93 | AK24: 3348.28 | AL24: 3462.01 | AM24: 3546.36 | AN24: 3313.15 | AO24: 3421.19 | AP24: 3518.77 | AQ24: 3591.38 | AR24: 3338.74 | AS24: 3543.42 | AT24: 3537.26 | AU24: 3721.13 | AV24: 3482.35 | AW24: 3683.27 | AX24: 3774.56 | AY24: 3858.28 | AZ24: 3621.67 | BA24: 3647.42 | BB24: 3709.1 | BC24: 3829.46 | BD24: 3555.66 | BE24: 3693.36 | BF24: 3765.91 | BG24: 3895.37 | BH24: 3706.03 | BI24: 3883.56 | BJ24: 3872.05 | BK24: 4084.49 | BL24: 3899.01 | BM24: 4042.29 | BN24: 4111.21 | BO24: 4249.78 | BP24: 4042.8 | BQ24: 4296.46 | BR24: 4257.77 | BS24: 4408.35 | BT24: 4267.02 | BU24: 4466.95 | BV24: 4572.97 | BW24: 4816.68 | BX24: 4592.89 | BY24: 4869.6 | BZ24: 5010.96 | CA24: 5119.68 | CB24: 4873.42 | CC24: 5283.01 | CD24: 5234.73 | CE24: 5462.46 | CF24: 5180.03 | CG24: 5325.21 | CH24: 5490.26 | CI24: 5610.77 | CJ24: 5374.33 | CK24: 5770.24 | CL24: 5983.87
B25: Przeciętne miesięczne wynagrodzenie nominalne brutto w handlu; naprawie pojazdów samochodowych∆, b | C25: w zł | D25: . | E25: . | F25: . | G25: . | H25: . | I25: . | J25: . | K25: . | L25: . | M25: . | N25: . | O25: . | P25: . | Q25: . | R25: . | S25: . | T25: . | U25: . | V25: . | W25: . | X25: . | Y25: . | Z25: . | AA25: . | AB25: . | AC25: . | AD25: . | AE25: . | AF25: 2581.04 | AG25: 2646.61 | AH25: 2706.23 | AI25: 2823.92 | AJ25: 2874.4 | AK25: 2955.63 | AL25: 2940.6 | AM25: 3018.34 | AN25: 3035.15 | AO25: 3058.25 | AP25: 3021.08 | AQ25: 3087.61 | AR25: 3078.68 | AS25: 3170.84 | AT25: 3028.48 | AU25: 3168.17 | AV25: 3212.22 | AW25: 3252.8 | AX25: 3233.43 | AY25: 3369.86 | AZ25: 3356.7 | BA25: 3336.92 | BB25: 3321.95 | BC25: 3365.38 | BD25: 3432.22 | BE25: 3420.62 | BF25: 3407.81 | BG25: 3455.76 | BH25: 3543.91 | BI25: 3577.06 | BJ25: 3532.47 | BK25: 3598.89 | BL25: 3723.97 | BM25: 3703.1 | BN25: 3677.22 | BO25: 3702.12 | BP25: 3887.89 | BQ25: 3934.17 | BR25: 3902 | BS25: 3871.17 | BT25: 4148.02 | BU25: 4201.81 | BV25: 4181.35 | BW25: 4291.26 | BX25: 4443.41 | BY25: 4516.23 | BZ25: 4485.01 | CA25: 4603.43 | CB25: 4751.4 | CC25: 4844.88 | CD25: 4797.29 | CE25: 4908.84 | CF25: 5118.87 | CG25: 5017.82 | CH25: 4976.77 | CI25: 5121.16 | CJ25: 5409.71 | CK25: 5436.56 | CL25: 5513.59
B26: Przeciętne miesięczne wynagrodzenie nominalne brutto w transporcie i gospodarce magazynowejb | C26: w zł | D26: . | E26: . | F26: . | G26: . | H26: . | I26: . | J26: . | K26: . | L26: . | M26: . | N26: . | O26: . | P26: . | Q26: . | R26: . | S26: . | T26: . | U26: . | V26: . | W26: . | X26: . | Y26: . | Z26: . | AA26: . | AB26: . | AC26: . | AD26: . | AE26: . | AF26: 2619.32 | AG26: 2727.61 | AH26: 2808.9 | AI26: 3208.76 | AJ26: 2926.34 | AK26: 3083.51 | AL26: 3178.26 | AM26: 3496.82 | AN26: 3097.86 | AO26: 3143.31 | AP26: 3347.33 | AQ26: 3445.77 | AR26: 3154.8 | AS26: 3207.42 | AT26: 3309.16 | AU26: 3609.11 | AV26: 3343.12 | AW26: 3338.3 | AX26: 3369.97 | AY26: 3683.24 | AZ26: 3356.4 | BA26: 3421.79 | BB26: 3543.33 | BC26: 3815.98 | BD26: 3439.23 | BE26: 3546.87 | BF26: 3588.81 | BG26: 3912.99 | BH26: 3666.32 | BI26: 3650.04 | BJ26: 3710.13 | BK26: 4006.29 | BL26: 3656.08 | BM26: 3757.29 | BN26: 3831.3 | BO26: 4089.43 | BP26: 3767.09 | BQ26: 3884.53 | BR26: 3966.77 | BS26: 4225.82 | BT26: 3906.89 | BU26: 4054.33 | BV26: 4168.34 | BW26: 4523.08 | BX26: 4167.51 | BY26: 4285.75 | BZ26: 4382.28 | CA26: 4723.04 | CB26: 4400.32 | CC26: 4533.99 | CD26: 4637.46 | CE26: 4984.21 | CF26: 4668 | CG26: 4560.35 | CH26: 4742.85 | CI26: 5044.2 | CJ26: 4811.71 | CK26: 4930.98 | CL26: 5131.22
B27: Przeciętne miesięczne wynagrodzenia nominalne brutto w informacji i komunikacjib | C27: w zł | D27: . | E27: . | F27: . | G27: . | H27: . | I27: . | J27: . | K27: . | L27: . | M27: . | N27: . | O27: . | P27: . | Q27: . | R27: . | S27: . | T27: . | U27: . | V27: . | W27: . | X27: . | Y27: . | Z27: . | AA27: . | AB27: . | AC27: . | AD27: . | AE27: . | AF27: 5250.98 | AG27: 5138.05 | AH27: 5141.93 | AI27: 5374.73 | AJ27: 5711.34 | AK27: 5698.12 | AL27: 5758.46 | AM27: 5606.49 | AN27: 6153.86 | AO27: 5853.55 | AP27: 5839.58 | AQ27: 5882.61 | AR27: 6352.91 | AS27: 6040.2 | AT27: 6054.32 | AU27: 6273.27 | AV27: 6648.14 | AW27: 6424.38 | AX27: 6361.01 | AY27: 6325.07 | AZ27: 6550.16 | BA27: 6474.85 | BB27: 6492.58 | BC27: 6379.39 | BD27: 6685.11 | BE27: 6707.32 | BF27: 6653.69 | BG27: 6694.95 | BH27: 6986.53 | BI27: 6835.14 | BJ27: 6834.51 | BK27: 6889.25 | BL27: 7299.99 | BM27: 7280.78 | BN27: 7142.81 | BO27: 7171.27 | BP27: 7599.24 | BQ27: 7593.05 | BR27: 7316.85 | BS27: 7762.5 | BT27: 7879.1 | BU27: 7864.12 | BV27: 7825.5 | BW27: 7948.16 | BX27: 8500.58 | BY27: 8458.7 | BZ27: 8276.44 | CA27: 8477.04 | CB27: 8896.65 | CC27: 8964.9 | CD27: 8492.08 | CE27: 8811.58 | CF27: 9457.34 | CG27: 9073.65 | CH27: 9191.28 | CI27: 9279.29 | CJ27: 10007.26 | CK27: 9968.64 | CL27: 9951.79
B28: Przeciętne miesięczne wynagrodzenie nominalne brutto w działalności finansowej i ubezpieczeniowejb | C28: w zł | D28: . | E28: . | F28: . | G28: . | H28: . | I28: . | J28: . | K28: . | L28: . | M28: . | N28: . | O28: . | P28: . | Q28: . | R28: . | S28: . | T28: . | U28: . | V28: . | W28: . | X28: . | Y28: . | Z28: . | AA28: . | AB28: . | AC28: . | AD28: . | AE28: . | AF28: 5246.59 | AG28: 5230.34 | AH28: 4844.45 | AI28: 5175.67 | AJ28: 5867.97 | AK28: 5281.48 | AL28: 5154.98 | AM28: 5128.81 | AN28: 5885.23 | AO28: 5486.68 | AP28: 5197.96 | AQ28: 5562.53 | AR28: 5736.51 | AS28: 5760.03 | AT28: 5624.49 | AU28: 5570.99 | AV28: 6229.06 | AW28: 6278.34 | AX28: 5877.77 | AY28: 5823.23 | AZ28: 6386.96 | BA28: 6688.26 | BB28: 5875.47 | BC28: 6043.73 | BD28: 6338.95 | BE28: 6702.46 | BF28: 6066.13 | BG28: 6602.17 | BH28: 6747.09 | BI28: 6737.54 | BJ28: 6360.07 | BK28: 6231.48 | BL28: 7240.12 | BM28: 6906 | BN28: 6583.08 | BO28: 6820.58 | BP28: 7329.59 | BQ28: 7017.37 | BR28: 6936.01 | BS28: 6965.46 | BT28: 7680.19 | BU28: 7617.38 | BV28: 7158.32 | BW28: 7354.18 | BX28: 8190.82 | BY28: 8006.79 | BZ28: 7562.98 | CA28: 7767.1 | CB28: 8539.55 | CC28: 8150.59 | CD28: 8095.63 | CE28: 8159.23 | CF28: 9461.46 | CG28: 8757.83 | CH28: 8060.39 | CI28: 8308.22 | CJ28: 9555.71 | CK28: 8986.86 | CL28: 8959.93
B29: Przeciętne miesięczne wynagrodzenie nominalne brutto w obsłudze rynku nieruchomości∆, b | C29: w zł | D29: . | E29: . | F29: . | G29: . | H29: . | I29: . | J29: . | K29: . | L29: . | M29: . | N29: . | O29: . | P29: . | Q29: . | R29: . | S29: . | T29: . | U29: . | V29: . | W29: . | X29: . | Y29: . | Z29: . | AA29: . | AB29: . | AC29: . | AD29: . | AE29: . | AF29: 2854.7 | AG29: 2834.94 | AH29: 2894.95 | AI29: 3211.36 | AJ29: 3136.86 | AK29: 3251.09 | AL29: 3270.41 | AM29: 3441.57 | AN29: 3383.02 | AO29: 3368.69 | AP29: 3365.45 | AQ29: 3570.2 | AR29: 3529.3 | AS29: 3194.28 | AT29: 3456.63 | AU29: 3782.73 | AV29: 3646.49 | AW29: 3642.59 | AX29: 3646.6 | AY29: 3929,,47 | AZ29: 3873.79 | BA29: 3777.55 | BB29: 3789.73 | BC29: 4073.1 | BD29: 4032.31 | BE29: 3967.29 | BF29: 3943.98 | BG29: 4203.31 | BH29: 4136.72 | BI29: 4119.11 | BJ29: 4136.31 | BK29: 4380.39 | BL29: 4300.89 | BM29: 4285.58 | BN29: 4284.45 | BO29: 4556.11 | BP29: 4539.52 | BQ29: 4439.91 | BR29: 4481.77 | BS29: 4801.53 | BT29: 4752.7 | BU29: 4757.94 | BV29: 4688.96 | BW29: 5155.13 | BX29: 5028.33 | BY29: 4859.47 | BZ29: 5015.77 | CA29: 5353.74 | CB29: 5280.34 | CC29: 5187.8 | CD29: 5326.47 | CE29: 5560.94 | CF29: 5635.9 | CG29: 5390.4 | CH29: 5638.6 | CI29: 5953.94 | CJ29: 5916.96 | CK29: 5815.15 | CL29: 5875.02
B30: Przeciętne miesięczne wynagrodzenie nominalne brutto w edukacjib | C30: w zł | D30: . | E30: . | F30: . | G30: . | H30: . | I30: . | J30: . | K30: . | L30: . | M30: . | N30: . | O30: . | P30: . | Q30: . | R30: . | S30: . | T30: . | U30: . | V30: . | W30: . | X30: . | Y30: . | Z30: . | AA30: . | AB30: . | AC30: . | AD30: . | AE30: . | AF30: 3048.69 | AG30: 2538 | AH30: 2614.54 | AI30: 2689.73 | AJ30: 3222.94 | AK30: 2814.22 | AL30: 2861.03 | AM30: 2937.51 | AN30: 3567.57 | AO30: 2959.27 | AP30: 3054.47 | AQ30: 3114.84 | AR30: 3923.53 | AS30: 3052.89 | AT30: 3189.94 | AU30: 3406.14 | AV30: 4147.57 | AW30: 3233.92 | AX30: 3423.16 | AY30: 3592.67 | AZ30: 4393.47 | BA30: 3389.63 | BB30: 3602.93 | BC30: 3701.38 | BD30: 4495.25 | BE30: 3538.03 | BF30: 3817.72 | BG30: 3846.46 | BH30: 4666.2 | BI30: 3647.96 | BJ30: 3865.57 | BK30: 3991.45 | BL30: 4787.16 | BM30: 3755.54 | BN30: 3991.99 | BO30: 4110.45 | BP30: 4854.01 | BQ30: 3834.87 | BR30: 3975.44 | BS30: 4120.75 | BT30: 4919.77 | BU30: 3936.18 | BV30: 3979.36 | BW30: 4280.5 | BX30: 5045.56 | BY30: 4120.34 | BZ30: 4276.01 | CA30: 4500.93 | CB30: 5437.43 | CC30: 4248.49 | CD30: 4738.32 | CE30: 5076.52 | CF30: 5949.75 | CG30: 4707.42 | CH30: 5108.12 | CI30: 5447.41 | CJ30: 6441.43 | CK30: 5144.19 | CL30: 5426.6
B31: Przeciętne miesięczne wynagrodzenie nominalne brutto w opiece zdrowotnej i pomocy społecznejb | C31: w zł | D31: . | E31: . | F31: . | G31: . | H31: . | I31: . | J31: . | K31: . | L31: . | M31: . | N31: . | O31: . | P31: . | Q31: . | R31: . | S31: . | T31: . | U31: . | V31: . | W31: . | X31: . | Y31: . | Z31: . | AA31: . | AB31: . | AC31: . | AD31: . | AE31: . | AF31: 2473.09 | AG31: 2390.53 | AH31: 2466.83 | AI31: 2681.89 | AJ31: 2845.13 | AK31: 2829.7 | AL31: 2931.58 | AM31: 3115.69 | AN31: 3157.58 | AO31: 3009.09 | AP31: 3121.33 | AQ31: 3165.16 | AR31: 3248.46 | AS31: 3109.26 | AT31: 3179.01 | AU31: 3260.62 | AV31: 3322.19 | AW31: 3196.68 | AX31: 3263.63 | AY31: 3329.47 | AZ31: 3414.98 | BA31: 3280.33 | BB31: 3321.03 | BC31: 3427.84 | BD31: 3499.19 | BE31: 3347.31 | BF31: 3398.83 | BG31: 3546.87 | BH31: 3571.33 | BI31: 3428.23 | BJ31: 3516 | BK31: 3595.39 | BL31: 3683.53 | BM31: 3502.5 | BN31: 3562.71 | BO31: 3813.08 | BP31: 3856.44 | BQ31: 3675.37 | BR31: 3772.58 | BS31: 3969.99 | BT31: 4031.92 | BU31: 3903.05 | BV31: 4009.1 | BW31: 4356.78 | BX31: 4378.72 | BY31: 4219.71 | BZ31: 4459.92 | CA31: 4884.72 | CB31: 4911.4 | CC31: 4741.9 | CD31: 5008.5 | CE31: 5130.75 | CF31: 5261.99 | CG31: 5039.86 | CH31: 5405.88 | CI31: 5770.81 | CJ31: 6235.26 | CK31: 6294.06 | CL31: 6300.18
B32: Przeciętne miesięczne wynagrodzenie realne brutto w gospodarce narodowej | C32: A | D32: . | E32: . | F32: . | G32: . | H32: . | I32: . | J32: . | K32: . | L32: . | M32: . | N32: . | O32: . | P32: . | Q32: . | R32: . | S32: . | T32: . | U32: . | V32: . | W32: . | X32: . | Y32: . | Z32: . | AA32: . | AB32: . | AC32: . | AD32: . | AE32: . | AF32: 105.2 | AG32: 106.5 | AH32: 107.8 | AI32: 105.4 | AJ32: 106 | AK32: 107.2 | AL32: 105.1 | AM32: 103.2 | AN32: 103.7 | AO32: 100.9 | AP32: 101.5 | AQ32: 101.4 | AR32: 101.1 | AS32: 101.5 | AT32: 100.8 | AU32: 103.2 | AV32: 100.8 | AW32: 100.9 | AX32: 102.5 | AY32: 99.9 | AZ32: 101.2 | BA32: 100 | BB32: 99.1 | BC32: 100.1 | BD32: 101.3 | BE32: 102.8 | BF32: 103 | BG32: 102.9 | BH32: 103.7 | BI32: 103.2 | BJ32: 103.7 | BK32: 103.8 | BL32: 105.8 | BM32: 104.1 | BN32: 103.8 | BO32: 104 | BP32: 104.1 | BQ32: 105.4 | BR32: 104.9 | BS32: 103.4 | BT32: 102.1 | BU32: 103.1 | BV32: 103 | BW32: 105 | BX32: 104.7 | BY32: 105.3 | BZ32: 105.5 | CA32: 106.2 | CB32: 105.7 | CC32: 104.5 | CD32: 104.9 | CE32: 104.1 | CF32: 103.2 | CG32: 100.8 | CH32: 101.8 | CI32: 102.2 | CJ32: 103.8 | CK32: 104.8 | CL32: 103.7
C33: A1 | D33: . | E33: . | F33: . | G33: . | H33: . | I33: . | J33: . | K33: . | L33: . | M33: . | N33: . | O33: . | P33: . | Q33: . | R33: . | S33: . | T33: . | U33: . | V33: . | W33: . | X33: . | Y33: . | Z33: . | AA33: . | AB33: . | AC33: . | AD33: . | AE33: . | AF33: 105.2 | AG33: 103.2 | AH33: 106.5 | AI33: 105.5 | AJ33: 106 | AK33: 103 | AL33: 106 | AM33: 106 | AN33: 103.7 | AO33: 102.2 | AP33: 102.1 | AQ33: 102.1 | AR33: 101.1 | AS33: 101.2 | AT33: 101 | AU33: 101.5 | AV33: 100.8 | AW33: 100.9 | AX33: 101.4 | AY33: 101.2 | AZ33: 101.2 | BA33: 100.7 | BB33: 100.1 | BC33: 99.9 | BD33: 101.3 | BE33: 102 | BF33: 102.4 | BG33: 102.5 | BH33: 103.7 | BI33: 103.5 | BJ33: 103.5 | BK33: 103.4 | BL33: 105.8 | BM33: 105 | BN33: 104.6 | BO33: 104.2 | BP33: 104.1 | BQ33: 104.6 | BR33: 104.6 | BS33: 104.2 | BT33: 102.1 | BU33: 102.6 | BV33: 103 | BW33: 103.4 | BX33: 104.7 | BY33: 105.1 | BZ33: 105.1 | CA33: 105.3 | CB33: 105.7 | CC33: 105.2 | CD33: 105.1 | CE33: 104.8 | CF33: 103.2 | CG33: 102 | CH33: 102 | CI33: 101.7 | CJ33: 103.8 | CK33: 104.1 | CL33: 104
C34: B | D34: . | E34: . | F34: . | G34: . | H34: . | I34: . | J34: . | K34: . | L34: . | M34: . | N34: . | O34: . | P34: . | Q34: . | R34: . | S34: . | T34: . | U34: . | V34: . | W34: . | X34: . | Y34: . | Z34: . | AA34: . | AB34: . | AC34: . | AD34: . | AE34: . | AF34: 101.2 | AG34: 96.4 | AH34: 102.2 | AI34: 105.7 | AJ34: 101.5 | AK34: 97.6 | AL34: 100.3 | AM34: 103.8 | AN34: 101.9 | AO34: 95 | AP34: 100.9 | AQ34: 104 | AR34: 101.4 | AS34: 95.4 | AT34: 100.2 | AU34: 106.3 | AV34: 98.9 | AW34: 95.7 | AX34: 101.8 | AY34: 103.7 | AZ34: 100.1 | BA34: 94.8 | BB34: 100.8 | BC34: 104.7 | BD34: 101.2 | BE34: 96.2 | BF34: 101.1 | BG34: 104.6 | BH34: 101.7 | BI34: 96 | BJ34: 101.6 | BK34: 104.7 | BL34: 103.4 | BM34: 94.6 | BN34: 101.4 | BO34: 104.7 | BP34: 103.5 | BQ34: 95.6 | BR34: 101.2 | BS34: 103.2 | BT34: 102.2 | BU34: 96.6 | BV34: 101.1 | BW34: 104.9 | BX34: 102.1 | BY34: 97.2 | BZ34: 101.3 | CA34: 105.7 | CB34: 101.6 | CC34: 96.1 | CD34: 101.6 | CE34: 104.8 | CF34: 100.7 | CG34: 94 | CH34: 102.7 | CI34: 105.2 | CJ34: 102.1 | CK34: 95.1 | CL34: 101.7
B35: Przeciętne miesięczne wynagrodzenie realne brutto w sektorze przedsiębiorstwb | C35: A | D35: . | E35: . | F35: . | G35: . | H35: . | I35: . | J35: . | K35: . | L35: . | M35: . | N35: . | O35: . | P35: . | Q35: . | R35: . | S35: . | T35: . | U35: . | V35: . | W35: . | X35: . | Y35: . | Z35: . | AA35: . | AB35: . | AC35: . | AD35: . | AE35: . | AF35: 105.9 | AG35: 106.5 | AH35: 108.2 | AI35: 106.6 | AJ35: 107.5 | AK35: 107.9 | AL35: 105.6 | AM35: 103.6 | AN35: 103.2 | AO35: 100.2 | AP35: 100.5 | AQ35: 100.5 | AR35: 99.8 | AS35: 101.5 | AT35: 99.9 | AU35: 101.6 | AV35: 100.4 | AW35: 100.6 | AX35: 102 | AY35: 100.2 | AZ35: 101.3 | BA35: 99.1 | BB35: 99 | BC35: 100 | BD35: 100.8 | BE35: 102.4 | BF35: 102.3 | BG35: 102.6 | BH35: 103.7 | BI35: 103.8 | BJ35: 103.5 | BK35: 104 | BL35: 105.7 | BM35: 104.1 | BN35: 104.4 | BO35: 104.2 | BP35: 104.7 | BQ35: 105.5 | BR35: 105 | BS35: 102.6 | BT35: 102.5 | BU35: 103.5 | BV35: 104.1 | BW35: 105.5 | BX35: 105.6 | BY35: 105.7 | BZ35: 104.8 | CA35: 105.5 | CB35: 105.3 | CC35: 104.4 | CD35: 104 | CE35: 103 | CF35: 102.5 | CG35: 99.1 | CH35: 101.4 | CI35: 102.6 | CJ35: 102.9 | CK35: 105.2 | CL35: 103.9 | CM35: 102
C36: A1 | D36: . | E36: . | F36: . | G36: . | H36: . | I36: . | J36: . | K36: . | L36: . | M36: . | N36: . | O36: . | P36: . | Q36: . | R36: . | S36: . | T36: . | U36: . | V36: . | W36: . | X36: . | Y36: . | Z36: . | AA36: . | AB36: . | AC36: . | AD36: . | AE36: . | AF36: 105.9 | AG36: 106.2 | AH36: 106.9 | AI36: 106.8 | AJ36: 107.5 | AK36: 107.7 | AL36: 106.9 | AM36: 106.1 | AN36: 103.2 | AO36: 101.6 | AP36: 101.3 | AQ36: 101.1 | AR36: 99.8 | AS36: 100.6 | AT36: 100.4 | AU36: 100.8 | AV36: 100.4 | AW36: 100.6 | AX36: 101.1 | AY36: 100.9 | AZ36: 101.3 | BA36: 100.3 | BB36: 99.8 | BC36: 99.8 | BD36: 100.8 | BE36: 101.6 | BF36: 101.9 | BG36: 102 | BH36: 103.7 | BI36: 103.7 | BJ36: 103.7 | BK36: 103.7 | BL36: 105.7 | BM36: 105 | BN36: 104.8 | BO36: 104.5 | BP36: 104.7 | BQ36: 105.1 | BR36: 105 | BS36: 104.4 | BT36: 102.5 | BU36: 103 | BV36: 103.4 | BW36: 103.9 | BX36: 105.6 | BY36: 105.7 | BZ36: 105.4 | CA36: 105.4 | CB36: 105.3 | CC36: 104.9 | CD36: 104.6 | CE36: 104.1 | CF36: 102.5 | CG36: 100.8 | CH36: 101.1 | CI36: 101.5 | CJ36: 102.9 | CK36: 104 | CL36: 103.9 | CM36: 103.4
C37: B | D37: . | E37: . | F37: . | G37: . | H37: . | I37: . | J37: . | K37: . | L37: . | M37: . | N37: . | O37: . | P37: . | Q37: . | R37: . | S37: . | T37: . | U37: . | V37: . | W37: . | X37: . | Y37: . | Z37: . | AA37: . | AB37: . | AC37: . | AD37: . | AE37: . | AF37: 96.4 | AG37: 101.6 | AH37: 102.8 | AI37: 105.8 | AJ37: 97 | AK37: 102 | AL37: 100.8 | AM37: 103.7 | AN37: 96.6 | AO37: 99.1 | AP37: 101 | AQ37: 104 | AR37: 95.9 | AS37: 100.8 | AT37: 99.5 | AU37: 105.6 | AV37: 94.7 | AW37: 101.2 | AX37: 100.9 | AY37: 103.6 | AZ37: 95.7 | BA37: 99.3 | BB37: 100.6 | BC37: 104.7 | BD37: 96.4 | BE37: 100.9 | BF37: 100.7 | BG37: 105 | BH37: 97.1 | BI37: 101.2 | BJ37: 100.4 | BK37: 105.5 | BL37: 98.5 | BM37: 99.8 | BN37: 100.8 | BO37: 105.2 | BP37: 98.9 | BQ37: 100.6 | BR37: 100.5 | BS37: 102.7 | BT37: 98.7 | BU37: 101.7 | BV37: 101.1 | BW37: 104 | BX37: 98.9 | BY37: 101.8 | BZ37: 100.2 | CA37: 104.7 | CB37: 98.7 | CC37: 100.8 | CD37: 99.8 | CE37: 103.6 | CF37: 98.1 | CG37: 97.6 | CH37: 102.1 | CI37: 104.9 | CJ37: 98.3 | CK37: 99.9 | CL37: 100.8 | CM37: 103
B38: Przeciętna liczba emerytów i rencistów pobierających emerytury i renty z pozarolniczego systemu ubezpieczeń społecznych | C38: w tys. | D38: 7549 | E38: 7543.8 | F38: 7510.7 | G38: 7497.2 | H38: 7490.6 | I38: 7481 | J38: 7456.6 | K38: 7447.5 | L38: 7446.2 | M38: 7445.3 | N38: 7430.2 | O38: 7433.9 | P38: 7445.4 | Q38: 7451.1 | R38: 7450.7 | S38: 7456.1 | T38: 7484.1 | U38: 7508.6 | V38: 7506.1 | W38: 7515.6 | X38: 7525.2 | Y38: 7521.5 | Z38: 7521.7 | AA38: 7527.7 | AB38: 7541.3 | AC38: 7559.5 | AD38: 7568.9 | AE38: 7588.9 | AF38: 7623.5 | AG38: 7654.3 | AH38: 7667.1 | AI38: 7689.9 | AJ38: 7719.7 | AK38: 7739.5 | AL38: 7810 | AM38: 7848.2 | AN38: 7888.9 | AO38: 7916.7 | AP38: 7919.6 | AQ38: 7900.6 | AR38: 7892.5 | AS38: 7883.6 | AT38: 7862.8 | AU38: 7835.7 | AV38: 7828.4 | AW38: 7812.1 | AX38: 7798.1 | AY38: 7748.1 | AZ38: 7751.9 | BA38: 7743.6 | BB38: 7740 | BC38: 7731.2 | BD38: 7730.9 | BE38: 7718.4 | BF38: 7696.1 | BG38: 7679.2 | BH38: 7671.6 | BI38: 7656.5 | BJ38: 7649.4 | BK38: 7657.1 | BL38: 7669.9 | BM38: 7677.7 | BN38: 7675.5 | BO38: 7682.8 | BP38: 7699.5 | BQ38: 7713.9 | BR38: 7716.5 | BS38: 7728 | BT38: 7730.3 | BU38: 7730.9 | BV38: 7729.3 | BW38: 7849 | BX38: 7995.6 | BY38: 8026.8 | BZ38: 8046.1 | CA38: 8097.6 | CB38: 8123.3 | CC38: 8140.2 | CD38: 8146.3 | CE38: 8200.3 | CF38: 8209.6 | CG38: 8227.6 | CH38: 8236.1 | CI38: 8274.1 | CJ38: 8251.3 | CK38: 8236.9 | CL38: 8226.2
B39: Przeciętna miesięczna nominalna emerytura i renta brutto z pozarolniczego systemu ubezpieczeń społecznych | C39: w zł | D39: 849.89 | E39: 863.9 | F39: 892.49 | G39: 895.8 | H39: 900.14 | I39: 940.07 | J39: 1021.47 | K39: 1026.01 | L39: 1029.94 | M39: 1034.89 | N39: 1043.85 | O39: 1048.71 | P39: 1064.73 | Q39: 1095.32 | R39: 1100.59 | S39: 1109.07 | T39: 1123.51 | U39: 1139.93 | V39: 1144.4 | W39: 1155.84 | X39: 1160,10d | Y39: 1168,89d | Z39: 1174,21d | AA39: 1179,75d | AB39: 1213.1 | AC39: 1271.13 | AD39: 1276.45 | AE39: 1282.41 | AF39: 1288.27 | AG39: 1296.74 | AH39: 1302.28 | AI39: 1307.92 | AJ39: 1346.76 | AK39: 1433.44 | AL39: 1444.07 | AM39: 1449.48 | AN39: 1486.37 | AO39: 1557.11 | AP39: 1559.94 | AQ39: 1566.94 | AR39: 1595.29 | AS39: 1652.07 | AT39: 1657.92 | AU39: 1666.61 | AV39: 1690.48 | AW39: 1735.03 | AX39: 1738.45 | AY39: 1745.33 | AZ39: 1775.07 | BA39: 1832.96 | BB39: 1834.59 | BC39: 1841.31 | BD39: 1877.38 | BE39: 1930.18 | BF39: 1934.81 | BG39: 1942.82 | BH39: 1959.26 | BI39: 2003.18 | BJ39: 2000.01 | BK39: 2002.18 | BL39: 2020.29 | BM39: 2050.57 | BN39: 2058.43 | BO39: 2067.69 | BP39: 2074.88 | BQ39: 2083.89 | BR39: 2090.18 | BS39: 2096.41 | BT39: 2109.47 | BU39: 2129.56 | BV39: 2138.83 | BW39: 2173.72 | BX39: 2183.64 | BY39: 2225.02 | BZ39: 2236.01 | CA39: 2242.57 | CB39: 2273.6 | CC39: 2336.77 | CD39: 2348.53 | CE39: 2352.44 | CF39: 2393.39 | CG39: 2457.7 | CH39: 2480.83 | CI39: 2487.98 | CJ39: 2569.42 | CK39: 2618.17 | CL39: 2643.2
C40: A | D40: 100.4 | E40: 108.7 | F40: 105.8 | G40: 105.8 | H40: 105.9 | I40: 108.8 | J40: 114.5 | K40: 114.5 | L40: 114.4 | M40: 110.1 | N40: 102.2 | O40: 102.2 | P40: 103.4 | Q40: 105.8 | R40: 105.4 | S40: 105.8 | T40: 105.5 | U40: 104.1 | V40: 104 | W40: 104.2 | X40: 103.3 | Y40: 102.5 | Z40: 102.6 | AA40: 102.1 | AB40: 104.6 | AC40: 108.7 | AD40: 108.7 | AE40: 108.7 | AF40: 106.2 | AG40: 102 | AH40: 102 | AI40: 102 | AJ40: 104.5 | AK40: 110.5 | AL40: 110.9 | AM40: 110.8 | AN40: 110.4 | AO40: 108.6 | AP40: 108 | AQ40: 108.1 | AR40: 107.3 | AS40: 106.1 | AT40: 106.3 | AU40: 106.4 | AV40: 106 | AW40: 105 | AX40: 104.9 | AY40: 104.7 | AZ40: 105 | BA40: 105.6 | BB40: 105.5 | BC40: 105.5 | BD40: 105.8 | BE40: 105.3 | BF40: 105.5 | BG40: 105.5 | BH40: 104.4 | BI40: 103.8 | BJ40: 103.4 | BK40: 103.1 | BL40: 103.1 | BM40: 102.4 | BN40: 102.9 | BO40: 103.3 | BP40: 102.7 | BQ40: 101.6 | BR40: 101.5 | BS40: 101.4 | BT40: 101.7 | BU40: 102.2 | BV40: 102.3 | BW40: 103.7 | BX40: 103.5 | BY40: 104.5 | BZ40: 104.5 | CA40: 103.2 | CB40: 104.1 | CC40: 105 | CD40: 105 | CE40: 104.9 | CF40: 105.3 | CG40: 105.2 | CH40: 105.6 | CI40: 105.8 | CJ40: 107.4 | CK40: 106.5 | CL40: 106.5
C41: A1 | D41: 110.4 | E41: 109.5 | F41: 108.2 | G41: 107.6 | H41: 105.9 | I41: 107.4 | J41: 109.8 | K41: 111 | L41: 114.4 | M41: 112.2 | N41: 108.6 | O41: 106.9 | P41: 103.4 | Q41: 104.6 | R41: 104.9 | S41: 105.1 | T41: 105.5 | U41: 104.8 | V41: 104.5 | W41: 104.4 | X41: 103.3 | Y41: 102.9 | Z41: 102.8 | AA41: 102.6 | AB41: 104.6 | AC41: 106.7 | AD41: 107.4 | AE41: 107.7 | AF41: 106.2 | AG41: 104.1 | AH41: 103.4 | AI41: 103 | AJ41: 104.5 | AK41: 107.6 | AL41: 108.7 | AM41: 109.2 | AN41: 110.4 | AO41: 109.5 | AP41: 109 | AQ41: 108.7 | AR41: 107.3 | AS41: 106.7 | AT41: 106.6 | AU41: 106.5 | AV41: 106 | AW41: 105.5 | AX41: 105.3 | AY41: 105.2 | AZ41: 105 | BA41: 105.3 | BB41: 105.4 | BC41: 105.4 | BD41: 105.8 | BE41: 105.5 | BF41: 105.5 | BG41: 105.5 | BH41: 104.4 | BI41: 104.1 | BJ41: 103.8 | BK41: 103.6 | BL41: 103.1 | BM41: 102.7 | BN41: 102.8 | BO41: 102.9 | BP41: 102.7 | BQ41: 102.2 | BR41: 102 | BS41: 101.8 | BT41: 101.7 | BU41: 101.9 | BV41: 102.1 | BW41: 102.5 | BX41: 103.5 | BY41: 104 | BZ41: 104.2 | CA41: 103.9 | CB41: 104.1 | CC41: 104.6 | CD41: 104.7 | CE41: 104.7 | CF41: 105.3 | CG41: 105.2 | CH41: 105.4 | CI41: 105.5 | CJ41: 107.4 | CK41: 106.9 | CL41: 106.8
C42: B | D42: 100.4 | E42: 101.6 | F42: 103.3 | G42: 100.4 | H42: 100.5 | I42: 104.4 | J42: 108.7 | K42: 100.4 | L42: 100.4 | M42: 100.5 | N42: 100.9 | O42: 100.5 | P42: 101.5 | Q42: 102.9 | R42: 100.5 | S42: 100.8 | T42: 101.3 | U42: 101.5 | V42: 100.4 | W42: 101 | X42: 100.4 | Y42: 100.8 | Z42: 100.5 | AA42: 100.5 | AB42: 102.8 | AC42: 104.8 | AD42: 100.4 | AE42: 100.5 | AF42: 100.5 | AG42: 100.7 | AH42: 100.4 | AI42: 100.4 | AJ42: 103 | AK42: 106.4 | AL42: 100.7 | AM42: 100.4 | AN42: 102.5 | AO42: 104.8 | AP42: 100.2 | AQ42: 100.4 | AR42: 101.8 | AS42: 103.6 | AT42: 100.4 | AU42: 100.5 | AV42: 101.4 | AW42: 102.6 | AX42: 100.2 | AY42: 100.4 | AZ42: 101.7 | BA42: 103.3 | BB42: 100.1 | BC42: 100.4 | BD42: 102 | BE42: 102.8 | BF42: 100.3 | BG42: 100.4 | BH42: 100.8 | BI42: 102.2 | BJ42: 99.8 | BK42: 100.1 | BL42: 100.9 | BM42: 101.5 | BN42: 100.4 | BO42: 100.5 | BP42: 100.3 | BQ42: 100.4 | BR42: 100.3 | BS42: 100.3 | BT42: 100.6 | BU42: 101 | BV42: 100.4 | BW42: 101.6 | BX42: 100.5 | BY42: 101.9 | BZ42: 100.5 | CA42: 100.3 | CB42: 101.4 | CC42: 102.8 | CD42: 100.5 | CE42: 100.2 | CF42: 101.7 | CG42: 102.7 | CH42: 100.9 | CI42: 100.3 | CJ42: 103.3 | CK42: 101.9 | CL42: 101
B43: Przeciętna miesięczna realna emerytura i renta brutto z pozarolniczego systemu ubezpieczeń społecznych | C43: A | D43: 100.4 | E43: 98.9 | F43: 95.2 | G43: 96.7 | H43: 99 | I43: 101.5 | J43: 108.5 | K43: 109.8 | L43: 110.1 | M43: 107.5 | N43: 100.8 | O43: 101.1 | P43: 102.9 | Q43: 105.3 | R43: 104.3 | S43: 103.9 | T43: 103.5 | U43: 100.4 | V43: 99 | W43: 99.5 | X43: 99.4 | Y43: 100 | Z43: 100.9 | AA43: 100.8 | AB43: 103.7 | AC43: 107.4 | AD43: 106.8 | AE43: 106.7 | AF43: 103.6 | AG43: 99.2 | AH43: 99.5 | AI43: 98.1 | AJ43: 99.8 | AK43: 105.2 | AL43: 105.2 | AM43: 105.9 | AN43: 105.7 | AO43: 103.7 | AP43: 103.6 | AQ43: 104.3 | AR43: 104.2 | AS43: 103.7 | AT43: 103.6 | AU43: 102.9 | AV43: 101.5 | AW43: 99.8 | AX43: 100.4 | AY43: 99.7 | AZ43: 100.6 | BA43: 101.2 | BB43: 101.2 | BC43: 102.2 | BD43: 104.2 | BE43: 104.7 | BF43: 104 | BG43: 104.5 | BH43: 103.4 | BI43: 103.4 | BJ43: 103.8 | BK43: 104 | BL43: 104.6 | BM43: 103.1 | BN43: 103.1 | BO43: 103.4 | BP43: 103.2 | BQ43: 102.3 | BR43: 102.2 | BS43: 101.3 | BT43: 99.8 | BU43: 100.2 | BV43: 100 | BW43: 100.8 | BX43: 101.5 | BY43: 102.6 | BZ43: 102.6 | CA43: 102 | CB43: 102.9 | CC43: 102.3 | CD43: 101.7 | CE43: 101.6 | CF43: 100.2 | CG43: 101.2 | CH43: 102 | CI43: 102.5 | CJ43: 104.5 | CK43: 102.4 | CL43: 101.3
C44: A1 | D44: 100.4 | E44: 99.5 | F44: 98.1 | G44: 97.7 | H44: 99 | I44: 100.3 | J44: 103 | K44: 104.7 | L44: 110.1 | M44: 108.8 | N44: 106 | O44: 104.6 | P44: 102.9 | Q44: 104.1 | R44: 104.2 | S44: 104.1 | T44: 103.5 | U44: 101.9 | V44: 101 | W44: 100.6 | X44: 99.4 | Y44: 99.7 | Z44: 100.1 | AA44: 100.3 | AB44: 103.7 | AC44: 105.5 | AD44: 106 | AE44: 106.2 | AF44: 103.6 | AG44: 101.4 | AH44: 100.8 | AI44: 100 | AJ44: 99.8 | AK44: 102.6 | AL44: 103.5 | AM44: 104.1 | AN44: 105.7 | AO44: 104.8 | AP44: 104.4 | AQ44: 104.3 | AR44: 104.2 | AS44: 104 | AT44: 103.9 | AU44: 103.6 | AV44: 101.5 | AW44: 100.7 | AX44: 100.6 | AY44: 100.4 | AZ44: 100.6 | BA44: 100.9 | BB44: 101.1 | BC44: 101.3 | BD44: 104.2 | BE44: 104.4 | BF44: 104.2 | BG44: 104.4 | BH44: 103.4 | BI44: 103.4 | BJ44: 103.5 | BK44: 103.6 | BL44: 104.6 | BM44: 103.7 | BN44: 103.6 | BO44: 103.5 | BP44: 103.2 | BQ44: 102.8 | BR44: 102.6 | BS44: 102.2 | BT44: 99.8 | BU44: 100 | BV44: 100 | BW44: 100.2 | BX44: 101.5 | BY44: 102 | BZ44: 102.3 | CA44: 102.1 | CB44: 102.9 | CC44: 101.6 | CD44: 102.3 | CE44: 102 | CF44: 100.2 | CG44: 100.7 | CH44: 101.2 | CI44: 101.5 | CJ44: 104.5 | CK44: 103.4 | CL44: 102.7
C45: B | D45: 96.6 | E45: 99.6 | F45: 101.9 | G45: 98.6 | H45: 98.8 | I45: 102.4 | J45: 108.9 | K45: 99.7 | L45: 99.1 | M45: 100 | N45: 102.1 | O45: 99.9 | P45: 100.8 | Q45: 102.4 | R45: 101.1 | S45: 99.6 | T45: 100.5 | U45: 99.3 | V45: 99.8 | W45: 100.1 | X45: 99.9 | Y45: 100.2 | Z45: 100.8 | AA45: 99.9 | AB45: 102.5 | AC45: 103.8 | AD45: 100.4 | AE45: 99.9 | AF45: 99.5 | AG45: 99.4 | AH45: 100.6 | AI45: 98.6 | AJ45: 101.1 | AK45: 104.8 | AL45: 100.6 | AM45: 99.3 | AN45: 100.7 | AO45: 102.8 | AP45: 100.5 | AQ45: 100.2 | AR45: 100.6 | AS45: 102.5 | AT45: 100.4 | AU45: 99.4 | AV45: 98.9 | AW45: 101.1 | AX45: 100.8 | AY45: 98.9 | AZ45: 99.7 | BA45: 101.9 | BB45: 100.7 | BC45: 100 | BD45: 101.6 | BE45: 102.3 | BF45: 100.2 | BG45: 100.3 | BH45: 100.4 | BI45: 102.4 | BJ45: 100.5 | BK45: 100.5 | BL45: 101 | BM45: 101 | BN45: 100.7 | BO45: 100.7 | BP45: 100.7 | BQ45: 100.1 | BR45: 100.7 | BS45: 99.7 | BT45: 99.2 | BU45: 100.6 | BV45: 100.5 | BW45: 100.4 | BX45: 99.9 | BY45: 101.6 | BZ45: 100.6 | CA45: 99.8 | CB45: 100.9 | CC45: 101.1 | CD45: 100 | CE45: 99.7 | CF45: 99.3 | CG45: 102 | CH45: 101 | CI45: 100.1 | CJ45: 101.1 | CK45: 100.2 | CL45: 100.1
B46: Przeciętna liczba emerytów i rencistów pobierających emerytury i renty rolników indywidualnych | C46: w tys. | D46: 1904.4 | E46: 1892.5 | F46: 1881.2 | G46: 1871 | H46: 1859.3 | I46: 1847.9 | J46: 1835.5 | K46: 1824.6 | L46: 1814 | M46: 1803.8 | N46: 1791.9 | O46: 1781.7 | P46: 1772.3 | Q46: 1760.3 | R46: 1748.9 | S46: 1739.7 | T46: 1730.2 | U46: 1718.8 | V46: 1701.5 | W46: 1684 | X46: 1669.8 | Y46: 1652.2 | Z46: 1635.4 | AA46: 1621.4 | AB46: 1609.8 | AC46: 1593.8 | AD46: 1576.7 | AE46: 1563.5 | AF46: 1551.2 | AG46: 1536.7 | AH46: 1522.6 | AI46: 1510.4 | AJ46: 1498.2 | AK46: 1483.8 | AL46: 1470.7 | AM46: 1459 | AN46: 1446.3 | AO46: 1432.1 | AP46: 1418.8 | AQ46: 1406 | AR46: 1393.5 | AS46: 1381.4 | AT46: 1368.4 | AU46: 1355.4 | AV46: 1343.5 | AW46: 1331.9 | AX46: 1320.8 | AY46: 1310.3 | AZ46: 1300.9 | BA46: 1290.6 | BB46: 1280.1 | BC46: 1271.1 | BD46: 1260.9 | BE46: 1249.8 | BF46: 1240.3 | BG46: 1231.8 | BH46: 1223.7 | BI46: 1215.6 | BJ46: 1207.1 | BK46: 1200 | BL46: 1198.1 | BM46: 1200.5 | BN46: 1208.9 | BO46: 1205.1 | BP46: 1200.9 | BQ46: 1195.8 | BR46: 1192 | BS46: 1189 | BT46: 1183.2 | BU46: 1177 | BV46: 1171 | BW46: 1170 | BX46: 1171.2 | BY46: 1163.1 | BZ46: 1152.4 | CA46: 1143 | CB46: 1133.7 | CC46: 1125 | CD46: 1116.6 | CE46: 1107.2 | CF46: 1096.3 | CG46: 1089.2 | CH46: 1079 | CI46: 1069.2 | CJ46: 1054 | CK46: 1041.1 | CL46: 1030.6
B47: Przeciętna miesięczna nominalna emerytura i renta rolników indywidualnych brutto | C47: w zł | D47: 585.32 | E47: 594.49 | F47: 612.82 | G47: 613.94 | H47: 624.21 | I47: 642.64 | J47: 695.43 | K47: 696.3 | L47: 696.98 | M47: 698.66 | N47: 702.02 | O47: 703.61 | P47: 712.02 | Q47: 730.32 | R47: 731.49 | S47: 734.39 | T47: 738.83 | U47: 748.16 | V47: 749.76 | W47: 752.42 | X47: 756,55c | Y47: 757,12c | Z47: 758,51c | AA47: 760,31c | AB47: 775.95 | AC47: 810.1 | AD47: 811.79 | AE47: 812.79 | AF47: 812.71 | AG47: 813.71 | AH47: 814.4 | AI47: 814.93 | AJ47: 829.98 | AK47: 866.94 | AL47: 867.3 | AM47: 867.93 | AN47: 884.67 | AO47: 919.79 | AP47: 919.84 | AQ47: 920.35 | AR47: 933.66 | AS47: 961.65 | AT47: 961.61 | AU47: 962.2 | AV47: 971.69 | AW47: 991.18 | AX47: 991.05 | AY47: 991.29 | AZ47: 1016.28 | BA47: 1067.75 | BB47: 1067.27 | BC47: 1067.73 | BD47: 1095.45 | BE47: 1129.99 | BF47: 1130.12 | BG47: 1130.97 | BH47: 1136.2 | BI47: 1147.26 | BJ47: 1146.75 | BK47: 1148.84 | BL47: 1161.39 | BM47: 1194.08 | BN47: 1182.47 | BO47: 1180.51 | BP47: 1180.88 | BQ47: 1184.86 | BR47: 1183.55 | BS47: 1182.05 | BT47: 1188.16 | BU47: 1202.26 | BV47: 1202.27 | BW47: 1207.44 | BX47: 1214.55 | BY47: 1229.31 | BZ47: 1231.7 | CA47: 1232.05 | CB47: 1255.76 | CC47: 1305.02 | CD47: 1303.39 | CE47: 1303.82 | CF47: 1335.68 | CG47: 1390.59 | CH47: 1391.68 | CI47: 1388.28 | CJ47: 1403.21 | CK47: 1438.43 | CL47: 1437.74
C48: A | D48: 109.6 | E48: 108.1 | F48: 105.1 | G48: 105.2 | H48: 106.6 | I48: 108.1 | J48: 113.5 | K48: 113.4 | L48: 111.7 | M48: 108.9 | N48: 101 | O48: 101 | P48: 102.2 | Q48: 104.5 | R48: 104.2 | S48: 104.8 | T48: 103.8 | U48: 102.4 | V48: 102.5 | W48: 102.5 | X48: 102.4 | Y48: 101.2 | Z48: 101.2 | AA48: 101 | AB48: 102.6 | AC48: 107 | AD48: 107 | AE48: 106.9 | AF48: 104.7 | AG48: 100.4 | AH48: 100.3 | AI48: 100.3 | AJ48: 102.1 | AK48: 106.5 | AL48: 106.5 | AM48: 106.5 | AN48: 106.6 | AO48: 106.1 | AP48: 106.1 | AQ48: 106 | AR48: 105.5 | AS48: 104.5 | AT48: 104.5 | AU48: 104.5 | AV48: 104.1 | AW48: 103.1 | AX48: 103.1 | AY48: 103 | AZ48: 104.6 | BA48: 107.7 | BB48: 107.7 | BC48: 107.7 | BD48: 107.8 | BE48: 105.8 | BF48: 105.9 | BG48: 105.9 | BH48: 103.7 | BI48: 101.5 | BJ48: 101.5 | BK48: 101.6 | BL48: 102.2 | BM48: 104.1 | BN48: 103.1 | BO48: 102.8 | BP48: 101.7 | BQ48: 99.2 | BR48: 100.1 | BS48: 100.1 | BT48: 100.6 | BU48: 101.5 | BV48: 101.6 | BW48: 102.1 | BX48: 102.2 | BY48: 102.3 | BZ48: 102.4 | CA48: 102 | CB48: 103.4 | CC48: 106.2 | CD48: 105.8 | CE48: 105.8 | CF48: 106.4 | CG48: 106.6 | CH48: 106.8 | CI48: 106.5 | CJ48: 105.1 | CK48: 103.4 | CL48: 103.3
C49: A1 | D49: 109.6 | E49: 108.8 | F49: 107.5 | G49: 106.9 | H49: 106.6 | I49: 107.3 | J49: 109.5 | K49: 110.4 | L49: 111.7 | M49: 110.2 | N49: 107 | O49: 105.4 | P49: 102.2 | Q49: 103.3 | R49: 103.6 | S49: 103.8 | T49: 103.8 | U49: 103.1 | V49: 103 | W49: 102.8 | X49: 102.4 | Y49: 101.8 | Z49: 101.6 | AA49: 101.5 | AB49: 102.6 | AC49: 104.8 | AD49: 105.5 | AE49: 105.9 | AF49: 104.7 | AG49: 102.6 | AH49: 101.8 | AI49: 101.4 | AJ49: 102.1 | AK49: 104.3 | AL49: 105 | AM49: 105.4 | AN49: 106.6 | AO49: 106.3 | AP49: 106.2 | AQ49: 106.2 | AR49: 105.5 | AS49: 105 | AT49: 104.9 | AU49: 104.8 | AV49: 104.1 | AW49: 103.6 | AX49: 103.4 | AY49: 103.3 | AZ49: 104.6 | BA49: 106.2 | BB49: 106.7 | BC49: 106.9 | BD49: 107.8 | BE49: 106.8 | BF49: 106.5 | BG49: 106.3 | BH49: 103.7 | BI49: 102.6 | BJ49: 102.2 | BK49: 102.1 | BL49: 102.2 | BM49: 103.2 | BN49: 103.1 | BO49: 103 | BP49: 101.7 | BQ49: 100.4 | BR49: 100.3 | BS49: 100.3 | BT49: 100.6 | BU49: 101 | BV49: 101.2 | BW49: 101.5 | BX49: 102.2 | BY49: 102.2 | BZ49: 102.3 | CA49: 102.2 | CB49: 103.4 | CC49: 104.8 | CD49: 105.1 | CE49: 105.3 | CF49: 106.4 | CG49: 106.5 | CH49: 106.6 | CI49: 106.5 | CJ49: 105.1 | CK49: 104.2 | CL49: 103.9
C50: B | D50: 100.2 | E50: 101.6 | F50: 103.1 | G50: 100.2 | H50: 101.7 | I50: 103 | J50: 108.2 | K50: 100.1 | L50: 100.1 | M50: 100.2 | N50: 100.5 | O50: 100.2 | P50: 101.2 | Q50: 102.6 | R50: 100.2 | S50: 100.4 | T50: 100.6 | U50: 101.3 | V50: 100.2 | W50: 100.4 | X50: 100.5 | Y50: 100.1 | Z50: 100.2 | AA50: 100.2 | AB50: 102.1 | AC50: 104.4 | AD50: 100.2 | AE50: 100.1 | AF50: 100 | AG50: 100.1 | AH50: 100.1 | AI50: 100.1 | AJ50: 101.8 | AK50: 104.5 | AL50: 100 | AM50: 100.1 | AN50: 101.9 | AO50: 104 | AP50: 100 | AQ50: 100.1 | AR50: 101.4 | AS50: 103 | AT50: 100 | AU50: 100.1 | AV50: 101 | AW50: 102 | AX50: 100 | AY50: 100 | AZ50: 102.5 | BA50: 105.1 | BB50: 100 | BC50: 100 | BD50: 102.6 | BE50: 103.2 | BF50: 100 | BG50: 100.1 | BH50: 100.5 | BI50: 101 | BJ50: 100 | BK50: 100.2 | BL50: 101.1 | BM50: 102.8 | BN50: 99 | BO50: 99.8 | BP50: 100 | BQ50: 100.3 | BR50: 99.9 | BS50: 99.9 | BT50: 100.5 | BU50: 101.2 | BV50: 100 | BW50: 100.4 | BX50: 100.6 | BY50: 101.2 | BZ50: 100.2 | CA50: 100 | CB50: 101.9 | CC50: 103.9 | CD50: 99.9 | CE50: 100 | CF50: 102.4 | CG50: 104.1 | CH50: 100.1 | CI50: 99.8 | CJ50: 101.1 | CK50: 102.5 | CL50: 100
B51: Przeciętna miesięczna realna emerytura i renta rolników indywidualnych brutto | C51: A | D51: 99.6 | E51: 98.4 | F51: 94.6 | G51: 96.2 | H51: 99.6 | I51: 100.8 | J51: 107.6 | K51: 108.7 | L51: 107.5 | M51: 106.3 | N51: 99.6 | O51: 99.9 | P51: 101.7 | Q51: 104 | R51: 103.1 | S51: 102.9 | T51: 101.9 | U51: 98.7 | V51: 97.6 | W51: 97.9 | X51: 98.6 | Y51: 98.7 | Z51: 99.5 | AA51: 99.7 | AB51: 101.8 | AC51: 105.7 | AD51: 105.1 | AE51: 104.9 | AF51: 102.1 | AG51: 99.7 | AH51: 97.9 | AI51: 96.4 | AJ51: 97.5 | AK51: 101.4 | AL51: 101 | AM51: 101.8 | AN51: 102.1 | AO51: 101.3 | AP51: 101.8 | AQ51: 102.3 | AR51: 102.4 | AS51: 102.2 | AT51: 101.9 | AU51: 101.1 | AV51: 99.7 | AW51: 98 | AX51: 98.7 | AY51: 98.1 | AZ51: 100.2 | BA51: 103.3 | BB51: 103.3 | BC51: 104.4 | BD51: 106.2 | BE51: 105.2 | BF51: 104.4 | BG51: 104.9 | BH51: 102.7 | BI51: 101.1 | BJ51: 101.9 | BK51: 102.5 | BL51: 103.7 | BM51: 104.8 | BN51: 103.3 | BO51: 103 | BP51: 102.2 | BQ51: 99.9 | BR51: 100.8 | BS51: 100 | BT51: 98.7 | BU51: 99.5 | BV51: 99.3 | BW51: 99.2 | BX51: 100.2 | BY51: 100.4 | BZ51: 100.5 | CA51: 100.8 | CB51: 102.2 | CC51: 103.5 | CD51: 102.5 | CE51: 102.5 | CF51: 101.2 | CG51: 102.5 | CH51: 103.2 | CI51: 103.2 | CJ51: 102.2 | CK51: 99.4 | CL51: 98.3
C52: A1 | D52: 99.6 | E52: 98.9 | F52: 97.5 | G52: 97.1 | H52: 99.6 | I52: 100.2 | J52: 102.7 | K52: 104.2 | L52: 107.5 | M52: 106.9 | N52: 104.4 | O52: 103.1 | P52: 101.7 | Q52: 102.8 | R52: 102.9 | S52: 102.8 | T52: 101.9 | U52: 100.3 | V52: 99.5 | W52: 99 | X52: 98.6 | Y52: 98.6 | Z52: 98.9 | AA52: 99.2 | AB52: 101.7 | AC52: 103.7 | AD52: 104.1 | AE52: 104.4 | AF52: 102.1 | AG52: 99.9 | AH52: 99.2 | AI52: 98.4 | AJ52: 97.5 | AK52: 99.4 | AL52: 100 | AM52: 100.5 | AN52: 102.1 | AO52: 101.7 | AP52: 101.7 | AQ52: 101.9 | AR52: 102.4 | AS52: 102.3 | AT52: 102.2 | AU52: 101.9 | AV52: 99.7 | AW52: 98.9 | AX52: 98.8 | AY52: 98.6 | AZ52: 100.2 | BA52: 101.7 | BB52: 102.3 | BC52: 102.8 | BD52: 106.2 | BE52: 105.6 | BF52: 105.2 | BG52: 105.1 | BH52: 102.7 | BI52: 101.9 | BJ52: 101.9 | BK52: 102.1 | BL52: 103.7 | BM52: 104.2 | BN52: 103.9 | BO52: 103.6 | BP52: 102.2 | BQ52: 101 | BR52: 100.9 | BS52: 100.7 | BT52: 98.7 | BU52: 99.1 | BV52: 99.1 | BW52: 99.2 | BX52: 100.2 | BY52: 100.2 | BZ52: 100.4 | CA52: 100.4 | CB52: 102.2 | CC52: 102.8 | CD52: 102.7 | CE52: 102.6 | CF52: 101.2 | CG52: 101.9 | CH52: 102.3 | CI52: 102.5 | CJ52: 102.2 | CK52: 100.8 | CL52: 99.9
C53: B | D53: 96.4 | E53: 99.6 | F53: 101.7 | G53: 98.4 | H53: 100 | I53: 101 | J53: 108.4 | K53: 99.4 | L53: 98.8 | M53: 99.7 | N53: 101.7 | O53: 99.6 | P53: 100.5 | Q53: 102.1 | R53: 100.8 | S53: 99.2 | T53: 99.8 | U53: 99.1 | V53: 99.6 | W53: 99.5 | X53: 100 | Y53: 99.5 | Z53: 100.5 | AA53: 99.6 | AB53: 101.8 | AC53: 103.4 | AD53: 100.2 | AE53: 99.5 | AF53: 99 | AG53: 98.8 | AH53: 100.3 | AI53: 98.3 | AJ53: 99.9 | AK53: 103 | AL53: 99.9 | AM53: 99 | AN53: 100.1 | AO53: 102.1 | AP53: 100.3 | AQ53: 99.9 | AR53: 100.2 | AS53: 101.9 | AT53: 100 | AU53: 99 | AV53: 98.5 | AW53: 100.5 | AX53: 100.6 | AY53: 98.5 | AZ53: 100.5 | BA53: 103.6 | BB53: 100.6 | BC53: 99.6 | BD53: 102.2 | BE53: 102.7 | BF53: 99.9 | BG53: 100 | BH53: 100.1 | BI53: 101.2 | BJ53: 100.7 | BK53: 100.6 | BL53: 101.2 | BM53: 102.3 | BN53: 99.3 | BO53: 100 | BP53: 100.4 | BQ53: 100 | BR53: 100.3 | BS53: 99.3 | BT53: 99.1 | BU53: 100.8 | BV53: 100.1 | BW53: 99.2 | BX53: 100 | BY53: 100.9 | BZ53: 100.3 | CA53: 99.5 | CB53: 101.4 | CC53: 102.2 | CD53: 99.4 | CE53: 99.5 | CF53: 100 | CG53: 103.4 | CH53: 100.2 | CI53: 99.6 | CJ53: 98.9 | CK53: 100.8 | CL53: 99.1
B55: a Dane dotyczą pełnej zbiorowości.
B56: b Dane obejmują podmioty gospodarcze o liczbie pracujących powyżej 9 osób.
B57: c Łącznie z jednorazową wypłatą dla osób pobierających świadczenie emerytalno-rentowe w kwocie nie wyższej niż kwota najniższej emerytury lub z renty z tytułu Ustawy z dnia 10 września 2004 r. o zmianie ustawy o emeryturach i rentach z FUS oraz o zmianie ustawy o ubezpieczeniu społecznym rolników (Dz. U. z 2004 r. Nr 236, poz. 2355).

Sheet Dane_Offset
A1: TABL. 48. PRODUKCJA SPRZEDANA PRZEMYSŁU SOLD PRODUCTION OF INDUSTRY
BI2: .
A3: Okresy Periods | B3: 1 | D3: 2 | F3: 3 | H3: 4 | J3: 5 | L3: 6 | N3: 7 | P3: 8 | R3: 9 | T3: 10 | V3: 11 | X3: 12 | Z3: 13 | AB3: 14 | AD3: 15 | AF3: 16 | AH3: 17 | AJ3: 18 | AL3: 19 | AN3: 20 | AP3: 21 | AR3: 22 | AT3: 23 | AV3: 24 | AX3: 25 | AZ3: 26 | BB3: 27 | BD3: 28 | BF3: 29 | BH3: 30
B4: Produkcja sprzedana przemysłu Sold production of industry
B5: Ogółem Grand total | D5: Górnictwo i wydobywanie Mining and quarrying | F5: wydobywanie węgla kamiennego i węgla brunatnego (lignitu) mining of coal and lignite | H5: Przetwórstwo przemysłowe Manufacturing | J5: produkcja artykułów spożywczych manufacture of food products | L5: produkcja napojów manufacture of beverages | N5: produkcja wyrobów tytoniowych manufacture of tobacco products | P5: produkcja wyrobów tekstylnych manufacture of textiles | R5: produkcja odzieży manufacture of wearing apparel | T5: produkcja skór i wyrobów skórzanych∆ manufacture of leather and related products | V5: produkcja wyrobów z drewna, korka, słomy i wikliny∆ manufacture of products of wood, cork, straw and wicker∆ | X5: produkcja papieru i wyrobów z papieru manufacture of paper and paper products | Z5: poligrafia i reprodukcja zapisanych nośników informacji printing and reproduction of recorded media | AB5: produkcja koksu i produktów rafinacji ropy naftowej∆ manufacture of coke and refined petroleum products | AD5: produkcja chemikaliów i wyrobów chemicznych manufacture of chemicals and chemical products | AF5: produkcja wyrobów farmaceuty-cznych∆ manufacture of pharmaceutical products∆ | AH5: produkcja wyrobów gumowych i z tworzyw sztucznych manufacture of rubber and plastic products | AJ5: produkcja wyrobów z pozostałych mineralnych surowców niemetalicznych manufacture of other non-metallic mineral products | AL5: produkcja metali manufacture of basic metals | AN5: produkcja wyrobów z metali∆ manufacture of metal products∆ | AP5: produkcja komputerów, wyrobów elektronicznych i optycznych manufacture of computer, electronic and optical products | AR5: produkcja urządzeń elektrycznych manufacture of electrical equipment | AT5: produkcja maszyn i urządzeń∆ manufacture of machinery and equipment | AV5: produkcja pojazdów samochodowych, przyczep i naczep∆ manufacture of motor vehicles, trailers and semi-trailers | AX5: produkcja pozostałego sprzętu transportowego manufacture of other transport equipment | AZ5: produkcja mebli manufacture of furniture | BB5: Wytwarzanie i zaopatrywanie w energię elektryczną, gaz, parę wodną i gorącą wodę∆ Electricity, gas, steam and air conditioning supply | BD5: Dostawa wody; gospodarowanie ściekami i odpadami; rekultywacja∆ Water supply; sewerage, waste management and remediation activities | BF5: pobór, uzdatnianie i dostarczanie wody water collection, treatment and supply | BH5: gospodarka odpadami; odzysk surowców∆ waste collection, treatment and disposal activities; materials recovery
B6: miliony PLN million PLN
A7: 2010 I | B7: 67008 | D7: 3123.5 | F7: 1952.3 | H7: 53435.6 | J7: 10545.7 | L7: 1041.7 | N7: 264.4 | P7: 519.9 | R7: 478.6 | T7: 172.8 | V7: 1457.6 | X7: 1778.2 | Z7: 577.4 | AB7: 3967.6 | AD7: 3031.3 | AF7: 886.6 | AH7: 3151.6 | AJ7: 1640.9 | AL7: 2399 | AN7: 3229.4 | AP7: 2878.2 | AR7: 2695.7 | AT7: 2579.3 | AV7: 6502.8 | AX7: 562.4 | AZ7: 1942.7 | BB7: 8923.6 | BD7: 1525.3 | BF7: 348.7 | BH7: 769.9
A8: 2010 II | B8: 68678.6 | D8: 3421.3 | F8: 2096.2 | H8: 55489.7 | J8: 10532.7 | L8: 1197.3 | N8: 266.2 | P8: 571.8 | R8: 495.5 | T8: 220.8 | V8: 1577 | X8: 1709.8 | Z8: 573 | AB8: 3886.1 | AD8: 2924.6 | AF8: 829 | AH8: 3323.3 | AJ8: 1885.8 | AL8: 2728 | AN8: 3334.1 | AP8: 2989.1 | AR8: 3032.6 | AT8: 2542.3 | AV8: 7058.3 | AX8: 623.6 | AZ8: 2036.9 | BB8: 8254.7 | BD8: 1512.9 | BF8: 394.9 | BH8: 736.1
A9: 2010 III | B9: 81494 | D9: 4170 | F9: 2252.3 | H9: 67369.8 | J9: 13023.2 | L9: 1613 | N9: 307.1 | P9: 671.3 | R9: 562.6 | T9: 260.3 | V9: 1917.3 | X9: 1969.9 | Z9: 683.2 | AB9: 5005.9 | AD9: 3779.4 | AF9: 1055.2 | AH9: 4108.7 | AJ9: 2930.6 | AL9: 2546.4 | AN9: 4242.4 | AP9: 2767.2 | AR9: 3555.9 | AT9: 3234.8 | AV9: 8402.5 | AX9: 1116 | AZ9: 2006.9 | BB9: 8269.7 | BD9: 1684.5 | BF9: 430.6 | BH9: 830.6
A10: 2010 IV | B10: 74673.4 | D10: 3969 | F10: 2007.9 | H10: 61939.4 | J10: 10900.3 | L10: 1476.9 | N10: 288.3 | P10: 582.1 | R10: 502.6 | T10: 220.9 | V10: 1836.7 | X10: 1836.6 | Z10: 635.7 | AB10: 4948.3 | AD10: 3698 | AF10: 856 | AH10: 3924.4 | AJ10: 3108.4 | AL10: 2849 | AN10: 3982.3 | AP10: 2979.6 | AR10: 3431.6 | AT10: 2559.2 | AV10: 7397.9 | AX10: 732.2 | AZ10: 1742.5 | BB10: 7040.1 | BD10: 1724.9 | BF10: 437.2 | BH10: 870.1
A11: 2010 V | B11: 76869 | D11: 3860.3 | F11: 1946.8 | H11: 64897.9 | J11: 11814.8 | L11: 1455.2 | N11: 229.5 | P11: 559.3 | R11: 466.8 | T11: 197.4 | V11: 1886.5 | X11: 1908.2 | Z11: 647 | AB11: 5305.6 | AD11: 4048.9 | AF11: 864.6 | AH11: 4061 | AJ11: 3239.2 | AL11: 2928.7 | AN11: 4249.4 | AP11: 3669 | AR11: 2773.4 | AT11: 2613.7 | AV11: 7863.3 | AX11: 757.6 | AZ11: 1778.6 | BB11: 6400.2 | BD11: 1710.7 | BF11: 432 | BH11: 858.4
A12: 2010 VI | B12: 82655 | D12: 4155.6 | F12: 2139.5 | H12: 70275.9 | J12: 12120.8 | L12: 1944.4 | N12: 238.5 | P12: 579.7 | R12: 491.5 | T12: 192.8 | V12: 1955.8 | X12: 2014.8 | Z12: 666.2 | AB12: 5553.7 | AD12: 4346.5 | AF12: 1094.7 | AH12: 4376.3 | AJ12: 3534.6 | AL12: 3059.7 | AN12: 4598.3 | AP12: 3736.8 | AR12: 2997.1 | AT12: 3157.7 | AV12: 9028 | AX12: 918.1 | AZ12: 1839.8 | BB12: 6437.5 | BD12: 1786 | BF12: 453.5 | BH12: 888.6
A13: 2010 VII | B13: 78608.2 | D13: 4312 | F13: 2361.7 | H13: 66276 | J13: 11849.2 | L13: 2158 | N13: 239.6 | P13: 528.1 | R13: 451.2 | T13: 179.7 | V13: 1855.7 | X13: 2011.8 | Z13: 643.8 | AB13: 5813.2 | AD13: 4062.8 | AF13: 956.2 | AH13: 4431.3 | AJ13: 3737.7 | AL13: 2851.8 | AN13: 4564.3 | AP13: 2848.7 | AR13: 2881.3 | AT13: 2765.5 | AV13: 7480.8 | AX13: 760.1 | AZ13: 1684.9 | BB13: 6300.9 | BD13: 1719.3 | BF13: 448.6 | BH13: 829.7
A14: 2010 VIII | B14: 77306.7 | D14: 4289.7 | F14: 2320.6 | H14: 64774.8 | J14: 12166 | L14: 1767.7 | N14: 246.8 | P14: 518.5 | R14: 517.5 | T14: 247.5 | V14: 1929.2 | X14: 1975.8 | Z14: 694.4 | AB14: 5948.5 | AD14: 4212.7 | AF14: 936.1 | AH14: 4189.9 | AJ14: 3777.2 | AL14: 2803.7 | AN14: 4683.5 | AP14: 2964 | AR14: 3035.5 | AT14: 2357.1 | AV14: 5261.7 | AX14: 828.5 | AZ14: 2058.5 | BB14: 6497.2 | BD14: 1744.9 | BF14: 457.1 | BH14: 850
A15: 2010 IX | B15: 86461.3 | D15: 4693.5 | F15: 2283.6 | H15: 73338.2 | J15: 12550.8 | L15: 1503.9 | N15: 233.6 | P15: 640.5 | R15: 620.4 | T15: 284.2 | V15: 2078 | X15: 2142 | Z15: 726 | AB15: 5903.6 | AD15: 4414.4 | AF15: 1184.3 | AH15: 4857.9 | AJ15: 4001.9 | AL15: 3089.2 | AN15: 5044.5 | AP15: 3493.7 | AR15: 3820.1 | AT15: 3202.2 | AV15: 8550.8 | AX15: 861.2 | AZ15: 2254.6 | BB15: 6602.9 | BD15: 1826.8 | BF15: 457.5 | BH15: 906.8
A16: 2010 X | B16: 85403.3 | D16: 4506.5 | F16: 2264.9 | H16: 71518.1 | J16: 13035 | L16: 1259.7 | N16: 260.3 | P16: 612.1 | R16: 575.4 | T16: 277.4 | V16: 2040.1 | X16: 2122.7 | Z16: 719.3 | AB16: 6198.3 | AD16: 3675.1 | AF16: 957.6 | AH16: 4805.9 | AJ16: 3897.2 | AL16: 3126.8 | AN16: 4954.2 | AP16: 3539.3 | AR16: 3848.7 | AT16: 2803.1 | AV16: 7968.1 | AX16: 702.6 | AZ16: 2208.4 | BB16: 7639.8 | BD16: 1738.9 | BF16: 449.1 | BH16: 860.1
A17: 2010 XI | B17: 84511 | D17: 4551.7 | F17: 2302.3 | H17: 70224 | J17: 13037.8 | L17: 1433.2 | N17: 238.2 | P17: 608.1 | R17: 532.9 | T17: 228.5 | V17: 1939.5 | X17: 2121.5 | Z17: 725.6 | AB17: 5934.8 | AD17: 3720.5 | AF17: 970.7 | AH17: 4612.5 | AJ17: 3411.7 | AL17: 2995 | AN17: 4863.2 | AP17: 3729.9 | AR17: 3564.9 | AT17: 2890.8 | AV17: 7901.7 | AX17: 681.3 | AZ17: 2227.8 | BB17: 7975.5 | BD17: 1759.8 | BF17: 442.9 | BH17: 879.7
A18: 2010 XII | B18: 82301.7 | D18: 4314.5 | F18: 1998.4 | H18: 66536.8 | J18: 12931 | L18: 1551.6 | N18: 236.1 | P18: 561.4 | R18: 576.9 | T18: 212.9 | V18: 1743.7 | X18: 1934.9 | Z18: 697.9 | AB18: 4875.8 | AD18: 3473.2 | AF18: 998.1 | AH18: 3826.7 | AJ18: 2423.5 | AL18: 2930.2 | AN18: 4586.7 | AP18: 3118.8 | AR18: 3350.4 | AT18: 3237.3 | AV18: 7329.1 | AX18: 1225.6 | AZ18: 2061.5 | BB18: 9474.7 | BD18: 1975.7 | BF18: 502.7 | BH18: 971.7
... A150: 2021 XII | B150: 176255.9 | D150: 5597.3 | F150: 2624.6 | H150: 146782.5 | J150: 26013.9 | L150: 2354.5 | N150: 644.6 | P150: 1412.1 | R150: 734.3 | T150: 308.7 | V150: 4231.1 | X150: 5386.7 | Z150: 1331.3 | AB150: 10016.8 | AD150: 8823.8 | AF150: 1139 | AH150: 9979.8 | AJ150: 6022.7 | AL150: 6995.8 | AN150: 12278.7 | AP150: 4990.8 | AR150: 9580.9 | AT150: 5138.4 | AV150: 14782.7 | AX150: 3389.2 | AZ150: 4966 | BB150: 19526 | BD150: 4350 | BF150: 778.9 | BH150: 2588
